Workbook

Sheet Guide
B1: A 10-Year Comparative Study on Performance of Sensex, Gold, and HDFC Flexi Cap Fund (2015–2024)
B2: Sensex (Equity Index) • Gold • HDFC Flexi Cap (Mutual Fund) | Jan-2015 to Dec-2024 | Built on daily returns
B4: What this workbook does
B5: Purpose | C5: Helps an investor compare three very different assets — an equity index, gold, and an actively-managed flexi-cap fund — and shows why blending them (diversification) can improve the risk-adjusted outcome. Everything is derived from DAILY price data, which is far more accurate than annual figures for risk metrics (volatility, drawdown, VaR, correlation).
B6: How to use it | C6: Change any input on the Assumptions sheet (allocation, risk-free rate, investment amounts). Every metric, chart-feed and table recalculates automatically. Then point Power BI / Excel charts at the 'Dashboard Data' and daily sheets.
B8: Sheet map
B9: Assumptions | C9: All editable inputs in one place — portfolio weights, risk-free rate, lumpsum & SIP amounts, annualisation factor, VaR confidence. Blue = you can change it.
B10: Daily Prices | C10: Cleaned, date-aligned daily levels for all three assets (only days when all three traded, so cross-asset stats are valid). This is the raw input — blue.
B11: Daily Returns | C11: Daily % change for each asset + the blended portfolio (constant-weight). The engine behind every risk statistic.
B12: Growth Index | C12: Growth of ₹100 and of your lumpsum, compounded daily. Feeds the 'growth' line chart.
B13: Drawdowns | C13: Running peak-to-trough loss for each asset & the portfolio. Feeds the 'underwater' chart — the most intuitive picture of risk.
B14: Rolling 1Y | C14: 252-day rolling annualised return, volatility, Sharpe, and rolling correlations — shows how risk & diversification change over time.
B15: Annual Returns | C15: Calendar-year returns per asset — source for the year-by-year bar/heatmap.
B16: Monthly Returns | C16: Month-by-month return matrix per asset — seasonality heatmap source.
B17: Correlation | C17: Daily-return correlation & covariance matrices — the statistical core of the diversification story.
B18: Metrics Summary | C18: The master scorecard: CAGR, volatility, Sharpe, Sortino, Calmar, max drawdown, VaR, CVaR, skew, kurtosis, beta, % positive days, best/worst day — per asset and for the blended portfolio.
B19: Investment Growth | C19: Lumpsum & SIP outcomes, including XIRR (money-weighted return) for a monthly SIP.
B20: Dashboard Data | C20: Tidy long-format tables (metrics & annual returns) ready to 'Get Data' straight into Power BI.
B22: Methodology notes
B23: • | C23: Alignment: only trading days on which ALL three assets have a real observation are kept (2,186 days). This avoids fake zero-return days and keeps correlations honest.
B24: • | C24: Daily simple returns are used for volatility, VaR, correlation and Sharpe (industry convention); geometric compounding is used for growth and CAGR.
B25: • | C25: The blended portfolio is constant-weight (daily-rebalanced) at the Assumptions weights, so its volatility correctly reflects diversification.
B26: • | C26: Annualisation uses the factor on the Assumptions sheet (252 by default). Sharpe/Sortino use the editable risk-free rate.
B27: • | C27: This is a research/education tool built from historical data. Past performance does not guarantee future results — it is not personalised investment advice.
B29: ⚠ Data-quality note (read before presenting)
B30: Sensex & Gold | C30: Daily series are clean — every daily metric (volatility, VaR, drawdown, correlation) is fully reliable.
B31: HDFC Flexi Cap | C31: The raw daily NAV feed contained 364 isolated bad values (spikes concentrated on month-boundary dates such as the 1st and 13th) that produced impossible single-day moves of 20-30%. These were repaired with a documented trend-median filter that preserves the fund's true trajectory and endpoints (its CAGR is unchanged). HDFC's CAGR, annual returns and growth figures are reliable; treat its day-level volatility / VaR as indicative and, for a publication-grade result, re-source clean daily NAV from AMFI.
B32: Why this matters | C32: A real equity fund should move closely with the equity index day-to-day. The raw HDFC feed did not — a red flag that the source, not the market, was the problem. Being upfront about this is exactly the kind of rigour that makes an investment-analysis project credible.
B34: Tip | C34: For a polished dashboard: use Growth Index for the hero line chart, Drawdowns for the underwater area chart, Correlation for a heatmap, Monthly Returns for a seasonality heatmap, and Metrics Summary cards for the KPI tiles.

Sheet Assumptions
B1: Assumptions & Parameters
B2: Change any blue value — the whole workbook recalculates. Yellow = key drivers.
B4: Investment & Risk Parameters
B5: Parameter | C5: Value | D5: Notes
B6: Lumpsum Investment (₹) | C6: 100000 | D6: One-time investment at the start of the period.
B7: SIP Monthly Amount (₹) | C7: 5000 | D7: Fixed amount invested every month across the period.
B8: Risk-Free Rate (annual) | C8: 0.065 | D8: Approx. 10-yr India G-Sec yield. Used for Sharpe / Sortino / Treynor.
B9: Annualisation Factor (days/yr) | C9: 252 | D9: Trading days per year used to annualise daily stats.
B10: VaR / CVaR Confidence | C10: 0.95 | D10: e.g. 0.95 = 95% one-day Value-at-Risk.
B12: Portfolio Allocation (constant-weight, daily-rebalanced)
B13: Asset Class | C13: Weight | D13: Notes
B14: Gold | C14: 0.4 | D14: Weights must sum to 100%.
B15: Sensex (Equity) | C15: 0.3
B16: HDFC Flexi Cap (Fund) | C16: 0.3
B17: Total | C17: =C14+C15+C16 -> 1 | D17: Should equal 100%.
B18: Weight check | C18: =IF(ROUND(C17,4)=1,"OK ✓","FIX — must total 100%") -> OK ✓

Sheet Metrics Summary
A1: Metrics Summary — master scorecard (daily-data based)
A2: Every figure is a live formula. Sharpe / Sortino / Treynor use the risk-free rate on Assumptions.
A3: Metric | B3: Sensex | C3: Gold | D3: HDFC Flexi Cap | E3: Portfolio
A4: PERFORMANCE
A5: Trading days observed | B5: =COUNT('Daily Returns'!B$4:B$2188) -> 2185 | C5: =COUNT('Daily Returns'!C$4:C$2188) -> 2185 | D5: =COUNT('Daily Returns'!D$4:D$2188) -> 2185 | E5: =COUNT('Daily Returns'!E$4:E$2188) -> 2185
A6: Years covered | B6: =('Daily Prices'!$A$2188-'Daily Prices'!$A$3)/365.25 -> 9.9986311 | C6: =('Daily Prices'!$A$2188-'Daily Prices'!$A$3)/365.25 -> 9.9986311 | D6: =('Daily Prices'!$A$2188-'Daily Prices'!$A$3)/365.25 -> 9.9986311 | E6: =('Daily Prices'!$A$2188-'Daily Prices'!$A$3)/365.25 -> 9.9986311
A7: Total return (cumulative) | B7: ='Growth Index'!B$2188/'Growth Index'!B$3-1 -> 1.8406397 | C7: ='Growth Index'!C$2188/'Growth Index'!C$3-1 -> 1.9224923 | D7: ='Growth Index'!D$2188/'Growth Index'!D$3-1 -> 3.2531413 | E7: ='Growth Index'!E$2188/'Growth Index'!E$3-1 -> 2.5293122
A8: CAGR (annualised) | B8: =('Growth Index'!B$2188/'Growth Index'!B$3)^(1/((('Daily Prices'!$A$2188-'Daily Prices'!$A$3)/365.25)))-1 -> 0.1100635 | C8: =('Growth Index'!C$2188/'Growth Index'!C$3)^(1/((('Daily Prices'!$A$2188-'Daily Prices'!$A$3)/365.25)))-1 -> 0.11322183 | D8: =('Growth Index'!D$2188/'Growth Index'!D$3)^(1/((('Daily Prices'!$A$2188-'Daily Prices'!$A$3)/365.25)))-1 -> 0.15579175 | E8: =('Growth Index'!E$2188/'Growth Index'!E$3)^(1/((('Daily Prices'!$A$2188-'Daily Prices'!$A$3)/365.25)))-1 -> 0.13442687
A9: Ann. return (arithmetic mean) | B9: =AVERAGE('Daily Returns'!B$4:B$2188)*Assumptions!$C$9 -> 0.1366159 | C9: =AVERAGE('Daily Returns'!C$4:C$2188)*Assumptions!$C$9 -> 0.13553013 | D9: =AVERAGE('Daily Returns'!D$4:D$2188)*Assumptions!$C$9 -> 0.18915122 | E9: =AVERAGE('Daily Returns'!E$4:E$2188)*Assumptions!$C$9 -> 0.15194219
A10: RISK
A11: Ann. volatility (std dev) | B11: =STDEV('Daily Returns'!B$4:B$2188)*SQRT(Assumptions!$C$9) -> 0.17923057 | C11: =STDEV('Daily Returns'!C$4:C$2188)*SQRT(Assumptions!$C$9) -> 0.15388333 | D11: =STDEV('Daily Returns'!D$4:D$2188)*SQRT(Assumptions!$C$9) -> 0.210804 | E11: =STDEV('Daily Returns'!E$4:E$2188)*SQRT(Assumptions!$C$9) -> 0.11355571
A12: Downside deviation (ann.) | B12: =SQRT(SUMPRODUCT(('Daily Returns'!B$4:B$2188<0)*('Daily Returns'!B$4:B$2188)^2)/COUNT('Daily Returns'!B$4:B$2188))*SQRT(Assumptions!$C$9) -> 0.12890835 | C12: =SQRT(SUMPRODUCT(('Daily Returns'!C$4:C$2188<0)*('Daily Returns'!C$4:C$2188)^2)/COUNT('Daily Returns'!C$4:C$2188))*SQRT(Assumptions!$C$9) -> 0.10221123 | D12: =SQRT(SUMPRODUCT(('Daily Returns'!D$4:D$2188<0)*('Daily Returns'!D$4:D$2188)^2)/COUNT('Daily Returns'!D$4:D$2188))*SQRT(Assumptions!$C$9) -> 0.1400823 | E12: =SQRT(SUMPRODUCT(('Daily Returns'!E$4:E$2188<0)*('Daily Returns'!E$4:E$2188)^2)/COUNT('Daily Returns'!E$4:E$2188))*SQRT(Assumptions!$C$9) -> 0.077258585
A13: Maximum drawdown | B13: =MIN(Drawdowns!B$3:B$2188) -> -0.38070057 | C13: =MIN(Drawdowns!C$3:C$2188) -> -0.20141514 | D13: =MIN(Drawdowns!D$3:D$2188) -> -0.36263947 | E13: =MIN(Drawdowns!E$3:E$2188) -> -0.22083249
A14: Best single day | B14: =MAX('Daily Returns'!B$4:B$2188) -> 0.083469761 | C14: =MAX('Daily Returns'!C$4:C$2188) -> 0.071344533 | D14: =MAX('Daily Returns'!D$4:D$2188) -> 0.087077166 | E14: =MAX('Daily Returns'!E$4:E$2188) -> 0.038247361
A15: Worst single day | B15: =MIN('Daily Returns'!B$4:B$2188) -> -0.13152578 | C15: =MIN('Daily Returns'!C$4:C$2188) -> -0.056991962 | D15: =MIN('Daily Returns'!D$4:D$2188) -> -0.076890051 | E15: =MIN('Daily Returns'!E$4:E$2188) -> -0.05822814
A16: Positive days | B16: =COUNTIF('Daily Returns'!B$4:B$2188,">0")/COUNT('Daily Returns'!B$4:B$2188) -> 0.53913043 | C16: =COUNTIF('Daily Returns'!C$4:C$2188,">0")/COUNT('Daily Returns'!C$4:C$2188) -> 0.50297483 | D16: =COUNTIF('Daily Returns'!D$4:D$2188,">0")/COUNT('Daily Returns'!D$4:D$2188) -> 0.54828375 | E16: =COUNTIF('Daily Returns'!E$4:E$2188,">0")/COUNT('Daily Returns'!E$4:E$2188) -> 0.54508009
A17: Skewness (daily) | B17: =SKEW('Daily Returns'!B$4:B$2188) -> -0.92196323 | C17: =SKEW('Daily Returns'!C$4:C$2188) -> 0.24129046 | D17: =SKEW('Daily Returns'!D$4:D$2188) -> 0.37183282 | E17: =SKEW('Daily Returns'!E$4:E$2188) -> -0.42133591
A18: Excess kurtosis (daily) | B18: =KURT('Daily Returns'!B$4:B$2188) -> 16.43674 | C18: =KURT('Daily Returns'!C$4:C$2188) -> 4.5321777 | D18: =KURT('Daily Returns'!D$4:D$2188) -> 5.5628952 | E18: =KURT('Daily Returns'!E$4:E$2188) -> 5.7345676
A19: 1-day VaR (historical) | B19: =PERCENTILE('Daily Returns'!B$4:B$2188,1-Assumptions!$C$10) -> -0.015596879 | C19: =PERCENTILE('Daily Returns'!C$4:C$2188,1-Assumptions!$C$10) -> -0.014509751 | D19: =PERCENTILE('Daily Returns'!D$4:D$2188,1-Assumptions!$C$10) -> -0.020420479 | E19: =PERCENTILE('Daily Returns'!E$4:E$2188,1-Assumptions!$C$10) -> -0.010336772
A20: 1-day CVaR / Expected Shortfall | B20: =AVERAGEIF('Daily Returns'!B$4:B$2188,"<="&B19) -> -0.026264095 | C20: =AVERAGEIF('Daily Returns'!C$4:C$2188,"<="&C19) -> -0.021526095 | D20: =AVERAGEIF('Daily Returns'!D$4:D$2188,"<="&D19) -> -0.029625092 | E20: =AVERAGEIF('Daily Returns'!E$4:E$2188,"<="&E19) -> -0.015673043
A21: RISK-ADJUSTED & MARKET
A22: Sharpe ratio | B22: =(B9-Assumptions!$C$8)/B11 -> 0.39957415 | C22: =(C9-Assumptions!$C$8)/C11 -> 0.4583351 | D22: =(D9-Assumptions!$C$8)/D11 -> 0.5889415 | E22: =(E9-Assumptions!$C$8)/E11 -> 0.76563468
A23: Sortino ratio | B23: =(B9-Assumptions!$C$8)/B12 -> 0.55555677 | C23: =(C9-Assumptions!$C$8)/C12 -> 0.69004287 | D23: =(D9-Assumptions!$C$8)/D12 -> 0.88627345 | E23: =(E9-Assumptions!$C$8)/E12 -> 1.1253402
A24: Calmar ratio | B24: =ABS(B8/B13) -> 0.28910779 | C24: =ABS(C8/C13) -> 0.56213168 | D24: =ABS(D8/D13) -> 0.42960504 | E24: =ABS(E8/E13) -> 0.60872779
A25: Beta (vs Sensex) | B25: =SLOPE('Daily Returns'!B$4:B$2188,'Daily Returns'!B$4:B$2188) -> 1 | C25: =SLOPE('Daily Returns'!C$4:C$2188,'Daily Returns'!B$4:B$2188) -> -0.06193432 | D25: =SLOPE('Daily Returns'!D$4:D$2188,'Daily Returns'!B$4:B$2188) -> 0.52533842 | E25: =SLOPE('Daily Returns'!E$4:E$2188,'Daily Returns'!B$4:B$2188) -> 0.4328278
A26: Treynor ratio | B26: =(B9-Assumptions!$C$8)/B25 -> 0.071615904 | C26: =(C9-Assumptions!$C$8)/C25 -> -1.1387892 | D26: =(D9-Assumptions!$C$8)/D25 -> 0.23632618 | E26: =(E9-Assumptions!$C$8)/E25 -> 0.20087016
A27: Correlation to Sensex | B27: =CORREL('Daily Returns'!B$4:B$2188,'Daily Returns'!B$4:B$2188) -> 1 | C27: =CORREL('Daily Returns'!C$4:C$2188,'Daily Returns'!B$4:B$2188) -> -0.072135972 | D27: =CORREL('Daily Returns'!D$4:D$2188,'Daily Returns'!B$4:B$2188) -> 0.44665522 | E27: =CORREL('Daily Returns'!E$4:E$2188,'Daily Returns'!B$4:B$2188) -> 0.68315344
A28: INVESTMENT OUTCOME
A29: Lumpsum final value | B29: =Assumptions!$C$6*(1+B7) -> 284063.97 | C29: =Assumptions!$C$6*(1+C7) -> 292249.23 | D29: =Assumptions!$C$6*(1+D7) -> 425314.13 | E29: =Assumptions!$C$6*(1+E7) -> 352931.22

Sheet Charts
A1: Charts — starter visuals (build your dashboard from here)
A2: Native Excel charts linked to the live data. Duplicate, restyle, or rebuild in Power BI as you like.
A40: Asset | B40: Volatility | C40: CAGR
A41: Sensex | B41: ='Metrics Summary'!B11 -> 0.17923057 | C41: ='Metrics Summary'!B8 -> 0.1100635
A42: Gold | B42: ='Metrics Summary'!C11 -> 0.15388333 | C42: ='Metrics Summary'!C8 -> 0.11322183
A43: HDFC Flexi Cap | B43: ='Metrics Summary'!D11 -> 0.210804 | C43: ='Metrics Summary'!D8 -> 0.15579175
A44: Portfolio | B44: ='Metrics Summary'!E11 -> 0.11355571 | C44: ='Metrics Summary'!E8 -> 0.13442687

Sheet Correlation
A1: Correlation & Covariance — the diversification engine
A2: Computed from daily simple returns. Low / negative correlation is what makes blending assets reduce risk.
A4: Correlation Matrix (daily returns)
B5: Sensex | C5: Gold | D5: HDFC Flexi Cap | E5: Portfolio
A6: Sensex | B6: =CORREL('Daily Returns'!B$4:B$2188,'Daily Returns'!B$4:B$2188) -> 1 | C6: =CORREL('Daily Returns'!B$4:B$2188,'Daily Returns'!C$4:C$2188) -> -0.072135972 | D6: =CORREL('Daily Returns'!B$4:B$2188,'Daily Returns'!D$4:D$2188) -> 0.44665522 | E6: =CORREL('Daily Returns'!B$4:B$2188,'Daily Returns'!E$4:E$2188) -> 0.68315344
A7: Gold | B7: =CORREL('Daily Returns'!C$4:C$2188,'Daily Returns'!B$4:B$2188) -> -0.072135972 | C7: =CORREL('Daily Returns'!C$4:C$2188,'Daily Returns'!C$4:C$2188) -> 1 | D7: =CORREL('Daily Returns'!C$4:C$2188,'Daily Returns'!D$4:D$2188) -> -0.044266172 | E7: =CORREL('Daily Returns'!C$4:C$2188,'Daily Returns'!E$4:E$2188) -> 0.4832447
A8: HDFC Flexi Cap | B8: =CORREL('Daily Returns'!D$4:D$2188,'Daily Returns'!B$4:B$2188) -> 0.44665522 | C8: =CORREL('Daily Returns'!D$4:D$2188,'Daily Returns'!C$4:C$2188) -> -0.044266172 | D8: =CORREL('Daily Returns'!D$4:D$2188,'Daily Returns'!D$4:D$2188) -> 1 | E8: =CORREL('Daily Returns'!D$4:D$2188,'Daily Returns'!E$4:E$2188) -> 0.74441654
A9: Portfolio | B9: =CORREL('Daily Returns'!E$4:E$2188,'Daily Returns'!B$4:B$2188) -> 0.68315344 | C9: =CORREL('Daily Returns'!E$4:E$2188,'Daily Returns'!C$4:C$2188) -> 0.4832447 | D9: =CORREL('Daily Returns'!E$4:E$2188,'Daily Returns'!D$4:D$2188) -> 0.74441654 | E9: =CORREL('Daily Returns'!E$4:E$2188,'Daily Returns'!E$4:E$2188) -> 1
A11: Annualised Covariance Matrix
B12: Sensex | C12: Gold | D12: HDFC Flexi Cap | E12: Portfolio
A13: Sensex | B13: =_xlfn.COVARIANCE.S('Daily Returns'!B$4:B$2188,'Daily Returns'!B$4:B$2188)*Assumptions!$C$9 -> 0.032123599 | C13: =_xlfn.COVARIANCE.S('Daily Returns'!B$4:B$2188,'Daily Returns'!C$4:C$2188)*Assumptions!$C$9 -> -0.0019895533 | D13: =_xlfn.COVARIANCE.S('Daily Returns'!B$4:B$2188,'Daily Returns'!D$4:D$2188)*Assumptions!$C$9 -> 0.016875761 | E13: =_xlfn.COVARIANCE.S('Daily Returns'!B$4:B$2188,'Daily Returns'!E$4:E$2188)*Assumptions!$C$9 -> 0.013903987
A14: Gold | B14: =_xlfn.COVARIANCE.S('Daily Returns'!C$4:C$2188,'Daily Returns'!B$4:B$2188)*Assumptions!$C$9 -> -0.0019895533 | C14: =_xlfn.COVARIANCE.S('Daily Returns'!C$4:C$2188,'Daily Returns'!C$4:C$2188)*Assumptions!$C$9 -> 0.02368008 | D14: =_xlfn.COVARIANCE.S('Daily Returns'!C$4:C$2188,'Daily Returns'!D$4:D$2188)*Assumptions!$C$9 -> -0.0014359601 | E14: =_xlfn.COVARIANCE.S('Daily Returns'!C$4:C$2188,'Daily Returns'!E$4:E$2188)*Assumptions!$C$9 -> 0.008444378
A15: HDFC Flexi Cap | B15: =_xlfn.COVARIANCE.S('Daily Returns'!D$4:D$2188,'Daily Returns'!B$4:B$2188)*Assumptions!$C$9 -> 0.016875761 | C15: =_xlfn.COVARIANCE.S('Daily Returns'!D$4:D$2188,'Daily Returns'!C$4:C$2188)*Assumptions!$C$9 -> -0.0014359601 | D15: =_xlfn.COVARIANCE.S('Daily Returns'!D$4:D$2188,'Daily Returns'!D$4:D$2188)*Assumptions!$C$9 -> 0.044438325 | E15: =_xlfn.COVARIANCE.S('Daily Returns'!D$4:D$2188,'Daily Returns'!E$4:E$2188)*Assumptions!$C$9 -> 0.017819842
A16: Portfolio | B16: =_xlfn.COVARIANCE.S('Daily Returns'!E$4:E$2188,'Daily Returns'!B$4:B$2188)*Assumptions!$C$9 -> 0.013903987 | C16: =_xlfn.COVARIANCE.S('Daily Returns'!E$4:E$2188,'Daily Returns'!C$4:C$2188)*Assumptions!$C$9 -> 0.008444378 | D16: =_xlfn.COVARIANCE.S('Daily Returns'!E$4:E$2188,'Daily Returns'!D$4:D$2188)*Assumptions!$C$9 -> 0.017819842 | E16: =_xlfn.COVARIANCE.S('Daily Returns'!E$4:E$2188,'Daily Returns'!E$4:E$2188)*Assumptions!$C$9 -> 0.0128949
A18: Diversification Benefit
A19: Weighted-avg volatility (no diversification) | B19: =Assumptions!$C$14*(STDEV('Daily Returns'!C$4:C$2188)*SQRT(Assumptions!$C$9))+Assumptions!$C$15*(STDEV('Daily Returns'!B$4:B$2188)*SQRT(Assumptions!$C$9))+Assumptions!$C$16*(STDEV('Daily Returns'!D$4:D$2188)*SQRT(Assumptions!$C$9)) -> 0.1785637
A20: Portfolio volatility (with diversification) | B20: =(STDEV('Daily Returns'!E$4:E$2188)*SQRT(Assumptions!$C$9)) -> 0.11355571
A21: Risk removed by diversification | B21: =(Assumptions!$C$14*(STDEV('Daily Returns'!C$4:C$2188)*SQRT(Assumptions!$C$9))+Assumptions!$C$15*(STDEV('Daily Returns'!B$4:B$2188)*SQRT(Assumptions!$C$9))+Assumptions!$C$16*(STDEV('Daily Returns'!D$4:D$2188)*SQRT(Assumptions!$C$9)))-(STDEV('Daily Returns'!E$4:E$2188)*SQRT(Assumptions!$C$9)) -> 0.065007993
A22: Diversification ratio | B22: =(Assumptions!$C$14*(STDEV('Daily Returns'!C$4:C$2188)*SQRT(Assumptions!$C$9))+Assumptions!$C$15*(STDEV('Daily Returns'!B$4:B$2188)*SQRT(Assumptions!$C$9))+Assumptions!$C$16*(STDEV('Daily Returns'!D$4:D$2188)*SQRT(Assumptions!$C$9)))/(STDEV('Daily Returns'!E$4:E$2188)*SQRT(Assumptions!$C$9)) -> 1.5724766

Sheet Annual Returns
A1: Calendar-Year Returns (from daily-compounded growth)
A2: Year | B2: Sensex | C2: Gold | D2: HDFC Flexi Cap | E2: Portfolio
A3: 2015 | B3: =IFERROR(LOOKUP(2,1/('Daily Prices'!$A$3:$A$2188<DATE(2016,1,1)),'Growth Index'!B$3:B$2188)/LOOKUP(2,1/('Daily Prices'!$A$3:$A$2188<DATE(2015,1,1)),'Growth Index'!B$3:B$2188)-1,LOOKUP(2,1/('Daily Prices'!$A$3:$A$2188<DATE(2016,1,1)),'Growth Index'!B$3:B$2188)/100-1) -> -0.0505316 | C3: =IFERROR(LOOKUP(2,1/('Daily Prices'!$A$3:$A$2188<DATE(2016,1,1)),'Growth Index'!C$3:C$2188)/LOOKUP(2,1/('Daily Prices'!$A$3:$A$2188<DATE(2015,1,1)),'Growth Index'!C$3:C$2188)-1,LOOKUP(2,1/('Daily Prices'!$A$3:$A$2188<DATE(2016,1,1)),'Growth Index'!C$3:C$2188)/100-1) -> -0.077097067 | D3: =IFERROR(LOOKUP(2,1/('Daily Prices'!$A$3:$A$2188<DATE(2016,1,1)),'Growth Index'!D$3:D$2188)/LOOKUP(2,1/('Daily Prices'!$A$3:$A$2188<DATE(2015,1,1)),'Growth Index'!D$3:D$2188)-1,LOOKUP(2,1/('Daily Prices'!$A$3:$A$2188<DATE(2016,1,1)),'Growth Index'!D$3:D$2188)/100-1) -> -0.046006423 | E3: =IFERROR(LOOKUP(2,1/('Daily Prices'!$A$3:$A$2188<DATE(2016,1,1)),'Growth Index'!E$3:E$2188)/LOOKUP(2,1/('Daily Prices'!$A$3:$A$2188<DATE(2015,1,1)),'Growth Index'!E$3:E$2188)-1,LOOKUP(2,1/('Daily Prices'!$A$3:$A$2188<DATE(2016,1,1)),'Growth Index'!E$3:E$2188)/100-1) -> -0.053078177
A4: 2016 | B4: =IFERROR(LOOKUP(2,1/('Daily Prices'!$A$3:$A$2188<DATE(2017,1,1)),'Growth Index'!B$3:B$2188)/LOOKUP(2,1/('Daily Prices'!$A$3:$A$2188<DATE(2016,1,1)),'Growth Index'!B$3:B$2188)-1,LOOKUP(2,1/('Daily Prices'!$A$3:$A$2188<DATE(2017,1,1)),'Growth Index'!B$3:B$2188)/100-1) -> 0.019485756 | C4: =IFERROR(LOOKUP(2,1/('Daily Prices'!$A$3:$A$2188<DATE(2017,1,1)),'Growth Index'!C$3:C$2188)/LOOKUP(2,1/('Daily Prices'!$A$3:$A$2188<DATE(2016,1,1)),'Growth Index'!C$3:C$2188)-1,LOOKUP(2,1/('Daily Prices'!$A$3:$A$2188<DATE(2017,1,1)),'Growth Index'!C$3:C$2188)/100-1) -> 0.10547275 | D4: =IFERROR(LOOKUP(2,1/('Daily Prices'!$A$3:$A$2188<DATE(2017,1,1)),'Growth Index'!D$3:D$2188)/LOOKUP(2,1/('Daily Prices'!$A$3:$A$2188<DATE(2016,1,1)),'Growth Index'!D$3:D$2188)-1,LOOKUP(2,1/('Daily Prices'!$A$3:$A$2188<DATE(2017,1,1)),'Growth Index'!D$3:D$2188)/100-1) -> 0.081613209 | E4: =IFERROR(LOOKUP(2,1/('Daily Prices'!$A$3:$A$2188<DATE(2017,1,1)),'Growth Index'!E$3:E$2188)/LOOKUP(2,1/('Daily Prices'!$A$3:$A$2188<DATE(2016,1,1)),'Growth Index'!E$3:E$2188)-1,LOOKUP(2,1/('Daily Prices'!$A$3:$A$2188<DATE(2017,1,1)),'Growth Index'!E$3:E$2188)/100-1) -> 0.082866022
A5: 2017 | B5: =IFERROR(LOOKUP(2,1/('Daily Prices'!$A$3:$A$2188<DATE(2018,1,1)),'Growth Index'!B$3:B$2188)/LOOKUP(2,1/('Daily Prices'!$A$3:$A$2188<DATE(2017,1,1)),'Growth Index'!B$3:B$2188)-1,LOOKUP(2,1/('Daily Prices'!$A$3:$A$2188<DATE(2018,1,1)),'Growth Index'!B$3:B$2188)/100-1) -> 0.27905963 | C5: =IFERROR(LOOKUP(2,1/('Daily Prices'!$A$3:$A$2188<DATE(2018,1,1)),'Growth Index'!C$3:C$2188)/LOOKUP(2,1/('Daily Prices'!$A$3:$A$2188<DATE(2017,1,1)),'Growth Index'!C$3:C$2188)-1,LOOKUP(2,1/('Daily Prices'!$A$3:$A$2188<DATE(2018,1,1)),'Growth Index'!C$3:C$2188)/100-1) -> 0.061998077 | D5: =IFERROR(LOOKUP(2,1/('Daily Prices'!$A$3:$A$2188<DATE(2018,1,1)),'Growth Index'!D$3:D$2188)/LOOKUP(2,1/('Daily Prices'!$A$3:$A$2188<DATE(2017,1,1)),'Growth Index'!D$3:D$2188)-1,LOOKUP(2,1/('Daily Prices'!$A$3:$A$2188<DATE(2018,1,1)),'Growth Index'!D$3:D$2188)/100-1) -> 0.38046724 | E5: =IFERROR(LOOKUP(2,1/('Daily Prices'!$A$3:$A$2188<DATE(2018,1,1)),'Growth Index'!E$3:E$2188)/LOOKUP(2,1/('Daily Prices'!$A$3:$A$2188<DATE(2017,1,1)),'Growth Index'!E$3:E$2188)-1,LOOKUP(2,1/('Daily Prices'!$A$3:$A$2188<DATE(2018,1,1)),'Growth Index'!E$3:E$2188)/100-1) -> 0.220447
A6: 2018 | B6: =IFERROR(LOOKUP(2,1/('Daily Prices'!$A$3:$A$2188<DATE(2019,1,1)),'Growth Index'!B$3:B$2188)/LOOKUP(2,1/('Daily Prices'!$A$3:$A$2188<DATE(2018,1,1)),'Growth Index'!B$3:B$2188)-1,LOOKUP(2,1/('Daily Prices'!$A$3:$A$2188<DATE(2019,1,1)),'Growth Index'!B$3:B$2188)/100-1) -> 0.059063043 | C6: =IFERROR(LOOKUP(2,1/('Daily Prices'!$A$3:$A$2188<DATE(2019,1,1)),'Growth Index'!C$3:C$2188)/LOOKUP(2,1/('Daily Prices'!$A$3:$A$2188<DATE(2018,1,1)),'Growth Index'!C$3:C$2188)-1,LOOKUP(2,1/('Daily Prices'!$A$3:$A$2188<DATE(2019,1,1)),'Growth Index'!C$3:C$2188)/100-1) -> 0.081192236 | D6: =IFERROR(LOOKUP(2,1/('Daily Prices'!$A$3:$A$2188<DATE(2019,1,1)),'Growth Index'!D$3:D$2188)/LOOKUP(2,1/('Daily Prices'!$A$3:$A$2188<DATE(2018,1,1)),'Growth Index'!D$3:D$2188)-1,LOOKUP(2,1/('Daily Prices'!$A$3:$A$2188<DATE(2019,1,1)),'Growth Index'!D$3:D$2188)/100-1) -> -0.026244201 | E6: =IFERROR(LOOKUP(2,1/('Daily Prices'!$A$3:$A$2188<DATE(2019,1,1)),'Growth Index'!E$3:E$2188)/LOOKUP(2,1/('Daily Prices'!$A$3:$A$2188<DATE(2018,1,1)),'Growth Index'!E$3:E$2188)-1,LOOKUP(2,1/('Daily Prices'!$A$3:$A$2188<DATE(2019,1,1)),'Growth Index'!E$3:E$2188)/100-1) -> 0.049746136
A7: 2019 | B7: =IFERROR(LOOKUP(2,1/('Daily Prices'!$A$3:$A$2188<DATE(2020,1,1)),'Growth Index'!B$3:B$2188)/LOOKUP(2,1/('Daily Prices'!$A$3:$A$2188<DATE(2019,1,1)),'Growth Index'!B$3:B$2188)-1,LOOKUP(2,1/('Daily Prices'!$A$3:$A$2188<DATE(2020,1,1)),'Growth Index'!B$3:B$2188)/100-1) -> 0.14376629 | C7: =IFERROR(LOOKUP(2,1/('Daily Prices'!$A$3:$A$2188<DATE(2020,1,1)),'Growth Index'!C$3:C$2188)/LOOKUP(2,1/('Daily Prices'!$A$3:$A$2188<DATE(2019,1,1)),'Growth Index'!C$3:C$2188)-1,LOOKUP(2,1/('Daily Prices'!$A$3:$A$2188<DATE(2020,1,1)),'Growth Index'!C$3:C$2188)/100-1) -> 0.20766113 | D7: =IFERROR(LOOKUP(2,1/('Daily Prices'!$A$3:$A$2188<DATE(2020,1,1)),'Growth Index'!D$3:D$2188)/LOOKUP(2,1/('Daily Prices'!$A$3:$A$2188<DATE(2019,1,1)),'Growth Index'!D$3:D$2188)-1,LOOKUP(2,1/('Daily Prices'!$A$3:$A$2188<DATE(2020,1,1)),'Growth Index'!D$3:D$2188)/100-1) -> 0.074331963 | E7: =IFERROR(LOOKUP(2,1/('Daily Prices'!$A$3:$A$2188<DATE(2020,1,1)),'Growth Index'!E$3:E$2188)/LOOKUP(2,1/('Daily Prices'!$A$3:$A$2188<DATE(2019,1,1)),'Growth Index'!E$3:E$2188)-1,LOOKUP(2,1/('Daily Prices'!$A$3:$A$2188<DATE(2020,1,1)),'Growth Index'!E$3:E$2188)/100-1) -> 0.15674905
A8: 2020 | B8: =IFERROR(LOOKUP(2,1/('Daily Prices'!$A$3:$A$2188<DATE(2021,1,1)),'Growth Index'!B$3:B$2188)/LOOKUP(2,1/('Daily Prices'!$A$3:$A$2188<DATE(2020,1,1)),'Growth Index'!B$3:B$2188)-1,LOOKUP(2,1/('Daily Prices'!$A$3:$A$2188<DATE(2021,1,1)),'Growth Index'!B$3:B$2188)/100-1) -> 0.15750305 | C8: =IFERROR(LOOKUP(2,1/('Daily Prices'!$A$3:$A$2188<DATE(2021,1,1)),'Growth Index'!C$3:C$2188)/LOOKUP(2,1/('Daily Prices'!$A$3:$A$2188<DATE(2020,1,1)),'Growth Index'!C$3:C$2188)-1,LOOKUP(2,1/('Daily Prices'!$A$3:$A$2188<DATE(2021,1,1)),'Growth Index'!C$3:C$2188)/100-1) -> 0.27914834 | D8: =IFERROR(LOOKUP(2,1/('Daily Prices'!$A$3:$A$2188<DATE(2021,1,1)),'Growth Index'!D$3:D$2188)/LOOKUP(2,1/('Daily Prices'!$A$3:$A$2188<DATE(2020,1,1)),'Growth Index'!D$3:D$2188)-1,LOOKUP(2,1/('Daily Prices'!$A$3:$A$2188<DATE(2021,1,1)),'Growth Index'!D$3:D$2188)/100-1) -> 0.070465251 | E8: =IFERROR(LOOKUP(2,1/('Daily Prices'!$A$3:$A$2188<DATE(2021,1,1)),'Growth Index'!E$3:E$2188)/LOOKUP(2,1/('Daily Prices'!$A$3:$A$2188<DATE(2020,1,1)),'Growth Index'!E$3:E$2188)-1,LOOKUP(2,1/('Daily Prices'!$A$3:$A$2188<DATE(2021,1,1)),'Growth Index'!E$3:E$2188)/100-1) -> 0.19649512
A9: 2021 | B9: =IFERROR(LOOKUP(2,1/('Daily Prices'!$A$3:$A$2188<DATE(2022,1,1)),'Growth Index'!B$3:B$2188)/LOOKUP(2,1/('Daily Prices'!$A$3:$A$2188<DATE(2021,1,1)),'Growth Index'!B$3:B$2188)-1,LOOKUP(2,1/('Daily Prices'!$A$3:$A$2188<DATE(2022,1,1)),'Growth Index'!B$3:B$2188)/100-1) -> 0.21994131 | C9: =IFERROR(LOOKUP(2,1/('Daily Prices'!$A$3:$A$2188<DATE(2022,1,1)),'Growth Index'!C$3:C$2188)/LOOKUP(2,1/('Daily Prices'!$A$3:$A$2188<DATE(2021,1,1)),'Growth Index'!C$3:C$2188)-1,LOOKUP(2,1/('Daily Prices'!$A$3:$A$2188<DATE(2022,1,1)),'Growth Index'!C$3:C$2188)/100-1) -> -0.02628293 | D9: =IFERROR(LOOKUP(2,1/('Daily Prices'!$A$3:$A$2188<DATE(2022,1,1)),'Growth Index'!D$3:D$2188)/LOOKUP(2,1/('Daily Prices'!$A$3:$A$2188<DATE(2021,1,1)),'Growth Index'!D$3:D$2188)-1,LOOKUP(2,1/('Daily Prices'!$A$3:$A$2188<DATE(2022,1,1)),'Growth Index'!D$3:D$2188)/100-1) -> 0.36996838 | E9: =IFERROR(LOOKUP(2,1/('Daily Prices'!$A$3:$A$2188<DATE(2022,1,1)),'Growth Index'!E$3:E$2188)/LOOKUP(2,1/('Daily Prices'!$A$3:$A$2188<DATE(2021,1,1)),'Growth Index'!E$3:E$2188)-1,LOOKUP(2,1/('Daily Prices'!$A$3:$A$2188<DATE(2022,1,1)),'Growth Index'!E$3:E$2188)/100-1) -> 0.16448467
A10: 2022 | B10: =IFERROR(LOOKUP(2,1/('Daily Prices'!$A$3:$A$2188<DATE(2023,1,1)),'Growth Index'!B$3:B$2188)/LOOKUP(2,1/('Daily Prices'!$A$3:$A$2188<DATE(2022,1,1)),'Growth Index'!B$3:B$2188)-1,LOOKUP(2,1/('Daily Prices'!$A$3:$A$2188<DATE(2023,1,1)),'Growth Index'!B$3:B$2188)/100-1) -> 0.044407732 | C10: =IFERROR(LOOKUP(2,1/('Daily Prices'!$A$3:$A$2188<DATE(2023,1,1)),'Growth Index'!C$3:C$2188)/LOOKUP(2,1/('Daily Prices'!$A$3:$A$2188<DATE(2022,1,1)),'Growth Index'!C$3:C$2188)-1,LOOKUP(2,1/('Daily Prices'!$A$3:$A$2188<DATE(2023,1,1)),'Growth Index'!C$3:C$2188)/100-1) -> 0.11710848 | D10: =IFERROR(LOOKUP(2,1/('Daily Prices'!$A$3:$A$2188<DATE(2023,1,1)),'Growth Index'!D$3:D$2188)/LOOKUP(2,1/('Daily Prices'!$A$3:$A$2188<DATE(2022,1,1)),'Growth Index'!D$3:D$2188)-1,LOOKUP(2,1/('Daily Prices'!$A$3:$A$2188<DATE(2023,1,1)),'Growth Index'!D$3:D$2188)/100-1) -> 0.19086224 | E10: =IFERROR(LOOKUP(2,1/('Daily Prices'!$A$3:$A$2188<DATE(2023,1,1)),'Growth Index'!E$3:E$2188)/LOOKUP(2,1/('Daily Prices'!$A$3:$A$2188<DATE(2022,1,1)),'Growth Index'!E$3:E$2188)-1,LOOKUP(2,1/('Daily Prices'!$A$3:$A$2188<DATE(2023,1,1)),'Growth Index'!E$3:E$2188)/100-1) -> 0.12693263
A11: 2023 | B11: =IFERROR(LOOKUP(2,1/('Daily Prices'!$A$3:$A$2188<DATE(2024,1,1)),'Growth Index'!B$3:B$2188)/LOOKUP(2,1/('Daily Prices'!$A$3:$A$2188<DATE(2023,1,1)),'Growth Index'!B$3:B$2188)-1,LOOKUP(2,1/('Daily Prices'!$A$3:$A$2188<DATE(2024,1,1)),'Growth Index'!B$3:B$2188)/100-1) -> 0.18736656 | C11: =IFERROR(LOOKUP(2,1/('Daily Prices'!$A$3:$A$2188<DATE(2024,1,1)),'Growth Index'!C$3:C$2188)/LOOKUP(2,1/('Daily Prices'!$A$3:$A$2188<DATE(2023,1,1)),'Growth Index'!C$3:C$2188)-1,LOOKUP(2,1/('Daily Prices'!$A$3:$A$2188<DATE(2024,1,1)),'Growth Index'!C$3:C$2188)/100-1) -> 0.1506805 | D11: =IFERROR(LOOKUP(2,1/('Daily Prices'!$A$3:$A$2188<DATE(2024,1,1)),'Growth Index'!D$3:D$2188)/LOOKUP(2,1/('Daily Prices'!$A$3:$A$2188<DATE(2023,1,1)),'Growth Index'!D$3:D$2188)-1,LOOKUP(2,1/('Daily Prices'!$A$3:$A$2188<DATE(2024,1,1)),'Growth Index'!D$3:D$2188)/100-1) -> 0.31452654 | E11: =IFERROR(LOOKUP(2,1/('Daily Prices'!$A$3:$A$2188<DATE(2024,1,1)),'Growth Index'!E$3:E$2188)/LOOKUP(2,1/('Daily Prices'!$A$3:$A$2188<DATE(2023,1,1)),'Growth Index'!E$3:E$2188)-1,LOOKUP(2,1/('Daily Prices'!$A$3:$A$2188<DATE(2024,1,1)),'Growth Index'!E$3:E$2188)/100-1) -> 0.21553019
A12: 2024 | B12: =IFERROR(LOOKUP(2,1/('Daily Prices'!$A$3:$A$2188<DATE(2025,1,1)),'Growth Index'!B$3:B$2188)/LOOKUP(2,1/('Daily Prices'!$A$3:$A$2188<DATE(2024,1,1)),'Growth Index'!B$3:B$2188)-1,LOOKUP(2,1/('Daily Prices'!$A$3:$A$2188<DATE(2025,1,1)),'Growth Index'!B$3:B$2188)/100-1) -> 0.081654606 | C12: =IFERROR(LOOKUP(2,1/('Daily Prices'!$A$3:$A$2188<DATE(2025,1,1)),'Growth Index'!C$3:C$2188)/LOOKUP(2,1/('Daily Prices'!$A$3:$A$2188<DATE(2024,1,1)),'Growth Index'!C$3:C$2188)-1,LOOKUP(2,1/('Daily Prices'!$A$3:$A$2188<DATE(2025,1,1)),'Growth Index'!C$3:C$2188)/100-1) -> 0.29024972 | D12: =IFERROR(LOOKUP(2,1/('Daily Prices'!$A$3:$A$2188<DATE(2025,1,1)),'Growth Index'!D$3:D$2188)/LOOKUP(2,1/('Daily Prices'!$A$3:$A$2188<DATE(2024,1,1)),'Growth Index'!D$3:D$2188)-1,LOOKUP(2,1/('Daily Prices'!$A$3:$A$2188<DATE(2025,1,1)),'Growth Index'!D$3:D$2188)/100-1) -> 0.24326503 | E12: =IFERROR(LOOKUP(2,1/('Daily Prices'!$A$3:$A$2188<DATE(2025,1,1)),'Growth Index'!E$3:E$2188)/LOOKUP(2,1/('Daily Prices'!$A$3:$A$2188<DATE(2024,1,1)),'Growth Index'!E$3:E$2188)-1,LOOKUP(2,1/('Daily Prices'!$A$3:$A$2188<DATE(2025,1,1)),'Growth Index'!E$3:E$2188)/100-1) -> 0.21688756
A13: CAGR | B13: =('Growth Index'!B$2188/'Growth Index'!B$3)^(365.25/('Daily Prices'!$A$2188-'Daily Prices'!$A$3))-1 -> 0.1100635 | C13: =('Growth Index'!C$2188/'Growth Index'!C$3)^(365.25/('Daily Prices'!$A$2188-'Daily Prices'!$A$3))-1 -> 0.11322183 | D13: =('Growth Index'!D$2188/'Growth Index'!D$3)^(365.25/('Daily Prices'!$A$2188-'Daily Prices'!$A$3))-1 -> 0.15579175 | E13: =('Growth Index'!E$2188/'Growth Index'!E$3)^(365.25/('Daily Prices'!$A$2188-'Daily Prices'!$A$3))-1 -> 0.13442687

Sheet Monthly Returns
A1: Monthly Returns — seasonality heatmap (one block per asset)
A3: Sensex
A4: Year | B4: Jan | C4: Feb | D4: Mar | E4: Apr | F4: May | G4: Jun | H4: Jul | I4: Aug | J4: Sep | K4: Oct | L4: Nov | M4: Dec | N4: Year
A5: 2015 | B5: =IFERROR(LOOKUP(2,1/('Daily Prices'!$A$3:$A$2188<DATE(2015,2,1)+0),'Growth Index'!B$3:B$2188)/LOOKUP(2,1/('Daily Prices'!$A$3:$A$2188<DATE(2015,1,1)),'Growth Index'!B$3:B$2188)-1,LOOKUP(2,1/('Daily Prices'!$A$3:$A$2188<DATE(2015,2,1)+0),'Growth Index'!B$3:B$2188)/100-1) -> 0.0609073 | C5: =IFERROR(LOOKUP(2,1/('Daily Prices'!$A$3:$A$2188<DATE(2015,3,1)+0),'Growth Index'!B$3:B$2188)/LOOKUP(2,1/('Daily Prices'!$A$3:$A$2188<DATE(2015,2,1)),'Growth Index'!B$3:B$2188)-1,LOOKUP(2,1/('Daily Prices'!$A$3:$A$2188<DATE(2015,3,1)+0),'Growth Index'!B$3:B$2188)/100-1) -> 0.0012736889 | D5: =IFERROR(LOOKUP(2,1/('Daily Prices'!$A$3:$A$2188<DATE(2015,4,1)+0),'Growth Index'!B$3:B$2188)/LOOKUP(2,1/('Daily Prices'!$A$3:$A$2188<DATE(2015,3,1)),'Growth Index'!B$3:B$2188)-1,LOOKUP(2,1/('Daily Prices'!$A$3:$A$2188<DATE(2015,4,1)+0),'Growth Index'!B$3:B$2188)/100-1) -> -0.043210979 | E5: =IFERROR(LOOKUP(2,1/('Daily Prices'!$A$3:$A$2188<DATE(2015,5,1)+0),'Growth Index'!B$3:B$2188)/LOOKUP(2,1/('Daily Prices'!$A$3:$A$2188<DATE(2015,4,1)),'Growth Index'!B$3:B$2188)-1,LOOKUP(2,1/('Daily Prices'!$A$3:$A$2188<DATE(2015,5,1)+0),'Growth Index'!B$3:B$2188)/100-1) -> -0.033843525 | F5: =IFERROR(LOOKUP(2,1/('Daily Prices'!$A$3:$A$2188<DATE(2015,6,1)+0),'Growth Index'!B$3:B$2188)/LOOKUP(2,1/('Daily Prices'!$A$3:$A$2188<DATE(2015,5,1)),'Growth Index'!B$3:B$2188)-1,LOOKUP(2,1/('Daily Prices'!$A$3:$A$2188<DATE(2015,6,1)+0),'Growth Index'!B$3:B$2188)/100-1) -> 0.030251402 | G5: =IFERROR(LOOKUP(2,1/('Daily Prices'!$A$3:$A$2188<DATE(2015,7,1)+0),'Growth Index'!B$3:B$2188)/LOOKUP(2,1/('Daily Prices'!$A$3:$A$2188<DATE(2015,6,1)),'Growth Index'!B$3:B$2188)-1,LOOKUP(2,1/('Daily Prices'!$A$3:$A$2188<DATE(2015,7,1)+0),'Growth Index'!B$3:B$2188)/100-1) -> -0.0017108397 | H5: =IFERROR(LOOKUP(2,1/('Daily Prices'!$A$3:$A$2188<DATE(2015,8,1)+0),'Growth Index'!B$3:B$2188)/LOOKUP(2,1/('Daily Prices'!$A$3:$A$2188<DATE(2015,7,1)),'Growth Index'!B$3:B$2188)-1,LOOKUP(2,1/('Daily Prices'!$A$3:$A$2188<DATE(2015,8,1)+0),'Growth Index'!B$3:B$2188)/100-1) -> 0.01201296 | I5: =IFERROR(LOOKUP(2,1/('Daily Prices'!$A$3:$A$2188<DATE(2015,9,1)+0),'Growth Index'!B$3:B$2188)/LOOKUP(2,1/('Daily Prices'!$A$3:$A$2188<DATE(2015,8,1)),'Growth Index'!B$3:B$2188)-1,LOOKUP(2,1/('Daily Prices'!$A$3:$A$2188<DATE(2015,9,1)+0),'Growth Index'!B$3:B$2188)/100-1) -> -0.065143114 | J5: =IFERROR(LOOKUP(2,1/('Daily Prices'!$A$3:$A$2188<DATE(2015,10,1)+0),'Growth Index'!B$3:B$2188)/LOOKUP(2,1/('Daily Prices'!$A$3:$A$2188<DATE(2015,9,1)),'Growth Index'!B$3:B$2188)-1,LOOKUP(2,1/('Daily Prices'!$A$3:$A$2188<DATE(2015,10,1)+0),'Growth Index'!B$3:B$2188)/100-1) -> -0.0048799437 | K5: =IFERROR(LOOKUP(2,1/('Daily Prices'!$A$3:$A$2188<DATE(2015,11,1)+0),'Growth Index'!B$3:B$2188)/LOOKUP(2,1/('Daily Prices'!$A$3:$A$2188<DATE(2015,10,1)),'Growth Index'!B$3:B$2188)-1,LOOKUP(2,1/('Daily Prices'!$A$3:$A$2188<DATE(2015,11,1)+0),'Growth Index'!B$3:B$2188)/100-1) -> 0.019193396 | L5: =IFERROR(LOOKUP(2,1/('Daily Prices'!$A$3:$A$2188<DATE(2015,12,1)+0),'Growth Index'!B$3:B$2188)/LOOKUP(2,1/('Daily Prices'!$A$3:$A$2188<DATE(2015,11,1)),'Growth Index'!B$3:B$2188)-1,LOOKUP(2,1/('Daily Prices'!$A$3:$A$2188<DATE(2015,12,1)+0),'Growth Index'!B$3:B$2188)/100-1) -> -0.019175573 | M5: =IFERROR(LOOKUP(2,1/('Daily Prices'!$A$3:$A$2188<DATE(2016,1,1)),'Growth Index'!B$3:B$2188)/LOOKUP(2,1/('Daily Prices'!$A$3:$A$2188<DATE(2015,12,1)),'Growth Index'!B$3:B$2188)-1,LOOKUP(2,1/('Daily Prices'!$A$3:$A$2188<DATE(2016,1,1)),'Growth Index'!B$3:B$2188)/100-1) -> -0.0010758952 | N5: =IFERROR(LOOKUP(2,1/('Daily Prices'!$A$3:$A$2188<DATE(2016,1,1)),'Growth Index'!B$3:B$2188)/LOOKUP(2,1/('Daily Prices'!$A$3:$A$2188<DATE(2015,1,1)),'Growth Index'!B$3:B$2188)-1,LOOKUP(2,1/('Daily Prices'!$A$3:$A$2188<DATE(2016,1,1)),'Growth Index'!B$3:B$2188)/100-1) -> -0.0505316
A6: 2016 | B6: =IFERROR(LOOKUP(2,1/('Daily Prices'!$A$3:$A$2188<DATE(2016,2,1)+0),'Growth Index'!B$3:B$2188)/LOOKUP(2,1/('Daily Prices'!$A$3:$A$2188<DATE(2016,1,1)),'Growth Index'!B$3:B$2188)-1,LOOKUP(2,1/('Daily Prices'!$A$3:$A$2188<DATE(2016,2,1)+0),'Growth Index'!B$3:B$2188)/100-1) -> -0.047739948 | C6: =IFERROR(LOOKUP(2,1/('Daily Prices'!$A$3:$A$2188<DATE(2016,3,1)+0),'Growth Index'!B$3:B$2188)/LOOKUP(2,1/('Daily Prices'!$A$3:$A$2188<DATE(2016,2,1)),'Growth Index'!B$3:B$2188)-1,LOOKUP(2,1/('Daily Prices'!$A$3:$A$2188<DATE(2016,3,1)+0),'Growth Index'!B$3:B$2188)/100-1) -> -0.075136235 | D6: =IFERROR(LOOKUP(2,1/('Daily Prices'!$A$3:$A$2188<DATE(2016,4,1)+0),'Growth Index'!B$3:B$2188)/LOOKUP(2,1/('Daily Prices'!$A$3:$A$2188<DATE(2016,3,1)),'Growth Index'!B$3:B$2188)-1,LOOKUP(2,1/('Daily Prices'!$A$3:$A$2188<DATE(2016,4,1)+0),'Growth Index'!B$3:B$2188)/100-1) -> 0.1017242 | E6: =IFERROR(LOOKUP(2,1/('Daily Prices'!$A$3:$A$2188<DATE(2016,5,1)+0),'Growth Index'!B$3:B$2188)/LOOKUP(2,1/('Daily Prices'!$A$3:$A$2188<DATE(2016,4,1)),'Growth Index'!B$3:B$2188)-1,LOOKUP(2,1/('Daily Prices'!$A$3:$A$2188<DATE(2016,5,1)+0),'Growth Index'!B$3:B$2188)/100-1) -> 0.010447536 | F6: =IFERROR(LOOKUP(2,1/('Daily Prices'!$A$3:$A$2188<DATE(2016,6,1)+0),'Growth Index'!B$3:B$2188)/LOOKUP(2,1/('Daily Prices'!$A$3:$A$2188<DATE(2016,5,1)),'Growth Index'!B$3:B$2188)-1,LOOKUP(2,1/('Daily Prices'!$A$3:$A$2188<DATE(2016,6,1)+0),'Growth Index'!B$3:B$2188)/100-1) -> 0.041447876 | G6: =IFERROR(LOOKUP(2,1/('Daily Prices'!$A$3:$A$2188<DATE(2016,7,1)+0),'Growth Index'!B$3:B$2188)/LOOKUP(2,1/('Daily Prices'!$A$3:$A$2188<DATE(2016,6,1)),'Growth Index'!B$3:B$2188)-1,LOOKUP(2,1/('Daily Prices'!$A$3:$A$2188<DATE(2016,7,1)+0),'Growth Index'!B$3:B$2188)/100-1) -> 0.012440397 | H6: =IFERROR(LOOKUP(2,1/('Daily Prices'!$A$3:$A$2188<DATE(2016,8,1)+0),'Growth Index'!B$3:B$2188)/LOOKUP(2,1/('Daily Prices'!$A$3:$A$2188<DATE(2016,7,1)),'Growth Index'!B$3:B$2188)-1,LOOKUP(2,1/('Daily Prices'!$A$3:$A$2188<DATE(2016,8,1)+0),'Growth Index'!B$3:B$2188)/100-1) -> 0.038968552 | I6: =IFERROR(LOOKUP(2,1/('Daily Prices'!$A$3:$A$2188<DATE(2016,9,1)+0),'Growth Index'!B$3:B$2188)/LOOKUP(2,1/('Daily Prices'!$A$3:$A$2188<DATE(2016,8,1)),'Growth Index'!B$3:B$2188)-1,LOOKUP(2,1/('Daily Prices'!$A$3:$A$2188<DATE(2016,9,1)+0),'Growth Index'!B$3:B$2188)/100-1) -> 0.014270355 | J6: =IFERROR(LOOKUP(2,1/('Daily Prices'!$A$3:$A$2188<DATE(2016,10,1)+0),'Growth Index'!B$3:B$2188)/LOOKUP(2,1/('Daily Prices'!$A$3:$A$2188<DATE(2016,9,1)),'Growth Index'!B$3:B$2188)-1,LOOKUP(2,1/('Daily Prices'!$A$3:$A$2188<DATE(2016,10,1)+0),'Growth Index'!B$3:B$2188)/100-1) -> -0.020603349 | K6: =IFERROR(LOOKUP(2,1/('Daily Prices'!$A$3:$A$2188<DATE(2016,11,1)+0),'Growth Index'!B$3:B$2188)/LOOKUP(2,1/('Daily Prices'!$A$3:$A$2188<DATE(2016,10,1)),'Growth Index'!B$3:B$2188)-1,LOOKUP(2,1/('Daily Prices'!$A$3:$A$2188<DATE(2016,11,1)+0),'Growth Index'!B$3:B$2188)/100-1) -> 0.0027111932 | L6: =IFERROR(LOOKUP(2,1/('Daily Prices'!$A$3:$A$2188<DATE(2016,12,1)+0),'Growth Index'!B$3:B$2188)/LOOKUP(2,1/('Daily Prices'!$A$3:$A$2188<DATE(2016,11,1)),'Growth Index'!B$3:B$2188)-1,LOOKUP(2,1/('Daily Prices'!$A$3:$A$2188<DATE(2016,12,1)+0),'Growth Index'!B$3:B$2188)/100-1) -> -0.046121344 | M6: =IFERROR(LOOKUP(2,1/('Daily Prices'!$A$3:$A$2188<DATE(2017,1,1)),'Growth Index'!B$3:B$2188)/LOOKUP(2,1/('Daily Prices'!$A$3:$A$2188<DATE(2016,12,1)),'Growth Index'!B$3:B$2188)-1,LOOKUP(2,1/('Daily Prices'!$A$3:$A$2188<DATE(2017,1,1)),'Growth Index'!B$3:B$2188)/100-1) -> -0.00098863872 | N6: =IFERROR(LOOKUP(2,1/('Daily Prices'!$A$3:$A$2188<DATE(2017,1,1)),'Growth Index'!B$3:B$2188)/LOOKUP(2,1/('Daily Prices'!$A$3:$A$2188<DATE(2016,1,1)),'Growth Index'!B$3:B$2188)-1,LOOKUP(2,1/('Daily Prices'!$A$3:$A$2188<DATE(2017,1,1)),'Growth Index'!B$3:B$2188)/100-1) -> 0.019485756
A7: 2017 | B7: =IFERROR(LOOKUP(2,1/('Daily Prices'!$A$3:$A$2188<DATE(2017,2,1)+0),'Growth Index'!B$3:B$2188)/LOOKUP(2,1/('Daily Prices'!$A$3:$A$2188<DATE(2017,1,1)),'Growth Index'!B$3:B$2188)-1,LOOKUP(2,1/('Daily Prices'!$A$3:$A$2188<DATE(2017,2,1)+0),'Growth Index'!B$3:B$2188)/100-1) -> 0.038664546 | C7: =IFERROR(LOOKUP(2,1/('Daily Prices'!$A$3:$A$2188<DATE(2017,3,1)+0),'Growth Index'!B$3:B$2188)/LOOKUP(2,1/('Daily Prices'!$A$3:$A$2188<DATE(2017,2,1)),'Growth Index'!B$3:B$2188)-1,LOOKUP(2,1/('Daily Prices'!$A$3:$A$2188<DATE(2017,3,1)+0),'Growth Index'!B$3:B$2188)/100-1) -> 0.039317384 | D7: =IFERROR(LOOKUP(2,1/('Daily Prices'!$A$3:$A$2188<DATE(2017,4,1)+0),'Growth Index'!B$3:B$2188)/LOOKUP(2,1/('Daily Prices'!$A$3:$A$2188<DATE(2017,3,1)),'Growth Index'!B$3:B$2188)-1,LOOKUP(2,1/('Daily Prices'!$A$3:$A$2188<DATE(2017,4,1)+0),'Growth Index'!B$3:B$2188)/100-1) -> 0.030517699 | E7: =IFERROR(LOOKUP(2,1/('Daily Prices'!$A$3:$A$2188<DATE(2017,5,1)+0),'Growth Index'!B$3:B$2188)/LOOKUP(2,1/('Daily Prices'!$A$3:$A$2188<DATE(2017,4,1)),'Growth Index'!B$3:B$2188)-1,LOOKUP(2,1/('Daily Prices'!$A$3:$A$2188<DATE(2017,5,1)+0),'Growth Index'!B$3:B$2188)/100-1) -> 0.010057224 | F7: =IFERROR(LOOKUP(2,1/('Daily Prices'!$A$3:$A$2188<DATE(2017,6,1)+0),'Growth Index'!B$3:B$2188)/LOOKUP(2,1/('Daily Prices'!$A$3:$A$2188<DATE(2017,5,1)),'Growth Index'!B$3:B$2188)-1,LOOKUP(2,1/('Daily Prices'!$A$3:$A$2188<DATE(2017,6,1)+0),'Growth Index'!B$3:B$2188)/100-1) -> 0.041024921 | G7: =IFERROR(LOOKUP(2,1/('Daily Prices'!$A$3:$A$2188<DATE(2017,7,1)+0),'Growth Index'!B$3:B$2188)/LOOKUP(2,1/('Daily Prices'!$A$3:$A$2188<DATE(2017,6,1)),'Growth Index'!B$3:B$2188)-1,LOOKUP(2,1/('Daily Prices'!$A$3:$A$2188<DATE(2017,7,1)+0),'Growth Index'!B$3:B$2188)/100-1) -> -0.0071980813 | H7: =IFERROR(LOOKUP(2,1/('Daily Prices'!$A$3:$A$2188<DATE(2017,8,1)+0),'Growth Index'!B$3:B$2188)/LOOKUP(2,1/('Daily Prices'!$A$3:$A$2188<DATE(2017,7,1)),'Growth Index'!B$3:B$2188)-1,LOOKUP(2,1/('Daily Prices'!$A$3:$A$2188<DATE(2017,8,1)+0),'Growth Index'!B$3:B$2188)/100-1) -> 0.051528041 | I7: =IFERROR(LOOKUP(2,1/('Daily Prices'!$A$3:$A$2188<DATE(2017,9,1)+0),'Growth Index'!B$3:B$2188)/LOOKUP(2,1/('Daily Prices'!$A$3:$A$2188<DATE(2017,8,1)),'Growth Index'!B$3:B$2188)-1,LOOKUP(2,1/('Daily Prices'!$A$3:$A$2188<DATE(2017,9,1)+0),'Growth Index'!B$3:B$2188)/100-1) -> -0.024125833 | J7: =IFERROR(LOOKUP(2,1/('Daily Prices'!$A$3:$A$2188<DATE(2017,10,1)+0),'Growth Index'!B$3:B$2188)/LOOKUP(2,1/('Daily Prices'!$A$3:$A$2188<DATE(2017,9,1)),'Growth Index'!B$3:B$2188)-1,LOOKUP(2,1/('Daily Prices'!$A$3:$A$2188<DATE(2017,10,1)+0),'Growth Index'!B$3:B$2188)/100-1) -> -0.014080148 | K7: =IFERROR(LOOKUP(2,1/('Daily Prices'!$A$3:$A$2188<DATE(2017,11,1)+0),'Growth Index'!B$3:B$2188)/LOOKUP(2,1/('Daily Prices'!$A$3:$A$2188<DATE(2017,10,1)),'Growth Index'!B$3:B$2188)-1,LOOKUP(2,1/('Daily Prices'!$A$3:$A$2188<DATE(2017,11,1)+0),'Growth Index'!B$3:B$2188)/100-1) -> 0.061674571 | L7: =IFERROR(LOOKUP(2,1/('Daily Prices'!$A$3:$A$2188<DATE(2017,12,1)+0),'Growth Index'!B$3:B$2188)/LOOKUP(2,1/('Daily Prices'!$A$3:$A$2188<DATE(2017,11,1)),'Growth Index'!B$3:B$2188)-1,LOOKUP(2,1/('Daily Prices'!$A$3:$A$2188<DATE(2017,12,1)+0),'Growth Index'!B$3:B$2188)/100-1) -> -0.0019203249 | M7: =IFERROR(LOOKUP(2,1/('Daily Prices'!$A$3:$A$2188<DATE(2018,1,1)),'Growth Index'!B$3:B$2188)/LOOKUP(2,1/('Daily Prices'!$A$3:$A$2188<DATE(2017,12,1)),'Growth Index'!B$3:B$2188)-1,LOOKUP(2,1/('Daily Prices'!$A$3:$A$2188<DATE(2018,1,1)),'Growth Index'!B$3:B$2188)/100-1) -> 0.027375499 | N7: =IFERROR(LOOKUP(2,1/('Daily Prices'!$A$3:$A$2188<DATE(2018,1,1)),'Growth Index'!B$3:B$2188)/LOOKUP(2,1/('Daily Prices'!$A$3:$A$2188<DATE(2017,1,1)),'Growth Index'!B$3:B$2188)-1,LOOKUP(2,1/('Daily Prices'!$A$3:$A$2188<DATE(2018,1,1)),'Growth Index'!B$3:B$2188)/100-1) -> 0.27905963
A8: 2018 | B8: =IFERROR(LOOKUP(2,1/('Daily Prices'!$A$3:$A$2188<DATE(2018,2,1)+0),'Growth Index'!B$3:B$2188)/LOOKUP(2,1/('Daily Prices'!$A$3:$A$2188<DATE(2018,1,1)),'Growth Index'!B$3:B$2188)-1,LOOKUP(2,1/('Daily Prices'!$A$3:$A$2188<DATE(2018,2,1)+0),'Growth Index'!B$3:B$2188)/100-1) -> 0.056029583 | C8: =IFERROR(LOOKUP(2,1/('Daily Prices'!$A$3:$A$2188<DATE(2018,3,1)+0),'Growth Index'!B$3:B$2188)/LOOKUP(2,1/('Daily Prices'!$A$3:$A$2188<DATE(2018,2,1)),'Growth Index'!B$3:B$2188)-1,LOOKUP(2,1/('Daily Prices'!$A$3:$A$2188<DATE(2018,3,1)+0),'Growth Index'!B$3:B$2188)/100-1) -> -0.049519783 | D8: =IFERROR(LOOKUP(2,1/('Daily Prices'!$A$3:$A$2188<DATE(2018,4,1)+0),'Growth Index'!B$3:B$2188)/LOOKUP(2,1/('Daily Prices'!$A$3:$A$2188<DATE(2018,3,1)),'Growth Index'!B$3:B$2188)-1,LOOKUP(2,1/('Daily Prices'!$A$3:$A$2188<DATE(2018,4,1)+0),'Growth Index'!B$3:B$2188)/100-1) -> -0.035553434 | E8: =IFERROR(LOOKUP(2,1/('Daily Prices'!$A$3:$A$2188<DATE(2018,5,1)+0),'Growth Index'!B$3:B$2188)/LOOKUP(2,1/('Daily Prices'!$A$3:$A$2188<DATE(2018,4,1)),'Growth Index'!B$3:B$2188)-1,LOOKUP(2,1/('Daily Prices'!$A$3:$A$2188<DATE(2018,5,1)+0),'Growth Index'!B$3:B$2188)/100-1) -> 0.066477639 | F8: =IFERROR(LOOKUP(2,1/('Daily Prices'!$A$3:$A$2188<DATE(2018,6,1)+0),'Growth Index'!B$3:B$2188)/LOOKUP(2,1/('Daily Prices'!$A$3:$A$2188<DATE(2018,5,1)),'Growth Index'!B$3:B$2188)-1,LOOKUP(2,1/('Daily Prices'!$A$3:$A$2188<DATE(2018,6,1)+0),'Growth Index'!B$3:B$2188)/100-1) -> 0.0046080302 | G8: =IFERROR(LOOKUP(2,1/('Daily Prices'!$A$3:$A$2188<DATE(2018,7,1)+0),'Growth Index'!B$3:B$2188)/LOOKUP(2,1/('Daily Prices'!$A$3:$A$2188<DATE(2018,6,1)),'Growth Index'!B$3:B$2188)-1,LOOKUP(2,1/('Daily Prices'!$A$3:$A$2188<DATE(2018,7,1)+0),'Growth Index'!B$3:B$2188)/100-1) -> 0.002862208 | H8: =IFERROR(LOOKUP(2,1/('Daily Prices'!$A$3:$A$2188<DATE(2018,8,1)+0),'Growth Index'!B$3:B$2188)/LOOKUP(2,1/('Daily Prices'!$A$3:$A$2188<DATE(2018,7,1)),'Growth Index'!B$3:B$2188)-1,LOOKUP(2,1/('Daily Prices'!$A$3:$A$2188<DATE(2018,8,1)+0),'Growth Index'!B$3:B$2188)/100-1) -> 0.061628615 | I8: =IFERROR(LOOKUP(2,1/('Daily Prices'!$A$3:$A$2188<DATE(2018,9,1)+0),'Growth Index'!B$3:B$2188)/LOOKUP(2,1/('Daily Prices'!$A$3:$A$2188<DATE(2018,8,1)),'Growth Index'!B$3:B$2188)-1,LOOKUP(2,1/('Daily Prices'!$A$3:$A$2188<DATE(2018,9,1)+0),'Growth Index'!B$3:B$2188)/100-1) -> 0.027614582 | J8: =IFERROR(LOOKUP(2,1/('Daily Prices'!$A$3:$A$2188<DATE(2018,10,1)+0),'Growth Index'!B$3:B$2188)/LOOKUP(2,1/('Daily Prices'!$A$3:$A$2188<DATE(2018,9,1)),'Growth Index'!B$3:B$2188)-1,LOOKUP(2,1/('Daily Prices'!$A$3:$A$2188<DATE(2018,10,1)+0),'Growth Index'!B$3:B$2188)/100-1) -> -0.062567619 | K8: =IFERROR(LOOKUP(2,1/('Daily Prices'!$A$3:$A$2188<DATE(2018,11,1)+0),'Growth Index'!B$3:B$2188)/LOOKUP(2,1/('Daily Prices'!$A$3:$A$2188<DATE(2018,10,1)),'Growth Index'!B$3:B$2188)-1,LOOKUP(2,1/('Daily Prices'!$A$3:$A$2188<DATE(2018,11,1)+0),'Growth Index'!B$3:B$2188)/100-1) -> -0.049274936 | L8: =IFERROR(LOOKUP(2,1/('Daily Prices'!$A$3:$A$2188<DATE(2018,12,1)+0),'Growth Index'!B$3:B$2188)/LOOKUP(2,1/('Daily Prices'!$A$3:$A$2188<DATE(2018,11,1)),'Growth Index'!B$3:B$2188)-1,LOOKUP(2,1/('Daily Prices'!$A$3:$A$2188<DATE(2018,12,1)+0),'Growth Index'!B$3:B$2188)/100-1) -> 0.050875311 | M8: =IFERROR(LOOKUP(2,1/('Daily Prices'!$A$3:$A$2188<DATE(2019,1,1)),'Growth Index'!B$3:B$2188)/LOOKUP(2,1/('Daily Prices'!$A$3:$A$2188<DATE(2018,12,1)),'Growth Index'!B$3:B$2188)-1,LOOKUP(2,1/('Daily Prices'!$A$3:$A$2188<DATE(2019,1,1)),'Growth Index'!B$3:B$2188)/100-1) -> -0.0034803823 | N8: =IFERROR(LOOKUP(2,1/('Daily Prices'!$A$3:$A$2188<DATE(2019,1,1)),'Growth Index'!B$3:B$2188)/LOOKUP(2,1/('Daily Prices'!$A$3:$A$2188<DATE(2018,1,1)),'Growth Index'!B$3:B$2188)-1,LOOKUP(2,1/('Daily Prices'!$A$3:$A$2188<DATE(2019,1,1)),'Growth Index'!B$3:B$2188)/100-1) -> 0.059063043
A9: 2019 | B9: =IFERROR(LOOKUP(2,1/('Daily Prices'!$A$3:$A$2188<DATE(2019,2,1)+0),'Growth Index'!B$3:B$2188)/LOOKUP(2,1/('Daily Prices'!$A$3:$A$2188<DATE(2019,1,1)),'Growth Index'!B$3:B$2188)-1,LOOKUP(2,1/('Daily Prices'!$A$3:$A$2188<DATE(2019,2,1)+0),'Growth Index'!B$3:B$2188)/100-1) -> 0.00522231 | C9: =IFERROR(LOOKUP(2,1/('Daily Prices'!$A$3:$A$2188<DATE(2019,3,1)+0),'Growth Index'!B$3:B$2188)/LOOKUP(2,1/('Daily Prices'!$A$3:$A$2188<DATE(2019,2,1)),'Growth Index'!B$3:B$2188)-1,LOOKUP(2,1/('Daily Prices'!$A$3:$A$2188<DATE(2019,3,1)+0),'Growth Index'!B$3:B$2188)/100-1) -> -0.01073595 | D9: =IFERROR(LOOKUP(2,1/('Daily Prices'!$A$3:$A$2188<DATE(2019,4,1)+0),'Growth Index'!B$3:B$2188)/LOOKUP(2,1/('Daily Prices'!$A$3:$A$2188<DATE(2019,3,1)),'Growth Index'!B$3:B$2188)-1,LOOKUP(2,1/('Daily Prices'!$A$3:$A$2188<DATE(2019,4,1)+0),'Growth Index'!B$3:B$2188)/100-1) -> 0.078217737 | E9: =IFERROR(LOOKUP(2,1/('Daily Prices'!$A$3:$A$2188<DATE(2019,5,1)+0),'Growth Index'!B$3:B$2188)/LOOKUP(2,1/('Daily Prices'!$A$3:$A$2188<DATE(2019,4,1)),'Growth Index'!B$3:B$2188)-1,LOOKUP(2,1/('Daily Prices'!$A$3:$A$2188<DATE(2019,5,1)+0),'Growth Index'!B$3:B$2188)/100-1) -> 0.009273675 | F9: =IFERROR(LOOKUP(2,1/('Daily Prices'!$A$3:$A$2188<DATE(2019,6,1)+0),'Growth Index'!B$3:B$2188)/LOOKUP(2,1/('Daily Prices'!$A$3:$A$2188<DATE(2019,5,1)),'Growth Index'!B$3:B$2188)-1,LOOKUP(2,1/('Daily Prices'!$A$3:$A$2188<DATE(2019,6,1)+0),'Growth Index'!B$3:B$2188)/100-1) -> 0.017489697 | G9: =IFERROR(LOOKUP(2,1/('Daily Prices'!$A$3:$A$2188<DATE(2019,7,1)+0),'Growth Index'!B$3:B$2188)/LOOKUP(2,1/('Daily Prices'!$A$3:$A$2188<DATE(2019,6,1)),'Growth Index'!B$3:B$2188)-1,LOOKUP(2,1/('Daily Prices'!$A$3:$A$2188<DATE(2019,7,1)+0),'Growth Index'!B$3:B$2188)/100-1) -> -0.0080464922 | H9: =IFERROR(LOOKUP(2,1/('Daily Prices'!$A$3:$A$2188<DATE(2019,8,1)+0),'Growth Index'!B$3:B$2188)/LOOKUP(2,1/('Daily Prices'!$A$3:$A$2188<DATE(2019,7,1)),'Growth Index'!B$3:B$2188)-1,LOOKUP(2,1/('Daily Prices'!$A$3:$A$2188<DATE(2019,8,1)+0),'Growth Index'!B$3:B$2188)/100-1) -> -0.048573105 | I9: =IFERROR(LOOKUP(2,1/('Daily Prices'!$A$3:$A$2188<DATE(2019,9,1)+0),'Growth Index'!B$3:B$2188)/LOOKUP(2,1/('Daily Prices'!$A$3:$A$2188<DATE(2019,8,1)),'Growth Index'!B$3:B$2188)-1,LOOKUP(2,1/('Daily Prices'!$A$3:$A$2188<DATE(2019,9,1)+0),'Growth Index'!B$3:B$2188)/100-1) -> -0.0039574591 | J9: =IFERROR(LOOKUP(2,1/('Daily Prices'!$A$3:$A$2188<DATE(2019,10,1)+0),'Growth Index'!B$3:B$2188)/LOOKUP(2,1/('Daily Prices'!$A$3:$A$2188<DATE(2019,9,1)),'Growth Index'!B$3:B$2188)-1,LOOKUP(2,1/('Daily Prices'!$A$3:$A$2188<DATE(2019,10,1)+0),'Growth Index'!B$3:B$2188)/100-1) -> 0.035747127 | K9: =IFERROR(LOOKUP(2,1/('Daily Prices'!$A$3:$A$2188<DATE(2019,11,1)+0),'Growth Index'!B$3:B$2188)/LOOKUP(2,1/('Daily Prices'!$A$3:$A$2188<DATE(2019,10,1)),'Growth Index'!B$3:B$2188)-1,LOOKUP(2,1/('Daily Prices'!$A$3:$A$2188<DATE(2019,11,1)+0),'Growth Index'!B$3:B$2188)/100-1) -> 0.037802455 | L9: =IFERROR(LOOKUP(2,1/('Daily Prices'!$A$3:$A$2188<DATE(2019,12,1)+0),'Growth Index'!B$3:B$2188)/LOOKUP(2,1/('Daily Prices'!$A$3:$A$2188<DATE(2019,11,1)),'Growth Index'!B$3:B$2188)-1,LOOKUP(2,1/('Daily Prices'!$A$3:$A$2188<DATE(2019,12,1)+0),'Growth Index'!B$3:B$2188)/100-1) -> 0.016565555 | M9: =IFERROR(LOOKUP(2,1/('Daily Prices'!$A$3:$A$2188<DATE(2020,1,1)),'Growth Index'!B$3:B$2188)/LOOKUP(2,1/('Daily Prices'!$A$3:$A$2188<DATE(2019,12,1)),'Growth Index'!B$3:B$2188)-1,LOOKUP(2,1/('Daily Prices'!$A$3:$A$2188<DATE(2020,1,1)),'Growth Index'!B$3:B$2188)/100-1) -> 0.011274505 | N9: =IFERROR(LOOKUP(2,1/('Daily Prices'!$A$3:$A$2188<DATE(2020,1,1)),'Growth Index'!B$3:B$2188)/LOOKUP(2,1/('Daily Prices'!$A$3:$A$2188<DATE(2019,1,1)),'Growth Index'!B$3:B$2188)-1,LOOKUP(2,1/('Daily Prices'!$A$3:$A$2188<DATE(2020,1,1)),'Growth Index'!B$3:B$2188)/100-1) -> 0.14376629
A10: 2020 | B10: =IFERROR(LOOKUP(2,1/('Daily Prices'!$A$3:$A$2188<DATE(2020,2,1)+0),'Growth Index'!B$3:B$2188)/LOOKUP(2,1/('Daily Prices'!$A$3:$A$2188<DATE(2020,1,1)),'Growth Index'!B$3:B$2188)-1,LOOKUP(2,1/('Daily Prices'!$A$3:$A$2188<DATE(2020,2,1)+0),'Growth Index'!B$3:B$2188)/100-1) -> -0.01285338 | C10: =IFERROR(LOOKUP(2,1/('Daily Prices'!$A$3:$A$2188<DATE(2020,3,1)+0),'Growth Index'!B$3:B$2188)/LOOKUP(2,1/('Daily Prices'!$A$3:$A$2188<DATE(2020,2,1)),'Growth Index'!B$3:B$2188)-1,LOOKUP(2,1/('Daily Prices'!$A$3:$A$2188<DATE(2020,3,1)+0),'Growth Index'!B$3:B$2188)/100-1) -> -0.059577409 | D10: =IFERROR(LOOKUP(2,1/('Daily Prices'!$A$3:$A$2188<DATE(2020,4,1)+0),'Growth Index'!B$3:B$2188)/LOOKUP(2,1/('Daily Prices'!$A$3:$A$2188<DATE(2020,3,1)),'Growth Index'!B$3:B$2188)-1,LOOKUP(2,1/('Daily Prices'!$A$3:$A$2188<DATE(2020,4,1)+0),'Growth Index'!B$3:B$2188)/100-1) -> -0.23053328 | E10: =IFERROR(LOOKUP(2,1/('Daily Prices'!$A$3:$A$2188<DATE(2020,5,1)+0),'Growth Index'!B$3:B$2188)/LOOKUP(2,1/('Daily Prices'!$A$3:$A$2188<DATE(2020,4,1)),'Growth Index'!B$3:B$2188)-1,LOOKUP(2,1/('Daily Prices'!$A$3:$A$2188<DATE(2020,5,1)+0),'Growth Index'!B$3:B$2188)/100-1) -> 0.14419232 | F10: =IFERROR(LOOKUP(2,1/('Daily Prices'!$A$3:$A$2188<DATE(2020,6,1)+0),'Growth Index'!B$3:B$2188)/LOOKUP(2,1/('Daily Prices'!$A$3:$A$2188<DATE(2020,5,1)),'Growth Index'!B$3:B$2188)-1,LOOKUP(2,1/('Daily Prices'!$A$3:$A$2188<DATE(2020,6,1)+0),'Growth Index'!B$3:B$2188)/100-1) -> -0.038363325 | G10: =IFERROR(LOOKUP(2,1/('Daily Prices'!$A$3:$A$2188<DATE(2020,7,1)+0),'Growth Index'!B$3:B$2188)/LOOKUP(2,1/('Daily Prices'!$A$3:$A$2188<DATE(2020,6,1)),'Growth Index'!B$3:B$2188)-1,LOOKUP(2,1/('Daily Prices'!$A$3:$A$2188<DATE(2020,7,1)+0),'Growth Index'!B$3:B$2188)/100-1) -> 0.07684716 | H10: =IFERROR(LOOKUP(2,1/('Daily Prices'!$A$3:$A$2188<DATE(2020,8,1)+0),'Growth Index'!B$3:B$2188)/LOOKUP(2,1/('Daily Prices'!$A$3:$A$2188<DATE(2020,7,1)),'Growth Index'!B$3:B$2188)-1,LOOKUP(2,1/('Daily Prices'!$A$3:$A$2188<DATE(2020,8,1)+0),'Growth Index'!B$3:B$2188)/100-1) -> 0.077073703 | I10: =IFERROR(LOOKUP(2,1/('Daily Prices'!$A$3:$A$2188<DATE(2020,9,1)+0),'Growth Index'!B$3:B$2188)/LOOKUP(2,1/('Daily Prices'!$A$3:$A$2188<DATE(2020,8,1)),'Growth Index'!B$3:B$2188)-1,LOOKUP(2,1/('Daily Prices'!$A$3:$A$2188<DATE(2020,9,1)+0),'Growth Index'!B$3:B$2188)/100-1) -> 0.027159917 | J10: =IFERROR(LOOKUP(2,1/('Daily Prices'!$A$3:$A$2188<DATE(2020,10,1)+0),'Growth Index'!B$3:B$2188)/LOOKUP(2,1/('Daily Prices'!$A$3:$A$2188<DATE(2020,9,1)),'Growth Index'!B$3:B$2188)-1,LOOKUP(2,1/('Daily Prices'!$A$3:$A$2188<DATE(2020,10,1)+0),'Growth Index'!B$3:B$2188)/100-1) -> -0.014506467 | K10: =IFERROR(LOOKUP(2,1/('Daily Prices'!$A$3:$A$2188<DATE(2020,11,1)+0),'Growth Index'!B$3:B$2188)/LOOKUP(2,1/('Daily Prices'!$A$3:$A$2188<DATE(2020,10,1)),'Growth Index'!B$3:B$2188)-1,LOOKUP(2,1/('Daily Prices'!$A$3:$A$2188<DATE(2020,11,1)+0),'Growth Index'!B$3:B$2188)/100-1) -> 0.04061529 | L10: =IFERROR(LOOKUP(2,1/('Daily Prices'!$A$3:$A$2188<DATE(2020,12,1)+0),'Growth Index'!B$3:B$2188)/LOOKUP(2,1/('Daily Prices'!$A$3:$A$2188<DATE(2020,11,1)),'Growth Index'!B$3:B$2188)-1,LOOKUP(2,1/('Daily Prices'!$A$3:$A$2188<DATE(2020,12,1)+0),'Growth Index'!B$3:B$2188)/100-1) -> 0.11449594 | M10: =IFERROR(LOOKUP(2,1/('Daily Prices'!$A$3:$A$2188<DATE(2021,1,1)),'Growth Index'!B$3:B$2188)/LOOKUP(2,1/('Daily Prices'!$A$3:$A$2188<DATE(2020,12,1)),'Growth Index'!B$3:B$2188)-1,LOOKUP(2,1/('Daily Prices'!$A$3:$A$2188<DATE(2021,1,1)),'Growth Index'!B$3:B$2188)/100-1) -> 0.081577188 | N10: =IFERROR(LOOKUP(2,1/('Daily Prices'!$A$3:$A$2188<DATE(2021,1,1)),'Growth Index'!B$3:B$2188)/LOOKUP(2,1/('Daily Prices'!$A$3:$A$2188<DATE(2020,1,1)),'Growth Index'!B$3:B$2188)-1,LOOKUP(2,1/('Daily Prices'!$A$3:$A$2188<DATE(2021,1,1)),'Growth Index'!B$3:B$2188)/100-1) -> 0.15750305
A11: 2021 | B11: =IFERROR(LOOKUP(2,1/('Daily Prices'!$A$3:$A$2188<DATE(2021,2,1)+0),'Growth Index'!B$3:B$2188)/LOOKUP(2,1/('Daily Prices'!$A$3:$A$2188<DATE(2021,1,1)),'Growth Index'!B$3:B$2188)-1,LOOKUP(2,1/('Daily Prices'!$A$3:$A$2188<DATE(2021,2,1)+0),'Growth Index'!B$3:B$2188)/100-1) -> -0.030691501 | C11: =IFERROR(LOOKUP(2,1/('Daily Prices'!$A$3:$A$2188<DATE(2021,3,1)+0),'Growth Index'!B$3:B$2188)/LOOKUP(2,1/('Daily Prices'!$A$3:$A$2188<DATE(2021,2,1)),'Growth Index'!B$3:B$2188)-1,LOOKUP(2,1/('Daily Prices'!$A$3:$A$2188<DATE(2021,3,1)+0),'Growth Index'!B$3:B$2188)/100-1) -> 0.060800976 | D11: =IFERROR(LOOKUP(2,1/('Daily Prices'!$A$3:$A$2188<DATE(2021,4,1)+0),'Growth Index'!B$3:B$2188)/LOOKUP(2,1/('Daily Prices'!$A$3:$A$2188<DATE(2021,3,1)),'Growth Index'!B$3:B$2188)-1,LOOKUP(2,1/('Daily Prices'!$A$3:$A$2188<DATE(2021,4,1)+0),'Growth Index'!B$3:B$2188)/100-1) -> 0.0083331993 | E11: =IFERROR(LOOKUP(2,1/('Daily Prices'!$A$3:$A$2188<DATE(2021,5,1)+0),'Growth Index'!B$3:B$2188)/LOOKUP(2,1/('Daily Prices'!$A$3:$A$2188<DATE(2021,4,1)),'Growth Index'!B$3:B$2188)-1,LOOKUP(2,1/('Daily Prices'!$A$3:$A$2188<DATE(2021,5,1)+0),'Growth Index'!B$3:B$2188)/100-1) -> -0.014679913 | F11: =IFERROR(LOOKUP(2,1/('Daily Prices'!$A$3:$A$2188<DATE(2021,6,1)+0),'Growth Index'!B$3:B$2188)/LOOKUP(2,1/('Daily Prices'!$A$3:$A$2188<DATE(2021,5,1)),'Growth Index'!B$3:B$2188)-1,LOOKUP(2,1/('Daily Prices'!$A$3:$A$2188<DATE(2021,6,1)+0),'Growth Index'!B$3:B$2188)/100-1) -> 0.064676658 | G11: =IFERROR(LOOKUP(2,1/('Daily Prices'!$A$3:$A$2188<DATE(2021,7,1)+0),'Growth Index'!B$3:B$2188)/LOOKUP(2,1/('Daily Prices'!$A$3:$A$2188<DATE(2021,6,1)),'Growth Index'!B$3:B$2188)-1,LOOKUP(2,1/('Daily Prices'!$A$3:$A$2188<DATE(2021,7,1)+0),'Growth Index'!B$3:B$2188)/100-1) -> 0.010498592 | H11: =IFERROR(LOOKUP(2,1/('Daily Prices'!$A$3:$A$2188<DATE(2021,8,1)+0),'Growth Index'!B$3:B$2188)/LOOKUP(2,1/('Daily Prices'!$A$3:$A$2188<DATE(2021,7,1)),'Growth Index'!B$3:B$2188)-1,LOOKUP(2,1/('Daily Prices'!$A$3:$A$2188<DATE(2021,8,1)+0),'Growth Index'!B$3:B$2188)/100-1) -> 0.001984082 | I11: =IFERROR(LOOKUP(2,1/('Daily Prices'!$A$3:$A$2188<DATE(2021,9,1)+0),'Growth Index'!B$3:B$2188)/LOOKUP(2,1/('Daily Prices'!$A$3:$A$2188<DATE(2021,8,1)),'Growth Index'!B$3:B$2188)-1,LOOKUP(2,1/('Daily Prices'!$A$3:$A$2188<DATE(2021,9,1)+0),'Growth Index'!B$3:B$2188)/100-1) -> 0.094425716 | J11: =IFERROR(LOOKUP(2,1/('Daily Prices'!$A$3:$A$2188<DATE(2021,10,1)+0),'Growth Index'!B$3:B$2188)/LOOKUP(2,1/('Daily Prices'!$A$3:$A$2188<DATE(2021,9,1)),'Growth Index'!B$3:B$2188)-1,LOOKUP(2,1/('Daily Prices'!$A$3:$A$2188<DATE(2021,10,1)+0),'Growth Index'!B$3:B$2188)/100-1) -> 0.027348473 | K11: =IFERROR(LOOKUP(2,1/('Daily Prices'!$A$3:$A$2188<DATE(2021,11,1)+0),'Growth Index'!B$3:B$2188)/LOOKUP(2,1/('Daily Prices'!$A$3:$A$2188<DATE(2021,10,1)),'Growth Index'!B$3:B$2188)-1,LOOKUP(2,1/('Daily Prices'!$A$3:$A$2188<DATE(2021,11,1)+0),'Growth Index'!B$3:B$2188)/100-1) -> 0.0030539678 | L11: =IFERROR(LOOKUP(2,1/('Daily Prices'!$A$3:$A$2188<DATE(2021,12,1)+0),'Growth Index'!B$3:B$2188)/LOOKUP(2,1/('Daily Prices'!$A$3:$A$2188<DATE(2021,11,1)),'Growth Index'!B$3:B$2188)-1,LOOKUP(2,1/('Daily Prices'!$A$3:$A$2188<DATE(2021,12,1)+0),'Growth Index'!B$3:B$2188)/100-1) -> -0.037804351 | M11: =IFERROR(LOOKUP(2,1/('Daily Prices'!$A$3:$A$2188<DATE(2022,1,1)),'Growth Index'!B$3:B$2188)/LOOKUP(2,1/('Daily Prices'!$A$3:$A$2188<DATE(2021,12,1)),'Growth Index'!B$3:B$2188)-1,LOOKUP(2,1/('Daily Prices'!$A$3:$A$2188<DATE(2022,1,1)),'Growth Index'!B$3:B$2188)/100-1) -> 0.02083506 | N11: =IFERROR(LOOKUP(2,1/('Daily Prices'!$A$3:$A$2188<DATE(2022,1,1)),'Growth Index'!B$3:B$2188)/LOOKUP(2,1/('Daily Prices'!$A$3:$A$2188<DATE(2021,1,1)),'Growth Index'!B$3:B$2188)-1,LOOKUP(2,1/('Daily Prices'!$A$3:$A$2188<DATE(2022,1,1)),'Growth Index'!B$3:B$2188)/100-1) -> 0.21994131
A12: 2022 | B12: =IFERROR(LOOKUP(2,1/('Daily Prices'!$A$3:$A$2188<DATE(2022,2,1)+0),'Growth Index'!B$3:B$2188)/LOOKUP(2,1/('Daily Prices'!$A$3:$A$2188<DATE(2022,1,1)),'Growth Index'!B$3:B$2188)-1,LOOKUP(2,1/('Daily Prices'!$A$3:$A$2188<DATE(2022,2,1)+0),'Growth Index'!B$3:B$2188)/100-1) -> -0.0041138933 | C12: =IFERROR(LOOKUP(2,1/('Daily Prices'!$A$3:$A$2188<DATE(2022,3,1)+0),'Growth Index'!B$3:B$2188)/LOOKUP(2,1/('Daily Prices'!$A$3:$A$2188<DATE(2022,2,1)),'Growth Index'!B$3:B$2188)-1,LOOKUP(2,1/('Daily Prices'!$A$3:$A$2188<DATE(2022,3,1)+0),'Growth Index'!B$3:B$2188)/100-1) -> -0.03045618 | D12: =IFERROR(LOOKUP(2,1/('Daily Prices'!$A$3:$A$2188<DATE(2022,4,1)+0),'Growth Index'!B$3:B$2188)/LOOKUP(2,1/('Daily Prices'!$A$3:$A$2188<DATE(2022,3,1)),'Growth Index'!B$3:B$2188)-1,LOOKUP(2,1/('Daily Prices'!$A$3:$A$2188<DATE(2022,4,1)+0),'Growth Index'!B$3:B$2188)/100-1) -> 0.041268307 | E12: =IFERROR(LOOKUP(2,1/('Daily Prices'!$A$3:$A$2188<DATE(2022,5,1)+0),'Growth Index'!B$3:B$2188)/LOOKUP(2,1/('Daily Prices'!$A$3:$A$2188<DATE(2022,4,1)),'Growth Index'!B$3:B$2188)-1,LOOKUP(2,1/('Daily Prices'!$A$3:$A$2188<DATE(2022,5,1)+0),'Growth Index'!B$3:B$2188)/100-1) -> -0.025741478 | F12: =IFERROR(LOOKUP(2,1/('Daily Prices'!$A$3:$A$2188<DATE(2022,6,1)+0),'Growth Index'!B$3:B$2188)/LOOKUP(2,1/('Daily Prices'!$A$3:$A$2188<DATE(2022,5,1)),'Growth Index'!B$3:B$2188)-1,LOOKUP(2,1/('Daily Prices'!$A$3:$A$2188<DATE(2022,6,1)+0),'Growth Index'!B$3:B$2188)/100-1) -> -0.026190628 | G12: =IFERROR(LOOKUP(2,1/('Daily Prices'!$A$3:$A$2188<DATE(2022,7,1)+0),'Growth Index'!B$3:B$2188)/LOOKUP(2,1/('Daily Prices'!$A$3:$A$2188<DATE(2022,6,1)),'Growth Index'!B$3:B$2188)-1,LOOKUP(2,1/('Daily Prices'!$A$3:$A$2188<DATE(2022,7,1)+0),'Growth Index'!B$3:B$2188)/100-1) -> -0.045845503 | H12: =IFERROR(LOOKUP(2,1/('Daily Prices'!$A$3:$A$2188<DATE(2022,8,1)+0),'Growth Index'!B$3:B$2188)/LOOKUP(2,1/('Daily Prices'!$A$3:$A$2188<DATE(2022,7,1)),'Growth Index'!B$3:B$2188)-1,LOOKUP(2,1/('Daily Prices'!$A$3:$A$2188<DATE(2022,8,1)+0),'Growth Index'!B$3:B$2188)/100-1) -> 0.085843097 | I12: =IFERROR(LOOKUP(2,1/('Daily Prices'!$A$3:$A$2188<DATE(2022,9,1)+0),'Growth Index'!B$3:B$2188)/LOOKUP(2,1/('Daily Prices'!$A$3:$A$2188<DATE(2022,8,1)),'Growth Index'!B$3:B$2188)-1,LOOKUP(2,1/('Daily Prices'!$A$3:$A$2188<DATE(2022,9,1)+0),'Growth Index'!B$3:B$2188)/100-1) -> 0.034163826 | J12: =IFERROR(LOOKUP(2,1/('Daily Prices'!$A$3:$A$2188<DATE(2022,10,1)+0),'Growth Index'!B$3:B$2188)/LOOKUP(2,1/('Daily Prices'!$A$3:$A$2188<DATE(2022,9,1)),'Growth Index'!B$3:B$2188)-1,LOOKUP(2,1/('Daily Prices'!$A$3:$A$2188<DATE(2022,10,1)+0),'Growth Index'!B$3:B$2188)/100-1) -> -0.035442624 | K12: =IFERROR(LOOKUP(2,1/('Daily Prices'!$A$3:$A$2188<DATE(2022,11,1)+0),'Growth Index'!B$3:B$2188)/LOOKUP(2,1/('Daily Prices'!$A$3:$A$2188<DATE(2022,10,1)),'Growth Index'!B$3:B$2188)-1,LOOKUP(2,1/('Daily Prices'!$A$3:$A$2188<DATE(2022,11,1)+0),'Growth Index'!B$3:B$2188)/100-1) -> 0.057806861 | L12: =IFERROR(LOOKUP(2,1/('Daily Prices'!$A$3:$A$2188<DATE(2022,12,1)+0),'Growth Index'!B$3:B$2188)/LOOKUP(2,1/('Daily Prices'!$A$3:$A$2188<DATE(2022,11,1)),'Growth Index'!B$3:B$2188)-1,LOOKUP(2,1/('Daily Prices'!$A$3:$A$2188<DATE(2022,12,1)+0),'Growth Index'!B$3:B$2188)/100-1) -> 0.038735672 | M12: =IFERROR(LOOKUP(2,1/('Daily Prices'!$A$3:$A$2188<DATE(2023,1,1)),'Growth Index'!B$3:B$2188)/LOOKUP(2,1/('Daily Prices'!$A$3:$A$2188<DATE(2022,12,1)),'Growth Index'!B$3:B$2188)-1,LOOKUP(2,1/('Daily Prices'!$A$3:$A$2188<DATE(2023,1,1)),'Growth Index'!B$3:B$2188)/100-1) -> -0.035799089 | N12: =IFERROR(LOOKUP(2,1/('Daily Prices'!$A$3:$A$2188<DATE(2023,1,1)),'Growth Index'!B$3:B$2188)/LOOKUP(2,1/('Daily Prices'!$A$3:$A$2188<DATE(2022,1,1)),'Growth Index'!B$3:B$2188)-1,LOOKUP(2,1/('Daily Prices'!$A$3:$A$2188<DATE(2023,1,1)),'Growth Index'!B$3:B$2188)/100-1) -> 0.044407732
A13: 2023 | B13: =IFERROR(LOOKUP(2,1/('Daily Prices'!$A$3:$A$2188<DATE(2023,2,1)+0),'Growth Index'!B$3:B$2188)/LOOKUP(2,1/('Daily Prices'!$A$3:$A$2188<DATE(2023,1,1)),'Growth Index'!B$3:B$2188)-1,LOOKUP(2,1/('Daily Prices'!$A$3:$A$2188<DATE(2023,2,1)+0),'Growth Index'!B$3:B$2188)/100-1) -> -0.021216704 | C13: =IFERROR(LOOKUP(2,1/('Daily Prices'!$A$3:$A$2188<DATE(2023,3,1)+0),'Growth Index'!B$3:B$2188)/LOOKUP(2,1/('Daily Prices'!$A$3:$A$2188<DATE(2023,2,1)),'Growth Index'!B$3:B$2188)-1,LOOKUP(2,1/('Daily Prices'!$A$3:$A$2188<DATE(2023,3,1)+0),'Growth Index'!B$3:B$2188)/100-1) -> -0.0098703776 | D13: =IFERROR(LOOKUP(2,1/('Daily Prices'!$A$3:$A$2188<DATE(2023,4,1)+0),'Growth Index'!B$3:B$2188)/LOOKUP(2,1/('Daily Prices'!$A$3:$A$2188<DATE(2023,3,1)),'Growth Index'!B$3:B$2188)-1,LOOKUP(2,1/('Daily Prices'!$A$3:$A$2188<DATE(2023,4,1)+0),'Growth Index'!B$3:B$2188)/100-1) -> 0.00049862522 | E13: =IFERROR(LOOKUP(2,1/('Daily Prices'!$A$3:$A$2188<DATE(2023,5,1)+0),'Growth Index'!B$3:B$2188)/LOOKUP(2,1/('Daily Prices'!$A$3:$A$2188<DATE(2023,4,1)),'Growth Index'!B$3:B$2188)-1,LOOKUP(2,1/('Daily Prices'!$A$3:$A$2188<DATE(2023,5,1)+0),'Growth Index'!B$3:B$2188)/100-1) -> 0.035952964 | F13: =IFERROR(LOOKUP(2,1/('Daily Prices'!$A$3:$A$2188<DATE(2023,6,1)+0),'Growth Index'!B$3:B$2188)/LOOKUP(2,1/('Daily Prices'!$A$3:$A$2188<DATE(2023,5,1)),'Growth Index'!B$3:B$2188)-1,LOOKUP(2,1/('Daily Prices'!$A$3:$A$2188<DATE(2023,6,1)+0),'Growth Index'!B$3:B$2188)/100-1) -> 0.024705281 | G13: =IFERROR(LOOKUP(2,1/('Daily Prices'!$A$3:$A$2188<DATE(2023,7,1)+0),'Growth Index'!B$3:B$2188)/LOOKUP(2,1/('Daily Prices'!$A$3:$A$2188<DATE(2023,6,1)),'Growth Index'!B$3:B$2188)-1,LOOKUP(2,1/('Daily Prices'!$A$3:$A$2188<DATE(2023,7,1)+0),'Growth Index'!B$3:B$2188)/100-1) -> 0.033475647 | H13: =IFERROR(LOOKUP(2,1/('Daily Prices'!$A$3:$A$2188<DATE(2023,8,1)+0),'Growth Index'!B$3:B$2188)/LOOKUP(2,1/('Daily Prices'!$A$3:$A$2188<DATE(2023,7,1)),'Growth Index'!B$3:B$2188)-1,LOOKUP(2,1/('Daily Prices'!$A$3:$A$2188<DATE(2023,8,1)+0),'Growth Index'!B$3:B$2188)/100-1) -> 0.027953496 | I13: =IFERROR(LOOKUP(2,1/('Daily Prices'!$A$3:$A$2188<DATE(2023,9,1)+0),'Growth Index'!B$3:B$2188)/LOOKUP(2,1/('Daily Prices'!$A$3:$A$2188<DATE(2023,8,1)),'Growth Index'!B$3:B$2188)-1,LOOKUP(2,1/('Daily Prices'!$A$3:$A$2188<DATE(2023,9,1)+0),'Growth Index'!B$3:B$2188)/100-1) -> -0.02549706 | J13: =IFERROR(LOOKUP(2,1/('Daily Prices'!$A$3:$A$2188<DATE(2023,10,1)+0),'Growth Index'!B$3:B$2188)/LOOKUP(2,1/('Daily Prices'!$A$3:$A$2188<DATE(2023,9,1)),'Growth Index'!B$3:B$2188)-1,LOOKUP(2,1/('Daily Prices'!$A$3:$A$2188<DATE(2023,10,1)+0),'Growth Index'!B$3:B$2188)/100-1) -> 0.015378348 | K13: =IFERROR(LOOKUP(2,1/('Daily Prices'!$A$3:$A$2188<DATE(2023,11,1)+0),'Growth Index'!B$3:B$2188)/LOOKUP(2,1/('Daily Prices'!$A$3:$A$2188<DATE(2023,10,1)),'Growth Index'!B$3:B$2188)-1,LOOKUP(2,1/('Daily Prices'!$A$3:$A$2188<DATE(2023,11,1)+0),'Growth Index'!B$3:B$2188)/100-1) -> -0.029675333 | L13: =IFERROR(LOOKUP(2,1/('Daily Prices'!$A$3:$A$2188<DATE(2023,12,1)+0),'Growth Index'!B$3:B$2188)/LOOKUP(2,1/('Daily Prices'!$A$3:$A$2188<DATE(2023,11,1)),'Growth Index'!B$3:B$2188)-1,LOOKUP(2,1/('Daily Prices'!$A$3:$A$2188<DATE(2023,12,1)+0),'Growth Index'!B$3:B$2188)/100-1) -> 0.04874385 | M13: =IFERROR(LOOKUP(2,1/('Daily Prices'!$A$3:$A$2188<DATE(2024,1,1)),'Growth Index'!B$3:B$2188)/LOOKUP(2,1/('Daily Prices'!$A$3:$A$2188<DATE(2023,12,1)),'Growth Index'!B$3:B$2188)-1,LOOKUP(2,1/('Daily Prices'!$A$3:$A$2188<DATE(2024,1,1)),'Growth Index'!B$3:B$2188)/100-1) -> 0.0783989 | N13: =IFERROR(LOOKUP(2,1/('Daily Prices'!$A$3:$A$2188<DATE(2024,1,1)),'Growth Index'!B$3:B$2188)/LOOKUP(2,1/('Daily Prices'!$A$3:$A$2188<DATE(2023,1,1)),'Growth Index'!B$3:B$2188)-1,LOOKUP(2,1/('Daily Prices'!$A$3:$A$2188<DATE(2024,1,1)),'Growth Index'!B$3:B$2188)/100-1) -> 0.18736656
A14: 2024 | B14: =IFERROR(LOOKUP(2,1/('Daily Prices'!$A$3:$A$2188<DATE(2024,2,1)+0),'Growth Index'!B$3:B$2188)/LOOKUP(2,1/('Daily Prices'!$A$3:$A$2188<DATE(2024,1,1)),'Growth Index'!B$3:B$2188)-1,LOOKUP(2,1/('Daily Prices'!$A$3:$A$2188<DATE(2024,2,1)+0),'Growth Index'!B$3:B$2188)/100-1) -> -0.0067573123 | C14: =IFERROR(LOOKUP(2,1/('Daily Prices'!$A$3:$A$2188<DATE(2024,3,1)+0),'Growth Index'!B$3:B$2188)/LOOKUP(2,1/('Daily Prices'!$A$3:$A$2188<DATE(2024,2,1)),'Growth Index'!B$3:B$2188)-1,LOOKUP(2,1/('Daily Prices'!$A$3:$A$2188<DATE(2024,3,1)+0),'Growth Index'!B$3:B$2188)/100-1) -> 0.010427429 | D14: =IFERROR(LOOKUP(2,1/('Daily Prices'!$A$3:$A$2188<DATE(2024,4,1)+0),'Growth Index'!B$3:B$2188)/LOOKUP(2,1/('Daily Prices'!$A$3:$A$2188<DATE(2024,3,1)),'Growth Index'!B$3:B$2188)-1,LOOKUP(2,1/('Daily Prices'!$A$3:$A$2188<DATE(2024,4,1)+0),'Growth Index'!B$3:B$2188)/100-1) -> 0.015876486 | E14: =IFERROR(LOOKUP(2,1/('Daily Prices'!$A$3:$A$2188<DATE(2024,5,1)+0),'Growth Index'!B$3:B$2188)/LOOKUP(2,1/('Daily Prices'!$A$3:$A$2188<DATE(2024,4,1)),'Growth Index'!B$3:B$2188)-1,LOOKUP(2,1/('Daily Prices'!$A$3:$A$2188<DATE(2024,5,1)+0),'Growth Index'!B$3:B$2188)/100-1) -> 0.011288727 | F14: =IFERROR(LOOKUP(2,1/('Daily Prices'!$A$3:$A$2188<DATE(2024,6,1)+0),'Growth Index'!B$3:B$2188)/LOOKUP(2,1/('Daily Prices'!$A$3:$A$2188<DATE(2024,5,1)),'Growth Index'!B$3:B$2188)-1,LOOKUP(2,1/('Daily Prices'!$A$3:$A$2188<DATE(2024,6,1)+0),'Growth Index'!B$3:B$2188)/100-1) -> -0.0070012156 | G14: =IFERROR(LOOKUP(2,1/('Daily Prices'!$A$3:$A$2188<DATE(2024,7,1)+0),'Growth Index'!B$3:B$2188)/LOOKUP(2,1/('Daily Prices'!$A$3:$A$2188<DATE(2024,6,1)),'Growth Index'!B$3:B$2188)-1,LOOKUP(2,1/('Daily Prices'!$A$3:$A$2188<DATE(2024,7,1)+0),'Growth Index'!B$3:B$2188)/100-1) -> 0.068568553 | H14: =IFERROR(LOOKUP(2,1/('Daily Prices'!$A$3:$A$2188<DATE(2024,8,1)+0),'Growth Index'!B$3:B$2188)/LOOKUP(2,1/('Daily Prices'!$A$3:$A$2188<DATE(2024,7,1)),'Growth Index'!B$3:B$2188)-1,LOOKUP(2,1/('Daily Prices'!$A$3:$A$2188<DATE(2024,8,1)+0),'Growth Index'!B$3:B$2188)/100-1) -> 0.034272004 | I14: =IFERROR(LOOKUP(2,1/('Daily Prices'!$A$3:$A$2188<DATE(2024,9,1)+0),'Growth Index'!B$3:B$2188)/LOOKUP(2,1/('Daily Prices'!$A$3:$A$2188<DATE(2024,8,1)),'Growth Index'!B$3:B$2188)-1,LOOKUP(2,1/('Daily Prices'!$A$3:$A$2188<DATE(2024,9,1)+0),'Growth Index'!B$3:B$2188)/100-1) -> 0.0076390967 | J14: =IFERROR(LOOKUP(2,1/('Daily Prices'!$A$3:$A$2188<DATE(2024,10,1)+0),'Growth Index'!B$3:B$2188)/LOOKUP(2,1/('Daily Prices'!$A$3:$A$2188<DATE(2024,9,1)),'Growth Index'!B$3:B$2188)-1,LOOKUP(2,1/('Daily Prices'!$A$3:$A$2188<DATE(2024,10,1)+0),'Growth Index'!B$3:B$2188)/100-1) -> 0.023480749 | K14: =IFERROR(LOOKUP(2,1/('Daily Prices'!$A$3:$A$2188<DATE(2024,11,1)+0),'Growth Index'!B$3:B$2188)/LOOKUP(2,1/('Daily Prices'!$A$3:$A$2188<DATE(2024,10,1)),'Growth Index'!B$3:B$2188)-1,LOOKUP(2,1/('Daily Prices'!$A$3:$A$2188<DATE(2024,11,1)+0),'Growth Index'!B$3:B$2188)/100-1) -> -0.058253058 | L14: =IFERROR(LOOKUP(2,1/('Daily Prices'!$A$3:$A$2188<DATE(2024,12,1)+0),'Growth Index'!B$3:B$2188)/LOOKUP(2,1/('Daily Prices'!$A$3:$A$2188<DATE(2024,11,1)),'Growth Index'!B$3:B$2188)-1,LOOKUP(2,1/('Daily Prices'!$A$3:$A$2188<DATE(2024,12,1)+0),'Growth Index'!B$3:B$2188)/100-1) -> 0.0052114233 | M14: =IFERROR(LOOKUP(2,1/('Daily Prices'!$A$3:$A$2188<DATE(2025,1,1)),'Growth Index'!B$3:B$2188)/LOOKUP(2,1/('Daily Prices'!$A$3:$A$2188<DATE(2024,12,1)),'Growth Index'!B$3:B$2188)-1,LOOKUP(2,1/('Daily Prices'!$A$3:$A$2188<DATE(2025,1,1)),'Growth Index'!B$3:B$2188)/100-1) -> -0.020848645 | N14: =IFERROR(LOOKUP(2,1/('Daily Prices'!$A$3:$A$2188<DATE(2025,1,1)),'Growth Index'!B$3:B$2188)/LOOKUP(2,1/('Daily Prices'!$A$3:$A$2188<DATE(2024,1,1)),'Growth Index'!B$3:B$2188)-1,LOOKUP(2,1/('Daily Prices'!$A$3:$A$2188<DATE(2025,1,1)),'Growth Index'!B$3:B$2188)/100-1) -> 0.081654606
A16: Gold
A17: Year | B17: Jan | C17: Feb | D17: Mar | E17: Apr | F17: May | G17: Jun | H17: Jul | I17: Aug | J17: Sep | K17: Oct | L17: Nov | M17: Dec | N17: Year
A18: 2015 | B18: =IFERROR(LOOKUP(2,1/('Daily Prices'!$A$3:$A$2188<DATE(2015,2,1)+0),'Growth Index'!C$3:C$2188)/LOOKUP(2,1/('Daily Prices'!$A$3:$A$2188<DATE(2015,1,1)),'Growth Index'!C$3:C$2188)-1,LOOKUP(2,1/('Daily Prices'!$A$3:$A$2188<DATE(2015,2,1)+0),'Growth Index'!C$3:C$2188)/100-1) -> 0.025081068 | C18: =IFERROR(LOOKUP(2,1/('Daily Prices'!$A$3:$A$2188<DATE(2015,3,1)+0),'Growth Index'!C$3:C$2188)/LOOKUP(2,1/('Daily Prices'!$A$3:$A$2188<DATE(2015,2,1)),'Growth Index'!C$3:C$2188)-1,LOOKUP(2,1/('Daily Prices'!$A$3:$A$2188<DATE(2015,3,1)+0),'Growth Index'!C$3:C$2188)/100-1) -> -0.042904322 | D18: =IFERROR(LOOKUP(2,1/('Daily Prices'!$A$3:$A$2188<DATE(2015,4,1)+0),'Growth Index'!C$3:C$2188)/LOOKUP(2,1/('Daily Prices'!$A$3:$A$2188<DATE(2015,3,1)),'Growth Index'!C$3:C$2188)-1,LOOKUP(2,1/('Daily Prices'!$A$3:$A$2188<DATE(2015,4,1)+0),'Growth Index'!C$3:C$2188)/100-1) -> -0.012268013 | E18: =IFERROR(LOOKUP(2,1/('Daily Prices'!$A$3:$A$2188<DATE(2015,5,1)+0),'Growth Index'!C$3:C$2188)/LOOKUP(2,1/('Daily Prices'!$A$3:$A$2188<DATE(2015,4,1)),'Growth Index'!C$3:C$2188)-1,LOOKUP(2,1/('Daily Prices'!$A$3:$A$2188<DATE(2015,5,1)+0),'Growth Index'!C$3:C$2188)/100-1) -> 0.015195781 | F18: =IFERROR(LOOKUP(2,1/('Daily Prices'!$A$3:$A$2188<DATE(2015,6,1)+0),'Growth Index'!C$3:C$2188)/LOOKUP(2,1/('Daily Prices'!$A$3:$A$2188<DATE(2015,5,1)),'Growth Index'!C$3:C$2188)-1,LOOKUP(2,1/('Daily Prices'!$A$3:$A$2188<DATE(2015,6,1)+0),'Growth Index'!C$3:C$2188)/100-1) -> 0.010581671 | G18: =IFERROR(LOOKUP(2,1/('Daily Prices'!$A$3:$A$2188<DATE(2015,7,1)+0),'Growth Index'!C$3:C$2188)/LOOKUP(2,1/('Daily Prices'!$A$3:$A$2188<DATE(2015,6,1)),'Growth Index'!C$3:C$2188)-1,LOOKUP(2,1/('Daily Prices'!$A$3:$A$2188<DATE(2015,7,1)+0),'Growth Index'!C$3:C$2188)/100-1) -> -0.018303203 | H18: =IFERROR(LOOKUP(2,1/('Daily Prices'!$A$3:$A$2188<DATE(2015,8,1)+0),'Growth Index'!C$3:C$2188)/LOOKUP(2,1/('Daily Prices'!$A$3:$A$2188<DATE(2015,7,1)),'Growth Index'!C$3:C$2188)-1,LOOKUP(2,1/('Daily Prices'!$A$3:$A$2188<DATE(2015,8,1)+0),'Growth Index'!C$3:C$2188)/100-1) -> -0.056608758 | I18: =IFERROR(LOOKUP(2,1/('Daily Prices'!$A$3:$A$2188<DATE(2015,9,1)+0),'Growth Index'!C$3:C$2188)/LOOKUP(2,1/('Daily Prices'!$A$3:$A$2188<DATE(2015,8,1)),'Growth Index'!C$3:C$2188)-1,LOOKUP(2,1/('Daily Prices'!$A$3:$A$2188<DATE(2015,9,1)+0),'Growth Index'!C$3:C$2188)/100-1) -> 0.069451417 | J18: =IFERROR(LOOKUP(2,1/('Daily Prices'!$A$3:$A$2188<DATE(2015,10,1)+0),'Growth Index'!C$3:C$2188)/LOOKUP(2,1/('Daily Prices'!$A$3:$A$2188<DATE(2015,9,1)),'Growth Index'!C$3:C$2188)-1,LOOKUP(2,1/('Daily Prices'!$A$3:$A$2188<DATE(2015,10,1)+0),'Growth Index'!C$3:C$2188)/100-1) -> -0.028692939 | K18: =IFERROR(LOOKUP(2,1/('Daily Prices'!$A$3:$A$2188<DATE(2015,11,1)+0),'Growth Index'!C$3:C$2188)/LOOKUP(2,1/('Daily Prices'!$A$3:$A$2188<DATE(2015,10,1)),'Growth Index'!C$3:C$2188)-1,LOOKUP(2,1/('Daily Prices'!$A$3:$A$2188<DATE(2015,11,1)+0),'Growth Index'!C$3:C$2188)/100-1) -> 0.023625695 | L18: =IFERROR(LOOKUP(2,1/('Daily Prices'!$A$3:$A$2188<DATE(2015,12,1)+0),'Growth Index'!C$3:C$2188)/LOOKUP(2,1/('Daily Prices'!$A$3:$A$2188<DATE(2015,11,1)),'Growth Index'!C$3:C$2188)-1,LOOKUP(2,1/('Daily Prices'!$A$3:$A$2188<DATE(2015,12,1)+0),'Growth Index'!C$3:C$2188)/100-1) -> -0.053961296 | M18: =IFERROR(LOOKUP(2,1/('Daily Prices'!$A$3:$A$2188<DATE(2016,1,1)),'Growth Index'!C$3:C$2188)/LOOKUP(2,1/('Daily Prices'!$A$3:$A$2188<DATE(2015,12,1)),'Growth Index'!C$3:C$2188)-1,LOOKUP(2,1/('Daily Prices'!$A$3:$A$2188<DATE(2016,1,1)),'Growth Index'!C$3:C$2188)/100-1) -> -0.0035736238 | N18: =IFERROR(LOOKUP(2,1/('Daily Prices'!$A$3:$A$2188<DATE(2016,1,1)),'Growth Index'!C$3:C$2188)/LOOKUP(2,1/('Daily Prices'!$A$3:$A$2188<DATE(2015,1,1)),'Growth Index'!C$3:C$2188)-1,LOOKUP(2,1/('Daily Prices'!$A$3:$A$2188<DATE(2016,1,1)),'Growth Index'!C$3:C$2188)/100-1) -> -0.077097067
A19: 2016 | B19: =IFERROR(LOOKUP(2,1/('Daily Prices'!$A$3:$A$2188<DATE(2016,2,1)+0),'Growth Index'!C$3:C$2188)/LOOKUP(2,1/('Daily Prices'!$A$3:$A$2188<DATE(2016,1,1)),'Growth Index'!C$3:C$2188)-1,LOOKUP(2,1/('Daily Prices'!$A$3:$A$2188<DATE(2016,2,1)+0),'Growth Index'!C$3:C$2188)/100-1) -> 0.071358834 | C19: =IFERROR(LOOKUP(2,1/('Daily Prices'!$A$3:$A$2188<DATE(2016,3,1)+0),'Growth Index'!C$3:C$2188)/LOOKUP(2,1/('Daily Prices'!$A$3:$A$2188<DATE(2016,2,1)),'Growth Index'!C$3:C$2188)-1,LOOKUP(2,1/('Daily Prices'!$A$3:$A$2188<DATE(2016,3,1)+0),'Growth Index'!C$3:C$2188)/100-1) -> 0.11634733 | D19: =IFERROR(LOOKUP(2,1/('Daily Prices'!$A$3:$A$2188<DATE(2016,4,1)+0),'Growth Index'!C$3:C$2188)/LOOKUP(2,1/('Daily Prices'!$A$3:$A$2188<DATE(2016,3,1)),'Growth Index'!C$3:C$2188)-1,LOOKUP(2,1/('Daily Prices'!$A$3:$A$2188<DATE(2016,4,1)+0),'Growth Index'!C$3:C$2188)/100-1) -> -0.02872232 | E19: =IFERROR(LOOKUP(2,1/('Daily Prices'!$A$3:$A$2188<DATE(2016,5,1)+0),'Growth Index'!C$3:C$2188)/LOOKUP(2,1/('Daily Prices'!$A$3:$A$2188<DATE(2016,4,1)),'Growth Index'!C$3:C$2188)-1,LOOKUP(2,1/('Daily Prices'!$A$3:$A$2188<DATE(2016,5,1)+0),'Growth Index'!C$3:C$2188)/100-1) -> 0.043734733 | F19: =IFERROR(LOOKUP(2,1/('Daily Prices'!$A$3:$A$2188<DATE(2016,6,1)+0),'Growth Index'!C$3:C$2188)/LOOKUP(2,1/('Daily Prices'!$A$3:$A$2188<DATE(2016,5,1)),'Growth Index'!C$3:C$2188)-1,LOOKUP(2,1/('Daily Prices'!$A$3:$A$2188<DATE(2016,6,1)+0),'Growth Index'!C$3:C$2188)/100-1) -> -0.047291909 | G19: =IFERROR(LOOKUP(2,1/('Daily Prices'!$A$3:$A$2188<DATE(2016,7,1)+0),'Growth Index'!C$3:C$2188)/LOOKUP(2,1/('Daily Prices'!$A$3:$A$2188<DATE(2016,6,1)),'Growth Index'!C$3:C$2188)-1,LOOKUP(2,1/('Daily Prices'!$A$3:$A$2188<DATE(2016,7,1)+0),'Growth Index'!C$3:C$2188)/100-1) -> 0.096148772 | H19: =IFERROR(LOOKUP(2,1/('Daily Prices'!$A$3:$A$2188<DATE(2016,8,1)+0),'Growth Index'!C$3:C$2188)/LOOKUP(2,1/('Daily Prices'!$A$3:$A$2188<DATE(2016,7,1)),'Growth Index'!C$3:C$2188)-1,LOOKUP(2,1/('Daily Prices'!$A$3:$A$2188<DATE(2016,8,1)+0),'Growth Index'!C$3:C$2188)/100-1) -> 0.0051350562 | I19: =IFERROR(LOOKUP(2,1/('Daily Prices'!$A$3:$A$2188<DATE(2016,9,1)+0),'Growth Index'!C$3:C$2188)/LOOKUP(2,1/('Daily Prices'!$A$3:$A$2188<DATE(2016,8,1)),'Growth Index'!C$3:C$2188)-1,LOOKUP(2,1/('Daily Prices'!$A$3:$A$2188<DATE(2016,9,1)+0),'Growth Index'!C$3:C$2188)/100-1) -> -0.022183965 | J19: =IFERROR(LOOKUP(2,1/('Daily Prices'!$A$3:$A$2188<DATE(2016,10,1)+0),'Growth Index'!C$3:C$2188)/LOOKUP(2,1/('Daily Prices'!$A$3:$A$2188<DATE(2016,9,1)),'Growth Index'!C$3:C$2188)-1,LOOKUP(2,1/('Daily Prices'!$A$3:$A$2188<DATE(2016,10,1)+0),'Growth Index'!C$3:C$2188)/100-1) -> 0.0052742389 | K19: =IFERROR(LOOKUP(2,1/('Daily Prices'!$A$3:$A$2188<DATE(2016,11,1)+0),'Growth Index'!C$3:C$2188)/LOOKUP(2,1/('Daily Prices'!$A$3:$A$2188<DATE(2016,10,1)),'Growth Index'!C$3:C$2188)-1,LOOKUP(2,1/('Daily Prices'!$A$3:$A$2188<DATE(2016,11,1)+0),'Growth Index'!C$3:C$2188)/100-1) -> -0.034997731 | L19: =IFERROR(LOOKUP(2,1/('Daily Prices'!$A$3:$A$2188<DATE(2016,12,1)+0),'Growth Index'!C$3:C$2188)/LOOKUP(2,1/('Daily Prices'!$A$3:$A$2188<DATE(2016,11,1)),'Growth Index'!C$3:C$2188)-1,LOOKUP(2,1/('Daily Prices'!$A$3:$A$2188<DATE(2016,12,1)+0),'Growth Index'!C$3:C$2188)/100-1) -> -0.050150868 | M19: =IFERROR(LOOKUP(2,1/('Daily Prices'!$A$3:$A$2188<DATE(2017,1,1)),'Growth Index'!C$3:C$2188)/LOOKUP(2,1/('Daily Prices'!$A$3:$A$2188<DATE(2016,12,1)),'Growth Index'!C$3:C$2188)-1,LOOKUP(2,1/('Daily Prices'!$A$3:$A$2188<DATE(2017,1,1)),'Growth Index'!C$3:C$2188)/100-1) -> -0.035945126 | N19: =IFERROR(LOOKUP(2,1/('Daily Prices'!$A$3:$A$2188<DATE(2017,1,1)),'Growth Index'!C$3:C$2188)/LOOKUP(2,1/('Daily Prices'!$A$3:$A$2188<DATE(2016,1,1)),'Growth Index'!C$3:C$2188)-1,LOOKUP(2,1/('Daily Prices'!$A$3:$A$2188<DATE(2017,1,1)),'Growth Index'!C$3:C$2188)/100-1) -> 0.10547275
A20: 2017 | B20: =IFERROR(LOOKUP(2,1/('Daily Prices'!$A$3:$A$2188<DATE(2017,2,1)+0),'Growth Index'!C$3:C$2188)/LOOKUP(2,1/('Daily Prices'!$A$3:$A$2188<DATE(2017,1,1)),'Growth Index'!C$3:C$2188)-1,LOOKUP(2,1/('Daily Prices'!$A$3:$A$2188<DATE(2017,2,1)+0),'Growth Index'!C$3:C$2188)/100-1) -> 0.051589658 | C20: =IFERROR(LOOKUP(2,1/('Daily Prices'!$A$3:$A$2188<DATE(2017,3,1)+0),'Growth Index'!C$3:C$2188)/LOOKUP(2,1/('Daily Prices'!$A$3:$A$2188<DATE(2017,2,1)),'Growth Index'!C$3:C$2188)-1,LOOKUP(2,1/('Daily Prices'!$A$3:$A$2188<DATE(2017,3,1)+0),'Growth Index'!C$3:C$2188)/100-1) -> 0.022671981 | D20: =IFERROR(LOOKUP(2,1/('Daily Prices'!$A$3:$A$2188<DATE(2017,4,1)+0),'Growth Index'!C$3:C$2188)/LOOKUP(2,1/('Daily Prices'!$A$3:$A$2188<DATE(2017,3,1)),'Growth Index'!C$3:C$2188)-1,LOOKUP(2,1/('Daily Prices'!$A$3:$A$2188<DATE(2017,4,1)+0),'Growth Index'!C$3:C$2188)/100-1) -> -0.035758265 | E20: =IFERROR(LOOKUP(2,1/('Daily Prices'!$A$3:$A$2188<DATE(2017,5,1)+0),'Growth Index'!C$3:C$2188)/LOOKUP(2,1/('Daily Prices'!$A$3:$A$2188<DATE(2017,4,1)),'Growth Index'!C$3:C$2188)-1,LOOKUP(2,1/('Daily Prices'!$A$3:$A$2188<DATE(2017,5,1)+0),'Growth Index'!C$3:C$2188)/100-1) -> 0.008111862 | F20: =IFERROR(LOOKUP(2,1/('Daily Prices'!$A$3:$A$2188<DATE(2017,6,1)+0),'Growth Index'!C$3:C$2188)/LOOKUP(2,1/('Daily Prices'!$A$3:$A$2188<DATE(2017,5,1)),'Growth Index'!C$3:C$2188)-1,LOOKUP(2,1/('Daily Prices'!$A$3:$A$2188<DATE(2017,6,1)+0),'Growth Index'!C$3:C$2188)/100-1) -> 0.0035218262 | G20: =IFERROR(LOOKUP(2,1/('Daily Prices'!$A$3:$A$2188<DATE(2017,7,1)+0),'Growth Index'!C$3:C$2188)/LOOKUP(2,1/('Daily Prices'!$A$3:$A$2188<DATE(2017,6,1)),'Growth Index'!C$3:C$2188)-1,LOOKUP(2,1/('Daily Prices'!$A$3:$A$2188<DATE(2017,7,1)+0),'Growth Index'!C$3:C$2188)/100-1) -> -0.017304456 | H20: =IFERROR(LOOKUP(2,1/('Daily Prices'!$A$3:$A$2188<DATE(2017,8,1)+0),'Growth Index'!C$3:C$2188)/LOOKUP(2,1/('Daily Prices'!$A$3:$A$2188<DATE(2017,7,1)),'Growth Index'!C$3:C$2188)-1,LOOKUP(2,1/('Daily Prices'!$A$3:$A$2188<DATE(2017,8,1)+0),'Growth Index'!C$3:C$2188)/100-1) -> 0.013333322 | I20: =IFERROR(LOOKUP(2,1/('Daily Prices'!$A$3:$A$2188<DATE(2017,9,1)+0),'Growth Index'!C$3:C$2188)/LOOKUP(2,1/('Daily Prices'!$A$3:$A$2188<DATE(2017,8,1)),'Growth Index'!C$3:C$2188)-1,LOOKUP(2,1/('Daily Prices'!$A$3:$A$2188<DATE(2017,9,1)+0),'Growth Index'!C$3:C$2188)/100-1) -> 0.031733965 | J20: =IFERROR(LOOKUP(2,1/('Daily Prices'!$A$3:$A$2188<DATE(2017,10,1)+0),'Growth Index'!C$3:C$2188)/LOOKUP(2,1/('Daily Prices'!$A$3:$A$2188<DATE(2017,9,1)),'Growth Index'!C$3:C$2188)-1,LOOKUP(2,1/('Daily Prices'!$A$3:$A$2188<DATE(2017,10,1)+0),'Growth Index'!C$3:C$2188)/100-1) -> -0.00089591076 | K20: =IFERROR(LOOKUP(2,1/('Daily Prices'!$A$3:$A$2188<DATE(2017,11,1)+0),'Growth Index'!C$3:C$2188)/LOOKUP(2,1/('Daily Prices'!$A$3:$A$2188<DATE(2017,10,1)),'Growth Index'!C$3:C$2188)-1,LOOKUP(2,1/('Daily Prices'!$A$3:$A$2188<DATE(2017,11,1)+0),'Growth Index'!C$3:C$2188)/100-1) -> -0.020537127 | L20: =IFERROR(LOOKUP(2,1/('Daily Prices'!$A$3:$A$2188<DATE(2017,12,1)+0),'Growth Index'!C$3:C$2188)/LOOKUP(2,1/('Daily Prices'!$A$3:$A$2188<DATE(2017,11,1)),'Growth Index'!C$3:C$2188)-1,LOOKUP(2,1/('Daily Prices'!$A$3:$A$2188<DATE(2017,12,1)+0),'Growth Index'!C$3:C$2188)/100-1) -> 0.0065017601 | M20: =IFERROR(LOOKUP(2,1/('Daily Prices'!$A$3:$A$2188<DATE(2018,1,1)),'Growth Index'!C$3:C$2188)/LOOKUP(2,1/('Daily Prices'!$A$3:$A$2188<DATE(2017,12,1)),'Growth Index'!C$3:C$2188)-1,LOOKUP(2,1/('Daily Prices'!$A$3:$A$2188<DATE(2018,1,1)),'Growth Index'!C$3:C$2188)/100-1) -> 0.00038530163 | N20: =IFERROR(LOOKUP(2,1/('Daily Prices'!$A$3:$A$2188<DATE(2018,1,1)),'Growth Index'!C$3:C$2188)/LOOKUP(2,1/('Daily Prices'!$A$3:$A$2188<DATE(2017,1,1)),'Growth Index'!C$3:C$2188)-1,LOOKUP(2,1/('Daily Prices'!$A$3:$A$2188<DATE(2018,1,1)),'Growth Index'!C$3:C$2188)/100-1) -> 0.061998077
A21: 2018 | B21: =IFERROR(LOOKUP(2,1/('Daily Prices'!$A$3:$A$2188<DATE(2018,2,1)+0),'Growth Index'!C$3:C$2188)/LOOKUP(2,1/('Daily Prices'!$A$3:$A$2188<DATE(2018,1,1)),'Growth Index'!C$3:C$2188)-1,LOOKUP(2,1/('Daily Prices'!$A$3:$A$2188<DATE(2018,2,1)+0),'Growth Index'!C$3:C$2188)/100-1) -> 0.035929899 | C21: =IFERROR(LOOKUP(2,1/('Daily Prices'!$A$3:$A$2188<DATE(2018,3,1)+0),'Growth Index'!C$3:C$2188)/LOOKUP(2,1/('Daily Prices'!$A$3:$A$2188<DATE(2018,2,1)),'Growth Index'!C$3:C$2188)-1,LOOKUP(2,1/('Daily Prices'!$A$3:$A$2188<DATE(2018,3,1)+0),'Growth Index'!C$3:C$2188)/100-1) -> 0.0026763381 | D21: =IFERROR(LOOKUP(2,1/('Daily Prices'!$A$3:$A$2188<DATE(2018,4,1)+0),'Growth Index'!C$3:C$2188)/LOOKUP(2,1/('Daily Prices'!$A$3:$A$2188<DATE(2018,3,1)),'Growth Index'!C$3:C$2188)-1,LOOKUP(2,1/('Daily Prices'!$A$3:$A$2188<DATE(2018,4,1)+0),'Growth Index'!C$3:C$2188)/100-1) -> 0.010527875 | E21: =IFERROR(LOOKUP(2,1/('Daily Prices'!$A$3:$A$2188<DATE(2018,5,1)+0),'Growth Index'!C$3:C$2188)/LOOKUP(2,1/('Daily Prices'!$A$3:$A$2188<DATE(2018,4,1)),'Growth Index'!C$3:C$2188)-1,LOOKUP(2,1/('Daily Prices'!$A$3:$A$2188<DATE(2018,5,1)+0),'Growth Index'!C$3:C$2188)/100-1) -> 0.0082059588 | F21: =IFERROR(LOOKUP(2,1/('Daily Prices'!$A$3:$A$2188<DATE(2018,6,1)+0),'Growth Index'!C$3:C$2188)/LOOKUP(2,1/('Daily Prices'!$A$3:$A$2188<DATE(2018,5,1)),'Growth Index'!C$3:C$2188)-1,LOOKUP(2,1/('Daily Prices'!$A$3:$A$2188<DATE(2018,6,1)+0),'Growth Index'!C$3:C$2188)/100-1) -> 0.005659949 | G21: =IFERROR(LOOKUP(2,1/('Daily Prices'!$A$3:$A$2188<DATE(2018,7,1)+0),'Growth Index'!C$3:C$2188)/LOOKUP(2,1/('Daily Prices'!$A$3:$A$2188<DATE(2018,6,1)),'Growth Index'!C$3:C$2188)-1,LOOKUP(2,1/('Daily Prices'!$A$3:$A$2188<DATE(2018,7,1)+0),'Growth Index'!C$3:C$2188)/100-1) -> -0.027067712 | H21: =IFERROR(LOOKUP(2,1/('Daily Prices'!$A$3:$A$2188<DATE(2018,8,1)+0),'Growth Index'!C$3:C$2188)/LOOKUP(2,1/('Daily Prices'!$A$3:$A$2188<DATE(2018,7,1)),'Growth Index'!C$3:C$2188)-1,LOOKUP(2,1/('Daily Prices'!$A$3:$A$2188<DATE(2018,8,1)+0),'Growth Index'!C$3:C$2188)/100-1) -> -0.023865232 | I21: =IFERROR(LOOKUP(2,1/('Daily Prices'!$A$3:$A$2188<DATE(2018,9,1)+0),'Growth Index'!C$3:C$2188)/LOOKUP(2,1/('Daily Prices'!$A$3:$A$2188<DATE(2018,8,1)),'Growth Index'!C$3:C$2188)-1,LOOKUP(2,1/('Daily Prices'!$A$3:$A$2188<DATE(2018,9,1)+0),'Growth Index'!C$3:C$2188)/100-1) -> 0.019508116 | J21: =IFERROR(LOOKUP(2,1/('Daily Prices'!$A$3:$A$2188<DATE(2018,10,1)+0),'Growth Index'!C$3:C$2188)/LOOKUP(2,1/('Daily Prices'!$A$3:$A$2188<DATE(2018,9,1)),'Growth Index'!C$3:C$2188)-1,LOOKUP(2,1/('Daily Prices'!$A$3:$A$2188<DATE(2018,10,1)+0),'Growth Index'!C$3:C$2188)/100-1) -> 0.010829157 | K21: =IFERROR(LOOKUP(2,1/('Daily Prices'!$A$3:$A$2188<DATE(2018,11,1)+0),'Growth Index'!C$3:C$2188)/LOOKUP(2,1/('Daily Prices'!$A$3:$A$2188<DATE(2018,10,1)),'Growth Index'!C$3:C$2188)-1,LOOKUP(2,1/('Daily Prices'!$A$3:$A$2188<DATE(2018,11,1)+0),'Growth Index'!C$3:C$2188)/100-1) -> 0.044637339 | L21: =IFERROR(LOOKUP(2,1/('Daily Prices'!$A$3:$A$2188<DATE(2018,12,1)+0),'Growth Index'!C$3:C$2188)/LOOKUP(2,1/('Daily Prices'!$A$3:$A$2188<DATE(2018,11,1)),'Growth Index'!C$3:C$2188)-1,LOOKUP(2,1/('Daily Prices'!$A$3:$A$2188<DATE(2018,12,1)+0),'Growth Index'!C$3:C$2188)/100-1) -> -0.056322683 | M21: =IFERROR(LOOKUP(2,1/('Daily Prices'!$A$3:$A$2188<DATE(2019,1,1)),'Growth Index'!C$3:C$2188)/LOOKUP(2,1/('Daily Prices'!$A$3:$A$2188<DATE(2018,12,1)),'Growth Index'!C$3:C$2188)-1,LOOKUP(2,1/('Daily Prices'!$A$3:$A$2188<DATE(2019,1,1)),'Growth Index'!C$3:C$2188)/100-1) -> 0.052963132 | N21: =IFERROR(LOOKUP(2,1/('Daily Prices'!$A$3:$A$2188<DATE(2019,1,1)),'Growth Index'!C$3:C$2188)/LOOKUP(2,1/('Daily Prices'!$A$3:$A$2188<DATE(2018,1,1)),'Growth Index'!C$3:C$2188)-1,LOOKUP(2,1/('Daily Prices'!$A$3:$A$2188<DATE(2019,1,1)),'Growth Index'!C$3:C$2188)/100-1) -> 0.081192236
A22: 2019 | B22: =IFERROR(LOOKUP(2,1/('Daily Prices'!$A$3:$A$2188<DATE(2019,2,1)+0),'Growth Index'!C$3:C$2188)/LOOKUP(2,1/('Daily Prices'!$A$3:$A$2188<DATE(2019,1,1)),'Growth Index'!C$3:C$2188)-1,LOOKUP(2,1/('Daily Prices'!$A$3:$A$2188<DATE(2019,2,1)+0),'Growth Index'!C$3:C$2188)/100-1) -> 0.050263118 | C22: =IFERROR(LOOKUP(2,1/('Daily Prices'!$A$3:$A$2188<DATE(2019,3,1)+0),'Growth Index'!C$3:C$2188)/LOOKUP(2,1/('Daily Prices'!$A$3:$A$2188<DATE(2019,2,1)),'Growth Index'!C$3:C$2188)-1,LOOKUP(2,1/('Daily Prices'!$A$3:$A$2188<DATE(2019,3,1)+0),'Growth Index'!C$3:C$2188)/100-1) -> -0.0049317137 | D22: =IFERROR(LOOKUP(2,1/('Daily Prices'!$A$3:$A$2188<DATE(2019,4,1)+0),'Growth Index'!C$3:C$2188)/LOOKUP(2,1/('Daily Prices'!$A$3:$A$2188<DATE(2019,3,1)),'Growth Index'!C$3:C$2188)-1,LOOKUP(2,1/('Daily Prices'!$A$3:$A$2188<DATE(2019,4,1)+0),'Growth Index'!C$3:C$2188)/100-1) -> -0.038933811 | E22: =IFERROR(LOOKUP(2,1/('Daily Prices'!$A$3:$A$2188<DATE(2019,5,1)+0),'Growth Index'!C$3:C$2188)/LOOKUP(2,1/('Daily Prices'!$A$3:$A$2188<DATE(2019,4,1)),'Growth Index'!C$3:C$2188)-1,LOOKUP(2,1/('Daily Prices'!$A$3:$A$2188<DATE(2019,5,1)+0),'Growth Index'!C$3:C$2188)/100-1) -> -0.006261595 | F22: =IFERROR(LOOKUP(2,1/('Daily Prices'!$A$3:$A$2188<DATE(2019,6,1)+0),'Growth Index'!C$3:C$2188)/LOOKUP(2,1/('Daily Prices'!$A$3:$A$2188<DATE(2019,5,1)),'Growth Index'!C$3:C$2188)-1,LOOKUP(2,1/('Daily Prices'!$A$3:$A$2188<DATE(2019,6,1)+0),'Growth Index'!C$3:C$2188)/100-1) -> 0.010272067 | G22: =IFERROR(LOOKUP(2,1/('Daily Prices'!$A$3:$A$2188<DATE(2019,7,1)+0),'Growth Index'!C$3:C$2188)/LOOKUP(2,1/('Daily Prices'!$A$3:$A$2188<DATE(2019,6,1)),'Growth Index'!C$3:C$2188)-1,LOOKUP(2,1/('Daily Prices'!$A$3:$A$2188<DATE(2019,7,1)+0),'Growth Index'!C$3:C$2188)/100-1) -> 0.077224453 | H22: =IFERROR(LOOKUP(2,1/('Daily Prices'!$A$3:$A$2188<DATE(2019,8,1)+0),'Growth Index'!C$3:C$2188)/LOOKUP(2,1/('Daily Prices'!$A$3:$A$2188<DATE(2019,7,1)),'Growth Index'!C$3:C$2188)-1,LOOKUP(2,1/('Daily Prices'!$A$3:$A$2188<DATE(2019,8,1)+0),'Growth Index'!C$3:C$2188)/100-1) -> 0.012380403 | I22: =IFERROR(LOOKUP(2,1/('Daily Prices'!$A$3:$A$2188<DATE(2019,9,1)+0),'Growth Index'!C$3:C$2188)/LOOKUP(2,1/('Daily Prices'!$A$3:$A$2188<DATE(2019,8,1)),'Growth Index'!C$3:C$2188)-1,LOOKUP(2,1/('Daily Prices'!$A$3:$A$2188<DATE(2019,9,1)+0),'Growth Index'!C$3:C$2188)/100-1) -> 0.11175457 | J22: =IFERROR(LOOKUP(2,1/('Daily Prices'!$A$3:$A$2188<DATE(2019,10,1)+0),'Growth Index'!C$3:C$2188)/LOOKUP(2,1/('Daily Prices'!$A$3:$A$2188<DATE(2019,9,1)),'Growth Index'!C$3:C$2188)-1,LOOKUP(2,1/('Daily Prices'!$A$3:$A$2188<DATE(2019,10,1)+0),'Growth Index'!C$3:C$2188)/100-1) -> -0.039742614 | K22: =IFERROR(LOOKUP(2,1/('Daily Prices'!$A$3:$A$2188<DATE(2019,11,1)+0),'Growth Index'!C$3:C$2188)/LOOKUP(2,1/('Daily Prices'!$A$3:$A$2188<DATE(2019,10,1)),'Growth Index'!C$3:C$2188)-1,LOOKUP(2,1/('Daily Prices'!$A$3:$A$2188<DATE(2019,11,1)+0),'Growth Index'!C$3:C$2188)/100-1) -> 0.022991234 | L22: =IFERROR(LOOKUP(2,1/('Daily Prices'!$A$3:$A$2188<DATE(2019,12,1)+0),'Growth Index'!C$3:C$2188)/LOOKUP(2,1/('Daily Prices'!$A$3:$A$2188<DATE(2019,11,1)),'Growth Index'!C$3:C$2188)-1,LOOKUP(2,1/('Daily Prices'!$A$3:$A$2188<DATE(2019,12,1)+0),'Growth Index'!C$3:C$2188)/100-1) -> -0.024047942 | M22: =IFERROR(LOOKUP(2,1/('Daily Prices'!$A$3:$A$2188<DATE(2020,1,1)),'Growth Index'!C$3:C$2188)/LOOKUP(2,1/('Daily Prices'!$A$3:$A$2188<DATE(2019,12,1)),'Growth Index'!C$3:C$2188)-1,LOOKUP(2,1/('Daily Prices'!$A$3:$A$2188<DATE(2020,1,1)),'Growth Index'!C$3:C$2188)/100-1) -> 0.030346876 | N22: =IFERROR(LOOKUP(2,1/('Daily Prices'!$A$3:$A$2188<DATE(2020,1,1)),'Growth Index'!C$3:C$2188)/LOOKUP(2,1/('Daily Prices'!$A$3:$A$2188<DATE(2019,1,1)),'Growth Index'!C$3:C$2188)-1,LOOKUP(2,1/('Daily Prices'!$A$3:$A$2188<DATE(2020,1,1)),'Growth Index'!C$3:C$2188)/100-1) -> 0.20766113
A23: 2020 | B23: =IFERROR(LOOKUP(2,1/('Daily Prices'!$A$3:$A$2188<DATE(2020,2,1)+0),'Growth Index'!C$3:C$2188)/LOOKUP(2,1/('Daily Prices'!$A$3:$A$2188<DATE(2020,1,1)),'Growth Index'!C$3:C$2188)-1,LOOKUP(2,1/('Daily Prices'!$A$3:$A$2188<DATE(2020,2,1)+0),'Growth Index'!C$3:C$2188)/100-1) -> 0.049993901 | C23: =IFERROR(LOOKUP(2,1/('Daily Prices'!$A$3:$A$2188<DATE(2020,3,1)+0),'Growth Index'!C$3:C$2188)/LOOKUP(2,1/('Daily Prices'!$A$3:$A$2188<DATE(2020,2,1)),'Growth Index'!C$3:C$2188)-1,LOOKUP(2,1/('Daily Prices'!$A$3:$A$2188<DATE(2020,3,1)+0),'Growth Index'!C$3:C$2188)/100-1) -> 0.028984963 | D23: =IFERROR(LOOKUP(2,1/('Daily Prices'!$A$3:$A$2188<DATE(2020,4,1)+0),'Growth Index'!C$3:C$2188)/LOOKUP(2,1/('Daily Prices'!$A$3:$A$2188<DATE(2020,3,1)),'Growth Index'!C$3:C$2188)-1,LOOKUP(2,1/('Daily Prices'!$A$3:$A$2188<DATE(2020,4,1)+0),'Growth Index'!C$3:C$2188)/100-1) -> 0.039543495 | E23: =IFERROR(LOOKUP(2,1/('Daily Prices'!$A$3:$A$2188<DATE(2020,5,1)+0),'Growth Index'!C$3:C$2188)/LOOKUP(2,1/('Daily Prices'!$A$3:$A$2188<DATE(2020,4,1)),'Growth Index'!C$3:C$2188)-1,LOOKUP(2,1/('Daily Prices'!$A$3:$A$2188<DATE(2020,5,1)+0),'Growth Index'!C$3:C$2188)/100-1) -> 0.056140918 | F23: =IFERROR(LOOKUP(2,1/('Daily Prices'!$A$3:$A$2188<DATE(2020,6,1)+0),'Growth Index'!C$3:C$2188)/LOOKUP(2,1/('Daily Prices'!$A$3:$A$2188<DATE(2020,5,1)),'Growth Index'!C$3:C$2188)-1,LOOKUP(2,1/('Daily Prices'!$A$3:$A$2188<DATE(2020,6,1)+0),'Growth Index'!C$3:C$2188)/100-1) -> 0.020119165 | G23: =IFERROR(LOOKUP(2,1/('Daily Prices'!$A$3:$A$2188<DATE(2020,7,1)+0),'Growth Index'!C$3:C$2188)/LOOKUP(2,1/('Daily Prices'!$A$3:$A$2188<DATE(2020,6,1)),'Growth Index'!C$3:C$2188)-1,LOOKUP(2,1/('Daily Prices'!$A$3:$A$2188<DATE(2020,7,1)+0),'Growth Index'!C$3:C$2188)/100-1) -> 0.022399285 | H23: =IFERROR(LOOKUP(2,1/('Daily Prices'!$A$3:$A$2188<DATE(2020,8,1)+0),'Growth Index'!C$3:C$2188)/LOOKUP(2,1/('Daily Prices'!$A$3:$A$2188<DATE(2020,7,1)),'Growth Index'!C$3:C$2188)-1,LOOKUP(2,1/('Daily Prices'!$A$3:$A$2188<DATE(2020,8,1)+0),'Growth Index'!C$3:C$2188)/100-1) -> 0.10202742 | I23: =IFERROR(LOOKUP(2,1/('Daily Prices'!$A$3:$A$2188<DATE(2020,9,1)+0),'Growth Index'!C$3:C$2188)/LOOKUP(2,1/('Daily Prices'!$A$3:$A$2188<DATE(2020,8,1)),'Growth Index'!C$3:C$2188)-1,LOOKUP(2,1/('Daily Prices'!$A$3:$A$2188<DATE(2020,9,1)+0),'Growth Index'!C$3:C$2188)/100-1) -> -0.026787326 | J23: =IFERROR(LOOKUP(2,1/('Daily Prices'!$A$3:$A$2188<DATE(2020,10,1)+0),'Growth Index'!C$3:C$2188)/LOOKUP(2,1/('Daily Prices'!$A$3:$A$2188<DATE(2020,9,1)),'Growth Index'!C$3:C$2188)-1,LOOKUP(2,1/('Daily Prices'!$A$3:$A$2188<DATE(2020,10,1)+0),'Growth Index'!C$3:C$2188)/100-1) -> -0.031068222 | K23: =IFERROR(LOOKUP(2,1/('Daily Prices'!$A$3:$A$2188<DATE(2020,11,1)+0),'Growth Index'!C$3:C$2188)/LOOKUP(2,1/('Daily Prices'!$A$3:$A$2188<DATE(2020,10,1)),'Growth Index'!C$3:C$2188)-1,LOOKUP(2,1/('Daily Prices'!$A$3:$A$2188<DATE(2020,11,1)+0),'Growth Index'!C$3:C$2188)/100-1) -> 0.011125203 | L23: =IFERROR(LOOKUP(2,1/('Daily Prices'!$A$3:$A$2188<DATE(2020,12,1)+0),'Growth Index'!C$3:C$2188)/LOOKUP(2,1/('Daily Prices'!$A$3:$A$2188<DATE(2020,11,1)),'Growth Index'!C$3:C$2188)-1,LOOKUP(2,1/('Daily Prices'!$A$3:$A$2188<DATE(2020,12,1)+0),'Growth Index'!C$3:C$2188)/100-1) -> -0.061999981 | M23: =IFERROR(LOOKUP(2,1/('Daily Prices'!$A$3:$A$2188<DATE(2021,1,1)),'Growth Index'!C$3:C$2188)/LOOKUP(2,1/('Daily Prices'!$A$3:$A$2188<DATE(2020,12,1)),'Growth Index'!C$3:C$2188)-1,LOOKUP(2,1/('Daily Prices'!$A$3:$A$2188<DATE(2021,1,1)),'Growth Index'!C$3:C$2188)/100-1) -> 0.049030198 | N23: =IFERROR(LOOKUP(2,1/('Daily Prices'!$A$3:$A$2188<DATE(2021,1,1)),'Growth Index'!C$3:C$2188)/LOOKUP(2,1/('Daily Prices'!$A$3:$A$2188<DATE(2020,1,1)),'Growth Index'!C$3:C$2188)-1,LOOKUP(2,1/('Daily Prices'!$A$3:$A$2188<DATE(2021,1,1)),'Growth Index'!C$3:C$2188)/100-1) -> 0.27914834
A24: 2021 | B24: =IFERROR(LOOKUP(2,1/('Daily Prices'!$A$3:$A$2188<DATE(2021,2,1)+0),'Growth Index'!C$3:C$2188)/LOOKUP(2,1/('Daily Prices'!$A$3:$A$2188<DATE(2021,1,1)),'Growth Index'!C$3:C$2188)-1,LOOKUP(2,1/('Daily Prices'!$A$3:$A$2188<DATE(2021,2,1)+0),'Growth Index'!C$3:C$2188)/100-1) -> -0.016469386 | C24: =IFERROR(LOOKUP(2,1/('Daily Prices'!$A$3:$A$2188<DATE(2021,3,1)+0),'Growth Index'!C$3:C$2188)/LOOKUP(2,1/('Daily Prices'!$A$3:$A$2188<DATE(2021,2,1)),'Growth Index'!C$3:C$2188)-1,LOOKUP(2,1/('Daily Prices'!$A$3:$A$2188<DATE(2021,3,1)+0),'Growth Index'!C$3:C$2188)/100-1) -> -0.051938519 | D24: =IFERROR(LOOKUP(2,1/('Daily Prices'!$A$3:$A$2188<DATE(2021,4,1)+0),'Growth Index'!C$3:C$2188)/LOOKUP(2,1/('Daily Prices'!$A$3:$A$2188<DATE(2021,3,1)),'Growth Index'!C$3:C$2188)-1,LOOKUP(2,1/('Daily Prices'!$A$3:$A$2188<DATE(2021,4,1)+0),'Growth Index'!C$3:C$2188)/100-1) -> -0.039339709 | E24: =IFERROR(LOOKUP(2,1/('Daily Prices'!$A$3:$A$2188<DATE(2021,5,1)+0),'Growth Index'!C$3:C$2188)/LOOKUP(2,1/('Daily Prices'!$A$3:$A$2188<DATE(2021,4,1)),'Growth Index'!C$3:C$2188)-1,LOOKUP(2,1/('Daily Prices'!$A$3:$A$2188<DATE(2021,5,1)+0),'Growth Index'!C$3:C$2188)/100-1) -> 0.057250277 | F24: =IFERROR(LOOKUP(2,1/('Daily Prices'!$A$3:$A$2188<DATE(2021,6,1)+0),'Growth Index'!C$3:C$2188)/LOOKUP(2,1/('Daily Prices'!$A$3:$A$2188<DATE(2021,5,1)),'Growth Index'!C$3:C$2188)-1,LOOKUP(2,1/('Daily Prices'!$A$3:$A$2188<DATE(2021,6,1)+0),'Growth Index'!C$3:C$2188)/100-1) -> 0.052065117 | G24: =IFERROR(LOOKUP(2,1/('Daily Prices'!$A$3:$A$2188<DATE(2021,7,1)+0),'Growth Index'!C$3:C$2188)/LOOKUP(2,1/('Daily Prices'!$A$3:$A$2188<DATE(2021,6,1)),'Growth Index'!C$3:C$2188)-1,LOOKUP(2,1/('Daily Prices'!$A$3:$A$2188<DATE(2021,7,1)+0),'Growth Index'!C$3:C$2188)/100-1) -> -0.04730992 | H24: =IFERROR(LOOKUP(2,1/('Daily Prices'!$A$3:$A$2188<DATE(2021,8,1)+0),'Growth Index'!C$3:C$2188)/LOOKUP(2,1/('Daily Prices'!$A$3:$A$2188<DATE(2021,7,1)),'Growth Index'!C$3:C$2188)-1,LOOKUP(2,1/('Daily Prices'!$A$3:$A$2188<DATE(2021,8,1)+0),'Growth Index'!C$3:C$2188)/100-1) -> 0.035419756 | I24: =IFERROR(LOOKUP(2,1/('Daily Prices'!$A$3:$A$2188<DATE(2021,9,1)+0),'Growth Index'!C$3:C$2188)/LOOKUP(2,1/('Daily Prices'!$A$3:$A$2188<DATE(2021,8,1)),'Growth Index'!C$3:C$2188)-1,LOOKUP(2,1/('Daily Prices'!$A$3:$A$2188<DATE(2021,9,1)+0),'Growth Index'!C$3:C$2188)/100-1) -> -0.024371886 | J24: =IFERROR(LOOKUP(2,1/('Daily Prices'!$A$3:$A$2188<DATE(2021,10,1)+0),'Growth Index'!C$3:C$2188)/LOOKUP(2,1/('Daily Prices'!$A$3:$A$2188<DATE(2021,9,1)),'Growth Index'!C$3:C$2188)-1,LOOKUP(2,1/('Daily Prices'!$A$3:$A$2188<DATE(2021,10,1)+0),'Growth Index'!C$3:C$2188)/100-1) -> -0.02292858 | K24: =IFERROR(LOOKUP(2,1/('Daily Prices'!$A$3:$A$2188<DATE(2021,11,1)+0),'Growth Index'!C$3:C$2188)/LOOKUP(2,1/('Daily Prices'!$A$3:$A$2188<DATE(2021,10,1)),'Growth Index'!C$3:C$2188)-1,LOOKUP(2,1/('Daily Prices'!$A$3:$A$2188<DATE(2021,11,1)+0),'Growth Index'!C$3:C$2188)/100-1) -> 0.025086097 | L24: =IFERROR(LOOKUP(2,1/('Daily Prices'!$A$3:$A$2188<DATE(2021,12,1)+0),'Growth Index'!C$3:C$2188)/LOOKUP(2,1/('Daily Prices'!$A$3:$A$2188<DATE(2021,11,1)),'Growth Index'!C$3:C$2188)-1,LOOKUP(2,1/('Daily Prices'!$A$3:$A$2188<DATE(2021,12,1)+0),'Growth Index'!C$3:C$2188)/100-1) -> 0.022142097 | M24: =IFERROR(LOOKUP(2,1/('Daily Prices'!$A$3:$A$2188<DATE(2022,1,1)),'Growth Index'!C$3:C$2188)/LOOKUP(2,1/('Daily Prices'!$A$3:$A$2188<DATE(2021,12,1)),'Growth Index'!C$3:C$2188)-1,LOOKUP(2,1/('Daily Prices'!$A$3:$A$2188<DATE(2022,1,1)),'Growth Index'!C$3:C$2188)/100-1) -> -0.0081001932 | N24: =IFERROR(LOOKUP(2,1/('Daily Prices'!$A$3:$A$2188<DATE(2022,1,1)),'Growth Index'!C$3:C$2188)/LOOKUP(2,1/('Daily Prices'!$A$3:$A$2188<DATE(2021,1,1)),'Growth Index'!C$3:C$2188)-1,LOOKUP(2,1/('Daily Prices'!$A$3:$A$2188<DATE(2022,1,1)),'Growth Index'!C$3:C$2188)/100-1) -> -0.02628293
A25: 2022 | B25: =IFERROR(LOOKUP(2,1/('Daily Prices'!$A$3:$A$2188<DATE(2022,2,1)+0),'Growth Index'!C$3:C$2188)/LOOKUP(2,1/('Daily Prices'!$A$3:$A$2188<DATE(2022,1,1)),'Growth Index'!C$3:C$2188)-1,LOOKUP(2,1/('Daily Prices'!$A$3:$A$2188<DATE(2022,2,1)+0),'Growth Index'!C$3:C$2188)/100-1) -> -0.0041877915 | C25: =IFERROR(LOOKUP(2,1/('Daily Prices'!$A$3:$A$2188<DATE(2022,3,1)+0),'Growth Index'!C$3:C$2188)/LOOKUP(2,1/('Daily Prices'!$A$3:$A$2188<DATE(2022,2,1)),'Growth Index'!C$3:C$2188)-1,LOOKUP(2,1/('Daily Prices'!$A$3:$A$2188<DATE(2022,3,1)+0),'Growth Index'!C$3:C$2188)/100-1) -> 0.0773258 | D25: =IFERROR(LOOKUP(2,1/('Daily Prices'!$A$3:$A$2188<DATE(2022,4,1)+0),'Growth Index'!C$3:C$2188)/LOOKUP(2,1/('Daily Prices'!$A$3:$A$2188<DATE(2022,3,1)),'Growth Index'!C$3:C$2188)-1,LOOKUP(2,1/('Daily Prices'!$A$3:$A$2188<DATE(2022,4,1)+0),'Growth Index'!C$3:C$2188)/100-1) -> 0.021874129 | E25: =IFERROR(LOOKUP(2,1/('Daily Prices'!$A$3:$A$2188<DATE(2022,5,1)+0),'Growth Index'!C$3:C$2188)/LOOKUP(2,1/('Daily Prices'!$A$3:$A$2188<DATE(2022,4,1)),'Growth Index'!C$3:C$2188)-1,LOOKUP(2,1/('Daily Prices'!$A$3:$A$2188<DATE(2022,5,1)+0),'Growth Index'!C$3:C$2188)/100-1) -> -0.0076732312 | F25: =IFERROR(LOOKUP(2,1/('Daily Prices'!$A$3:$A$2188<DATE(2022,6,1)+0),'Growth Index'!C$3:C$2188)/LOOKUP(2,1/('Daily Prices'!$A$3:$A$2188<DATE(2022,5,1)),'Growth Index'!C$3:C$2188)-1,LOOKUP(2,1/('Daily Prices'!$A$3:$A$2188<DATE(2022,6,1)+0),'Growth Index'!C$3:C$2188)/100-1) -> -0.024435397 | G25: =IFERROR(LOOKUP(2,1/('Daily Prices'!$A$3:$A$2188<DATE(2022,7,1)+0),'Growth Index'!C$3:C$2188)/LOOKUP(2,1/('Daily Prices'!$A$3:$A$2188<DATE(2022,6,1)),'Growth Index'!C$3:C$2188)-1,LOOKUP(2,1/('Daily Prices'!$A$3:$A$2188<DATE(2022,7,1)+0),'Growth Index'!C$3:C$2188)/100-1) -> 0.0049566186 | H25: =IFERROR(LOOKUP(2,1/('Daily Prices'!$A$3:$A$2188<DATE(2022,8,1)+0),'Growth Index'!C$3:C$2188)/LOOKUP(2,1/('Daily Prices'!$A$3:$A$2188<DATE(2022,7,1)),'Growth Index'!C$3:C$2188)-1,LOOKUP(2,1/('Daily Prices'!$A$3:$A$2188<DATE(2022,8,1)+0),'Growth Index'!C$3:C$2188)/100-1) -> -0.029318483 | I25: =IFERROR(LOOKUP(2,1/('Daily Prices'!$A$3:$A$2188<DATE(2022,9,1)+0),'Growth Index'!C$3:C$2188)/LOOKUP(2,1/('Daily Prices'!$A$3:$A$2188<DATE(2022,8,1)),'Growth Index'!C$3:C$2188)-1,LOOKUP(2,1/('Daily Prices'!$A$3:$A$2188<DATE(2022,9,1)+0),'Growth Index'!C$3:C$2188)/100-1) -> -0.010010308 | J25: =IFERROR(LOOKUP(2,1/('Daily Prices'!$A$3:$A$2188<DATE(2022,10,1)+0),'Growth Index'!C$3:C$2188)/LOOKUP(2,1/('Daily Prices'!$A$3:$A$2188<DATE(2022,9,1)),'Growth Index'!C$3:C$2188)-1,LOOKUP(2,1/('Daily Prices'!$A$3:$A$2188<DATE(2022,10,1)+0),'Growth Index'!C$3:C$2188)/100-1) -> -0.012826696 | K25: =IFERROR(LOOKUP(2,1/('Daily Prices'!$A$3:$A$2188<DATE(2022,11,1)+0),'Growth Index'!C$3:C$2188)/LOOKUP(2,1/('Daily Prices'!$A$3:$A$2188<DATE(2022,10,1)),'Growth Index'!C$3:C$2188)-1,LOOKUP(2,1/('Daily Prices'!$A$3:$A$2188<DATE(2022,11,1)+0),'Growth Index'!C$3:C$2188)/100-1) -> -0.0022629737 | L25: =IFERROR(LOOKUP(2,1/('Daily Prices'!$A$3:$A$2188<DATE(2022,12,1)+0),'Growth Index'!C$3:C$2188)/LOOKUP(2,1/('Daily Prices'!$A$3:$A$2188<DATE(2022,11,1)),'Growth Index'!C$3:C$2188)-1,LOOKUP(2,1/('Daily Prices'!$A$3:$A$2188<DATE(2022,12,1)+0),'Growth Index'!C$3:C$2188)/100-1) -> 0.052616649 | M25: =IFERROR(LOOKUP(2,1/('Daily Prices'!$A$3:$A$2188<DATE(2023,1,1)),'Growth Index'!C$3:C$2188)/LOOKUP(2,1/('Daily Prices'!$A$3:$A$2188<DATE(2022,12,1)),'Growth Index'!C$3:C$2188)-1,LOOKUP(2,1/('Daily Prices'!$A$3:$A$2188<DATE(2023,1,1)),'Growth Index'!C$3:C$2188)/100-1) -> 0.051303773 | N25: =IFERROR(LOOKUP(2,1/('Daily Prices'!$A$3:$A$2188<DATE(2023,1,1)),'Growth Index'!C$3:C$2188)/LOOKUP(2,1/('Daily Prices'!$A$3:$A$2188<DATE(2022,1,1)),'Growth Index'!C$3:C$2188)-1,LOOKUP(2,1/('Daily Prices'!$A$3:$A$2188<DATE(2023,1,1)),'Growth Index'!C$3:C$2188)/100-1) -> 0.11710848
A26: 2023 | B26: =IFERROR(LOOKUP(2,1/('Daily Prices'!$A$3:$A$2188<DATE(2023,2,1)+0),'Growth Index'!C$3:C$2188)/LOOKUP(2,1/('Daily Prices'!$A$3:$A$2188<DATE(2023,1,1)),'Growth Index'!C$3:C$2188)-1,LOOKUP(2,1/('Daily Prices'!$A$3:$A$2188<DATE(2023,2,1)+0),'Growth Index'!C$3:C$2188)/100-1) -> 0.046983462 | C26: =IFERROR(LOOKUP(2,1/('Daily Prices'!$A$3:$A$2188<DATE(2023,3,1)+0),'Growth Index'!C$3:C$2188)/LOOKUP(2,1/('Daily Prices'!$A$3:$A$2188<DATE(2023,2,1)),'Growth Index'!C$3:C$2188)-1,LOOKUP(2,1/('Daily Prices'!$A$3:$A$2188<DATE(2023,3,1)+0),'Growth Index'!C$3:C$2188)/100-1) -> -0.041464016 | D26: =IFERROR(LOOKUP(2,1/('Daily Prices'!$A$3:$A$2188<DATE(2023,4,1)+0),'Growth Index'!C$3:C$2188)/LOOKUP(2,1/('Daily Prices'!$A$3:$A$2188<DATE(2023,3,1)),'Growth Index'!C$3:C$2188)-1,LOOKUP(2,1/('Daily Prices'!$A$3:$A$2188<DATE(2023,4,1)+0),'Growth Index'!C$3:C$2188)/100-1) -> 0.078328116 | E26: =IFERROR(LOOKUP(2,1/('Daily Prices'!$A$3:$A$2188<DATE(2023,5,1)+0),'Growth Index'!C$3:C$2188)/LOOKUP(2,1/('Daily Prices'!$A$3:$A$2188<DATE(2023,4,1)),'Growth Index'!C$3:C$2188)-1,LOOKUP(2,1/('Daily Prices'!$A$3:$A$2188<DATE(2023,5,1)+0),'Growth Index'!C$3:C$2188)/100-1) -> -0.003300245 | F26: =IFERROR(LOOKUP(2,1/('Daily Prices'!$A$3:$A$2188<DATE(2023,6,1)+0),'Growth Index'!C$3:C$2188)/LOOKUP(2,1/('Daily Prices'!$A$3:$A$2188<DATE(2023,5,1)),'Growth Index'!C$3:C$2188)-1,LOOKUP(2,1/('Daily Prices'!$A$3:$A$2188<DATE(2023,6,1)+0),'Growth Index'!C$3:C$2188)/100-1) -> 0.0025276264 | G26: =IFERROR(LOOKUP(2,1/('Daily Prices'!$A$3:$A$2188<DATE(2023,7,1)+0),'Growth Index'!C$3:C$2188)/LOOKUP(2,1/('Daily Prices'!$A$3:$A$2188<DATE(2023,6,1)),'Growth Index'!C$3:C$2188)-1,LOOKUP(2,1/('Daily Prices'!$A$3:$A$2188<DATE(2023,7,1)+0),'Growth Index'!C$3:C$2188)/100-1) -> -0.034222236 | H26: =IFERROR(LOOKUP(2,1/('Daily Prices'!$A$3:$A$2188<DATE(2023,8,1)+0),'Growth Index'!C$3:C$2188)/LOOKUP(2,1/('Daily Prices'!$A$3:$A$2188<DATE(2023,7,1)),'Growth Index'!C$3:C$2188)-1,LOOKUP(2,1/('Daily Prices'!$A$3:$A$2188<DATE(2023,8,1)+0),'Growth Index'!C$3:C$2188)/100-1) -> 0.033141203 | I26: =IFERROR(LOOKUP(2,1/('Daily Prices'!$A$3:$A$2188<DATE(2023,9,1)+0),'Growth Index'!C$3:C$2188)/LOOKUP(2,1/('Daily Prices'!$A$3:$A$2188<DATE(2023,8,1)),'Growth Index'!C$3:C$2188)-1,LOOKUP(2,1/('Daily Prices'!$A$3:$A$2188<DATE(2023,9,1)+0),'Growth Index'!C$3:C$2188)/100-1) -> -0.0091042273 | J26: =IFERROR(LOOKUP(2,1/('Daily Prices'!$A$3:$A$2188<DATE(2023,10,1)+0),'Growth Index'!C$3:C$2188)/LOOKUP(2,1/('Daily Prices'!$A$3:$A$2188<DATE(2023,9,1)),'Growth Index'!C$3:C$2188)-1,LOOKUP(2,1/('Daily Prices'!$A$3:$A$2188<DATE(2023,10,1)+0),'Growth Index'!C$3:C$2188)/100-1) -> -0.032209334 | K26: =IFERROR(LOOKUP(2,1/('Daily Prices'!$A$3:$A$2188<DATE(2023,11,1)+0),'Growth Index'!C$3:C$2188)/LOOKUP(2,1/('Daily Prices'!$A$3:$A$2188<DATE(2023,10,1)),'Growth Index'!C$3:C$2188)-1,LOOKUP(2,1/('Daily Prices'!$A$3:$A$2188<DATE(2023,11,1)+0),'Growth Index'!C$3:C$2188)/100-1) -> 0.069845484 | L26: =IFERROR(LOOKUP(2,1/('Daily Prices'!$A$3:$A$2188<DATE(2023,12,1)+0),'Growth Index'!C$3:C$2188)/LOOKUP(2,1/('Daily Prices'!$A$3:$A$2188<DATE(2023,11,1)),'Growth Index'!C$3:C$2188)-1,LOOKUP(2,1/('Daily Prices'!$A$3:$A$2188<DATE(2023,12,1)+0),'Growth Index'!C$3:C$2188)/100-1) -> 0.020699022 | M26: =IFERROR(LOOKUP(2,1/('Daily Prices'!$A$3:$A$2188<DATE(2024,1,1)),'Growth Index'!C$3:C$2188)/LOOKUP(2,1/('Daily Prices'!$A$3:$A$2188<DATE(2023,12,1)),'Growth Index'!C$3:C$2188)-1,LOOKUP(2,1/('Daily Prices'!$A$3:$A$2188<DATE(2024,1,1)),'Growth Index'!C$3:C$2188)/100-1) -> 0.018426839 | N26: =IFERROR(LOOKUP(2,1/('Daily Prices'!$A$3:$A$2188<DATE(2024,1,1)),'Growth Index'!C$3:C$2188)/LOOKUP(2,1/('Daily Prices'!$A$3:$A$2188<DATE(2023,1,1)),'Growth Index'!C$3:C$2188)-1,LOOKUP(2,1/('Daily Prices'!$A$3:$A$2188<DATE(2024,1,1)),'Growth Index'!C$3:C$2188)/100-1) -> 0.1506805
A27: 2024 | B27: =IFERROR(LOOKUP(2,1/('Daily Prices'!$A$3:$A$2188<DATE(2024,2,1)+0),'Growth Index'!C$3:C$2188)/LOOKUP(2,1/('Daily Prices'!$A$3:$A$2188<DATE(2024,1,1)),'Growth Index'!C$3:C$2188)-1,LOOKUP(2,1/('Daily Prices'!$A$3:$A$2188<DATE(2024,2,1)+0),'Growth Index'!C$3:C$2188)/100-1) -> -0.014192251 | C27: =IFERROR(LOOKUP(2,1/('Daily Prices'!$A$3:$A$2188<DATE(2024,3,1)+0),'Growth Index'!C$3:C$2188)/LOOKUP(2,1/('Daily Prices'!$A$3:$A$2188<DATE(2024,2,1)),'Growth Index'!C$3:C$2188)-1,LOOKUP(2,1/('Daily Prices'!$A$3:$A$2188<DATE(2024,3,1)+0),'Growth Index'!C$3:C$2188)/100-1) -> -0.0037896429 | D27: =IFERROR(LOOKUP(2,1/('Daily Prices'!$A$3:$A$2188<DATE(2024,4,1)+0),'Growth Index'!C$3:C$2188)/LOOKUP(2,1/('Daily Prices'!$A$3:$A$2188<DATE(2024,3,1)),'Growth Index'!C$3:C$2188)-1,LOOKUP(2,1/('Daily Prices'!$A$3:$A$2188<DATE(2024,4,1)+0),'Growth Index'!C$3:C$2188)/100-1) -> 0.087358117 | E27: =IFERROR(LOOKUP(2,1/('Daily Prices'!$A$3:$A$2188<DATE(2024,5,1)+0),'Growth Index'!C$3:C$2188)/LOOKUP(2,1/('Daily Prices'!$A$3:$A$2188<DATE(2024,4,1)),'Growth Index'!C$3:C$2188)-1,LOOKUP(2,1/('Daily Prices'!$A$3:$A$2188<DATE(2024,5,1)+0),'Growth Index'!C$3:C$2188)/100-1) -> 0.043081649 | F27: =IFERROR(LOOKUP(2,1/('Daily Prices'!$A$3:$A$2188<DATE(2024,6,1)+0),'Growth Index'!C$3:C$2188)/LOOKUP(2,1/('Daily Prices'!$A$3:$A$2188<DATE(2024,5,1)),'Growth Index'!C$3:C$2188)-1,LOOKUP(2,1/('Daily Prices'!$A$3:$A$2188<DATE(2024,6,1)+0),'Growth Index'!C$3:C$2188)/100-1) -> 0.017642568 | G27: =IFERROR(LOOKUP(2,1/('Daily Prices'!$A$3:$A$2188<DATE(2024,7,1)+0),'Growth Index'!C$3:C$2188)/LOOKUP(2,1/('Daily Prices'!$A$3:$A$2188<DATE(2024,6,1)),'Growth Index'!C$3:C$2188)-1,LOOKUP(2,1/('Daily Prices'!$A$3:$A$2188<DATE(2024,7,1)+0),'Growth Index'!C$3:C$2188)/100-1) -> -0.008367467 | H27: =IFERROR(LOOKUP(2,1/('Daily Prices'!$A$3:$A$2188<DATE(2024,8,1)+0),'Growth Index'!C$3:C$2188)/LOOKUP(2,1/('Daily Prices'!$A$3:$A$2188<DATE(2024,7,1)),'Growth Index'!C$3:C$2188)-1,LOOKUP(2,1/('Daily Prices'!$A$3:$A$2188<DATE(2024,8,1)+0),'Growth Index'!C$3:C$2188)/100-1) -> 0.044966514 | I27: =IFERROR(LOOKUP(2,1/('Daily Prices'!$A$3:$A$2188<DATE(2024,9,1)+0),'Growth Index'!C$3:C$2188)/LOOKUP(2,1/('Daily Prices'!$A$3:$A$2188<DATE(2024,8,1)),'Growth Index'!C$3:C$2188)-1,LOOKUP(2,1/('Daily Prices'!$A$3:$A$2188<DATE(2024,9,1)+0),'Growth Index'!C$3:C$2188)/100-1) -> 0.038396548 | J27: =IFERROR(LOOKUP(2,1/('Daily Prices'!$A$3:$A$2188<DATE(2024,10,1)+0),'Growth Index'!C$3:C$2188)/LOOKUP(2,1/('Daily Prices'!$A$3:$A$2188<DATE(2024,9,1)),'Growth Index'!C$3:C$2188)-1,LOOKUP(2,1/('Daily Prices'!$A$3:$A$2188<DATE(2024,10,1)+0),'Growth Index'!C$3:C$2188)/100-1) -> 0.044919193 | K27: =IFERROR(LOOKUP(2,1/('Daily Prices'!$A$3:$A$2188<DATE(2024,11,1)+0),'Growth Index'!C$3:C$2188)/LOOKUP(2,1/('Daily Prices'!$A$3:$A$2188<DATE(2024,10,1)),'Growth Index'!C$3:C$2188)-1,LOOKUP(2,1/('Daily Prices'!$A$3:$A$2188<DATE(2024,11,1)+0),'Growth Index'!C$3:C$2188)/100-1) -> 0.043504807 | L27: =IFERROR(LOOKUP(2,1/('Daily Prices'!$A$3:$A$2188<DATE(2024,12,1)+0),'Growth Index'!C$3:C$2188)/LOOKUP(2,1/('Daily Prices'!$A$3:$A$2188<DATE(2024,11,1)),'Growth Index'!C$3:C$2188)-1,LOOKUP(2,1/('Daily Prices'!$A$3:$A$2188<DATE(2024,12,1)+0),'Growth Index'!C$3:C$2188)/100-1) -> -0.025087971 | M27: =IFERROR(LOOKUP(2,1/('Daily Prices'!$A$3:$A$2188<DATE(2025,1,1)),'Growth Index'!C$3:C$2188)/LOOKUP(2,1/('Daily Prices'!$A$3:$A$2188<DATE(2024,12,1)),'Growth Index'!C$3:C$2188)-1,LOOKUP(2,1/('Daily Prices'!$A$3:$A$2188<DATE(2025,1,1)),'Growth Index'!C$3:C$2188)/100-1) -> -0.0048573131 | N27: =IFERROR(LOOKUP(2,1/('Daily Prices'!$A$3:$A$2188<DATE(2025,1,1)),'Growth Index'!C$3:C$2188)/LOOKUP(2,1/('Daily Prices'!$A$3:$A$2188<DATE(2024,1,1)),'Growth Index'!C$3:C$2188)-1,LOOKUP(2,1/('Daily Prices'!$A$3:$A$2188<DATE(2025,1,1)),'Growth Index'!C$3:C$2188)/100-1) -> 0.29024972
A29: HDFC Flexi Cap
A30: Year | B30: Jan | C30: Feb | D30: Mar | E30: Apr | F30: May | G30: Jun | H30: Jul | I30: Aug | J30: Sep | K30: Oct | L30: Nov | M30: Dec | N30: Year
A31: 2015 | B31: =IFERROR(LOOKUP(2,1/('Daily Prices'!$A$3:$A$2188<DATE(2015,2,1)+0),'Growth Index'!D$3:D$2188)/LOOKUP(2,1/('Daily Prices'!$A$3:$A$2188<DATE(2015,1,1)),'Growth Index'!D$3:D$2188)-1,LOOKUP(2,1/('Daily Prices'!$A$3:$A$2188<DATE(2015,2,1)+0),'Growth Index'!D$3:D$2188)/100-1) -> 0.043735175 | C31: =IFERROR(LOOKUP(2,1/('Daily Prices'!$A$3:$A$2188<DATE(2015,3,1)+0),'Growth Index'!D$3:D$2188)/LOOKUP(2,1/('Daily Prices'!$A$3:$A$2188<DATE(2015,2,1)),'Growth Index'!D$3:D$2188)-1,LOOKUP(2,1/('Daily Prices'!$A$3:$A$2188<DATE(2015,3,1)+0),'Growth Index'!D$3:D$2188)/100-1) -> -0.0202162 | D31: =IFERROR(LOOKUP(2,1/('Daily Prices'!$A$3:$A$2188<DATE(2015,4,1)+0),'Growth Index'!D$3:D$2188)/LOOKUP(2,1/('Daily Prices'!$A$3:$A$2188<DATE(2015,3,1)),'Growth Index'!D$3:D$2188)-1,LOOKUP(2,1/('Daily Prices'!$A$3:$A$2188<DATE(2015,4,1)+0),'Growth Index'!D$3:D$2188)/100-1) -> -0.020600485 | E31: =IFERROR(LOOKUP(2,1/('Daily Prices'!$A$3:$A$2188<DATE(2015,5,1)+0),'Growth Index'!D$3:D$2188)/LOOKUP(2,1/('Daily Prices'!$A$3:$A$2188<DATE(2015,4,1)),'Growth Index'!D$3:D$2188)-1,LOOKUP(2,1/('Daily Prices'!$A$3:$A$2188<DATE(2015,5,1)+0),'Growth Index'!D$3:D$2188)/100-1) -> -0.019738566 | F31: =IFERROR(LOOKUP(2,1/('Daily Prices'!$A$3:$A$2188<DATE(2015,6,1)+0),'Growth Index'!D$3:D$2188)/LOOKUP(2,1/('Daily Prices'!$A$3:$A$2188<DATE(2015,5,1)),'Growth Index'!D$3:D$2188)-1,LOOKUP(2,1/('Daily Prices'!$A$3:$A$2188<DATE(2015,6,1)+0),'Growth Index'!D$3:D$2188)/100-1) -> 0.018040747 | G31: =IFERROR(LOOKUP(2,1/('Daily Prices'!$A$3:$A$2188<DATE(2015,7,1)+0),'Growth Index'!D$3:D$2188)/LOOKUP(2,1/('Daily Prices'!$A$3:$A$2188<DATE(2015,6,1)),'Growth Index'!D$3:D$2188)-1,LOOKUP(2,1/('Daily Prices'!$A$3:$A$2188<DATE(2015,7,1)+0),'Growth Index'!D$3:D$2188)/100-1) -> -0.0075311294 | H31: =IFERROR(LOOKUP(2,1/('Daily Prices'!$A$3:$A$2188<DATE(2015,8,1)+0),'Growth Index'!D$3:D$2188)/LOOKUP(2,1/('Daily Prices'!$A$3:$A$2188<DATE(2015,7,1)),'Growth Index'!D$3:D$2188)-1,LOOKUP(2,1/('Daily Prices'!$A$3:$A$2188<DATE(2015,8,1)+0),'Growth Index'!D$3:D$2188)/100-1) -> 0.034087999 | I31: =IFERROR(LOOKUP(2,1/('Daily Prices'!$A$3:$A$2188<DATE(2015,9,1)+0),'Growth Index'!D$3:D$2188)/LOOKUP(2,1/('Daily Prices'!$A$3:$A$2188<DATE(2015,8,1)),'Growth Index'!D$3:D$2188)-1,LOOKUP(2,1/('Daily Prices'!$A$3:$A$2188<DATE(2015,9,1)+0),'Growth Index'!D$3:D$2188)/100-1) -> -0.066483179 | J31: =IFERROR(LOOKUP(2,1/('Daily Prices'!$A$3:$A$2188<DATE(2015,10,1)+0),'Growth Index'!D$3:D$2188)/LOOKUP(2,1/('Daily Prices'!$A$3:$A$2188<DATE(2015,9,1)),'Growth Index'!D$3:D$2188)-1,LOOKUP(2,1/('Daily Prices'!$A$3:$A$2188<DATE(2015,10,1)+0),'Growth Index'!D$3:D$2188)/100-1) -> -0.0056094925 | K31: =IFERROR(LOOKUP(2,1/('Daily Prices'!$A$3:$A$2188<DATE(2015,11,1)+0),'Growth Index'!D$3:D$2188)/LOOKUP(2,1/('Daily Prices'!$A$3:$A$2188<DATE(2015,10,1)),'Growth Index'!D$3:D$2188)-1,LOOKUP(2,1/('Daily Prices'!$A$3:$A$2188<DATE(2015,11,1)+0),'Growth Index'!D$3:D$2188)/100-1) -> 0.014353044 | L31: =IFERROR(LOOKUP(2,1/('Daily Prices'!$A$3:$A$2188<DATE(2015,12,1)+0),'Growth Index'!D$3:D$2188)/LOOKUP(2,1/('Daily Prices'!$A$3:$A$2188<DATE(2015,11,1)),'Growth Index'!D$3:D$2188)-1,LOOKUP(2,1/('Daily Prices'!$A$3:$A$2188<DATE(2015,12,1)+0),'Growth Index'!D$3:D$2188)/100-1) -> 0.0093862125 | M31: =IFERROR(LOOKUP(2,1/('Daily Prices'!$A$3:$A$2188<DATE(2016,1,1)),'Growth Index'!D$3:D$2188)/LOOKUP(2,1/('Daily Prices'!$A$3:$A$2188<DATE(2015,12,1)),'Growth Index'!D$3:D$2188)-1,LOOKUP(2,1/('Daily Prices'!$A$3:$A$2188<DATE(2016,1,1)),'Growth Index'!D$3:D$2188)/100-1) -> -0.021506603 | N31: =IFERROR(LOOKUP(2,1/('Daily Prices'!$A$3:$A$2188<DATE(2016,1,1)),'Growth Index'!D$3:D$2188)/LOOKUP(2,1/('Daily Prices'!$A$3:$A$2188<DATE(2015,1,1)),'Growth Index'!D$3:D$2188)-1,LOOKUP(2,1/('Daily Prices'!$A$3:$A$2188<DATE(2016,1,1)),'Growth Index'!D$3:D$2188)/100-1) -> -0.046006423
A32: 2016 | B32: =IFERROR(LOOKUP(2,1/('Daily Prices'!$A$3:$A$2188<DATE(2016,2,1)+0),'Growth Index'!D$3:D$2188)/LOOKUP(2,1/('Daily Prices'!$A$3:$A$2188<DATE(2016,1,1)),'Growth Index'!D$3:D$2188)-1,LOOKUP(2,1/('Daily Prices'!$A$3:$A$2188<DATE(2016,2,1)+0),'Growth Index'!D$3:D$2188)/100-1) -> -0.086163534 | C32: =IFERROR(LOOKUP(2,1/('Daily Prices'!$A$3:$A$2188<DATE(2016,3,1)+0),'Growth Index'!D$3:D$2188)/LOOKUP(2,1/('Daily Prices'!$A$3:$A$2188<DATE(2016,2,1)),'Growth Index'!D$3:D$2188)-1,LOOKUP(2,1/('Daily Prices'!$A$3:$A$2188<DATE(2016,3,1)+0),'Growth Index'!D$3:D$2188)/100-1) -> -0.11048026 | D32: =IFERROR(LOOKUP(2,1/('Daily Prices'!$A$3:$A$2188<DATE(2016,4,1)+0),'Growth Index'!D$3:D$2188)/LOOKUP(2,1/('Daily Prices'!$A$3:$A$2188<DATE(2016,3,1)),'Growth Index'!D$3:D$2188)-1,LOOKUP(2,1/('Daily Prices'!$A$3:$A$2188<DATE(2016,4,1)+0),'Growth Index'!D$3:D$2188)/100-1) -> 0.15519584 | E32: =IFERROR(LOOKUP(2,1/('Daily Prices'!$A$3:$A$2188<DATE(2016,5,1)+0),'Growth Index'!D$3:D$2188)/LOOKUP(2,1/('Daily Prices'!$A$3:$A$2188<DATE(2016,4,1)),'Growth Index'!D$3:D$2188)-1,LOOKUP(2,1/('Daily Prices'!$A$3:$A$2188<DATE(2016,5,1)+0),'Growth Index'!D$3:D$2188)/100-1) -> 0.029810387 | F32: =IFERROR(LOOKUP(2,1/('Daily Prices'!$A$3:$A$2188<DATE(2016,6,1)+0),'Growth Index'!D$3:D$2188)/LOOKUP(2,1/('Daily Prices'!$A$3:$A$2188<DATE(2016,5,1)),'Growth Index'!D$3:D$2188)-1,LOOKUP(2,1/('Daily Prices'!$A$3:$A$2188<DATE(2016,6,1)+0),'Growth Index'!D$3:D$2188)/100-1) -> 0.044251694 | G32: =IFERROR(LOOKUP(2,1/('Daily Prices'!$A$3:$A$2188<DATE(2016,7,1)+0),'Growth Index'!D$3:D$2188)/LOOKUP(2,1/('Daily Prices'!$A$3:$A$2188<DATE(2016,6,1)),'Growth Index'!D$3:D$2188)-1,LOOKUP(2,1/('Daily Prices'!$A$3:$A$2188<DATE(2016,7,1)+0),'Growth Index'!D$3:D$2188)/100-1) -> 0.028908296 | H32: =IFERROR(LOOKUP(2,1/('Daily Prices'!$A$3:$A$2188<DATE(2016,8,1)+0),'Growth Index'!D$3:D$2188)/LOOKUP(2,1/('Daily Prices'!$A$3:$A$2188<DATE(2016,7,1)),'Growth Index'!D$3:D$2188)-1,LOOKUP(2,1/('Daily Prices'!$A$3:$A$2188<DATE(2016,8,1)+0),'Growth Index'!D$3:D$2188)/100-1) -> 0.054688575 | I32: =IFERROR(LOOKUP(2,1/('Daily Prices'!$A$3:$A$2188<DATE(2016,9,1)+0),'Growth Index'!D$3:D$2188)/LOOKUP(2,1/('Daily Prices'!$A$3:$A$2188<DATE(2016,8,1)),'Growth Index'!D$3:D$2188)-1,LOOKUP(2,1/('Daily Prices'!$A$3:$A$2188<DATE(2016,9,1)+0),'Growth Index'!D$3:D$2188)/100-1) -> 0.029867979 | J32: =IFERROR(LOOKUP(2,1/('Daily Prices'!$A$3:$A$2188<DATE(2016,10,1)+0),'Growth Index'!D$3:D$2188)/LOOKUP(2,1/('Daily Prices'!$A$3:$A$2188<DATE(2016,9,1)),'Growth Index'!D$3:D$2188)-1,LOOKUP(2,1/('Daily Prices'!$A$3:$A$2188<DATE(2016,10,1)+0),'Growth Index'!D$3:D$2188)/100-1) -> -0.00035874439 | K32: =IFERROR(LOOKUP(2,1/('Daily Prices'!$A$3:$A$2188<DATE(2016,11,1)+0),'Growth Index'!D$3:D$2188)/LOOKUP(2,1/('Daily Prices'!$A$3:$A$2188<DATE(2016,10,1)),'Growth Index'!D$3:D$2188)-1,LOOKUP(2,1/('Daily Prices'!$A$3:$A$2188<DATE(2016,11,1)+0),'Growth Index'!D$3:D$2188)/100-1) -> 0.026435688 | L32: =IFERROR(LOOKUP(2,1/('Daily Prices'!$A$3:$A$2188<DATE(2016,12,1)+0),'Growth Index'!D$3:D$2188)/LOOKUP(2,1/('Daily Prices'!$A$3:$A$2188<DATE(2016,11,1)),'Growth Index'!D$3:D$2188)-1,LOOKUP(2,1/('Daily Prices'!$A$3:$A$2188<DATE(2016,12,1)+0),'Growth Index'!D$3:D$2188)/100-1) -> -0.047424326 | M32: =IFERROR(LOOKUP(2,1/('Daily Prices'!$A$3:$A$2188<DATE(2017,1,1)),'Growth Index'!D$3:D$2188)/LOOKUP(2,1/('Daily Prices'!$A$3:$A$2188<DATE(2016,12,1)),'Growth Index'!D$3:D$2188)-1,LOOKUP(2,1/('Daily Prices'!$A$3:$A$2188<DATE(2017,1,1)),'Growth Index'!D$3:D$2188)/100-1) -> -0.019444976 | N32: =IFERROR(LOOKUP(2,1/('Daily Prices'!$A$3:$A$2188<DATE(2017,1,1)),'Growth Index'!D$3:D$2188)/LOOKUP(2,1/('Daily Prices'!$A$3:$A$2188<DATE(2016,1,1)),'Growth Index'!D$3:D$2188)-1,LOOKUP(2,1/('Daily Prices'!$A$3:$A$2188<DATE(2017,1,1)),'Growth Index'!D$3:D$2188)/100-1) -> 0.081613209
A33: 2017 | B33: =IFERROR(LOOKUP(2,1/('Daily Prices'!$A$3:$A$2188<DATE(2017,2,1)+0),'Growth Index'!D$3:D$2188)/LOOKUP(2,1/('Daily Prices'!$A$3:$A$2188<DATE(2017,1,1)),'Growth Index'!D$3:D$2188)-1,LOOKUP(2,1/('Daily Prices'!$A$3:$A$2188<DATE(2017,2,1)+0),'Growth Index'!D$3:D$2188)/100-1) -> 0.060417362 | C33: =IFERROR(LOOKUP(2,1/('Daily Prices'!$A$3:$A$2188<DATE(2017,3,1)+0),'Growth Index'!D$3:D$2188)/LOOKUP(2,1/('Daily Prices'!$A$3:$A$2188<DATE(2017,2,1)),'Growth Index'!D$3:D$2188)-1,LOOKUP(2,1/('Daily Prices'!$A$3:$A$2188<DATE(2017,3,1)+0),'Growth Index'!D$3:D$2188)/100-1) -> 0.036382786 | D33: =IFERROR(LOOKUP(2,1/('Daily Prices'!$A$3:$A$2188<DATE(2017,4,1)+0),'Growth Index'!D$3:D$2188)/LOOKUP(2,1/('Daily Prices'!$A$3:$A$2188<DATE(2017,3,1)),'Growth Index'!D$3:D$2188)-1,LOOKUP(2,1/('Daily Prices'!$A$3:$A$2188<DATE(2017,4,1)+0),'Growth Index'!D$3:D$2188)/100-1) -> 0.039592542 | E33: =IFERROR(LOOKUP(2,1/('Daily Prices'!$A$3:$A$2188<DATE(2017,5,1)+0),'Growth Index'!D$3:D$2188)/LOOKUP(2,1/('Daily Prices'!$A$3:$A$2188<DATE(2017,4,1)),'Growth Index'!D$3:D$2188)-1,LOOKUP(2,1/('Daily Prices'!$A$3:$A$2188<DATE(2017,5,1)+0),'Growth Index'!D$3:D$2188)/100-1) -> 0.035572285 | F33: =IFERROR(LOOKUP(2,1/('Daily Prices'!$A$3:$A$2188<DATE(2017,6,1)+0),'Growth Index'!D$3:D$2188)/LOOKUP(2,1/('Daily Prices'!$A$3:$A$2188<DATE(2017,5,1)),'Growth Index'!D$3:D$2188)-1,LOOKUP(2,1/('Daily Prices'!$A$3:$A$2188<DATE(2017,6,1)+0),'Growth Index'!D$3:D$2188)/100-1) -> 0.019575478 | G33: =IFERROR(LOOKUP(2,1/('Daily Prices'!$A$3:$A$2188<DATE(2017,7,1)+0),'Growth Index'!D$3:D$2188)/LOOKUP(2,1/('Daily Prices'!$A$3:$A$2188<DATE(2017,6,1)),'Growth Index'!D$3:D$2188)-1,LOOKUP(2,1/('Daily Prices'!$A$3:$A$2188<DATE(2017,7,1)+0),'Growth Index'!D$3:D$2188)/100-1) -> -0.0038753415 | H33: =IFERROR(LOOKUP(2,1/('Daily Prices'!$A$3:$A$2188<DATE(2017,8,1)+0),'Growth Index'!D$3:D$2188)/LOOKUP(2,1/('Daily Prices'!$A$3:$A$2188<DATE(2017,7,1)),'Growth Index'!D$3:D$2188)-1,LOOKUP(2,1/('Daily Prices'!$A$3:$A$2188<DATE(2017,8,1)+0),'Growth Index'!D$3:D$2188)/100-1) -> 0.066257309 | I33: =IFERROR(LOOKUP(2,1/('Daily Prices'!$A$3:$A$2188<DATE(2017,9,1)+0),'Growth Index'!D$3:D$2188)/LOOKUP(2,1/('Daily Prices'!$A$3:$A$2188<DATE(2017,8,1)),'Growth Index'!D$3:D$2188)-1,LOOKUP(2,1/('Daily Prices'!$A$3:$A$2188<DATE(2017,9,1)+0),'Growth Index'!D$3:D$2188)/100-1) -> -0.031677355 | J33: =IFERROR(LOOKUP(2,1/('Daily Prices'!$A$3:$A$2188<DATE(2017,10,1)+0),'Growth Index'!D$3:D$2188)/LOOKUP(2,1/('Daily Prices'!$A$3:$A$2188<DATE(2017,9,1)),'Growth Index'!D$3:D$2188)-1,LOOKUP(2,1/('Daily Prices'!$A$3:$A$2188<DATE(2017,10,1)+0),'Growth Index'!D$3:D$2188)/100-1) -> -0.017231598 | K33: =IFERROR(LOOKUP(2,1/('Daily Prices'!$A$3:$A$2188<DATE(2017,11,1)+0),'Growth Index'!D$3:D$2188)/LOOKUP(2,1/('Daily Prices'!$A$3:$A$2188<DATE(2017,10,1)),'Growth Index'!D$3:D$2188)-1,LOOKUP(2,1/('Daily Prices'!$A$3:$A$2188<DATE(2017,11,1)+0),'Growth Index'!D$3:D$2188)/100-1) -> 0.058095151 | L33: =IFERROR(LOOKUP(2,1/('Daily Prices'!$A$3:$A$2188<DATE(2017,12,1)+0),'Growth Index'!D$3:D$2188)/LOOKUP(2,1/('Daily Prices'!$A$3:$A$2188<DATE(2017,11,1)),'Growth Index'!D$3:D$2188)-1,LOOKUP(2,1/('Daily Prices'!$A$3:$A$2188<DATE(2017,12,1)+0),'Growth Index'!D$3:D$2188)/100-1) -> 0.040507734 | M33: =IFERROR(LOOKUP(2,1/('Daily Prices'!$A$3:$A$2188<DATE(2018,1,1)),'Growth Index'!D$3:D$2188)/LOOKUP(2,1/('Daily Prices'!$A$3:$A$2188<DATE(2017,12,1)),'Growth Index'!D$3:D$2188)-1,LOOKUP(2,1/('Daily Prices'!$A$3:$A$2188<DATE(2018,1,1)),'Growth Index'!D$3:D$2188)/100-1) -> 0.02836931 | N33: =IFERROR(LOOKUP(2,1/('Daily Prices'!$A$3:$A$2188<DATE(2018,1,1)),'Growth Index'!D$3:D$2188)/LOOKUP(2,1/('Daily Prices'!$A$3:$A$2188<DATE(2017,1,1)),'Growth Index'!D$3:D$2188)-1,LOOKUP(2,1/('Daily Prices'!$A$3:$A$2188<DATE(2018,1,1)),'Growth Index'!D$3:D$2188)/100-1) -> 0.38046724
A34: 2018 | B34: =IFERROR(LOOKUP(2,1/('Daily Prices'!$A$3:$A$2188<DATE(2018,2,1)+0),'Growth Index'!D$3:D$2188)/LOOKUP(2,1/('Daily Prices'!$A$3:$A$2188<DATE(2018,1,1)),'Growth Index'!D$3:D$2188)-1,LOOKUP(2,1/('Daily Prices'!$A$3:$A$2188<DATE(2018,2,1)+0),'Growth Index'!D$3:D$2188)/100-1) -> 0.030942192 | C34: =IFERROR(LOOKUP(2,1/('Daily Prices'!$A$3:$A$2188<DATE(2018,3,1)+0),'Growth Index'!D$3:D$2188)/LOOKUP(2,1/('Daily Prices'!$A$3:$A$2188<DATE(2018,2,1)),'Growth Index'!D$3:D$2188)-1,LOOKUP(2,1/('Daily Prices'!$A$3:$A$2188<DATE(2018,3,1)+0),'Growth Index'!D$3:D$2188)/100-1) -> -0.065789003 | D34: =IFERROR(LOOKUP(2,1/('Daily Prices'!$A$3:$A$2188<DATE(2018,4,1)+0),'Growth Index'!D$3:D$2188)/LOOKUP(2,1/('Daily Prices'!$A$3:$A$2188<DATE(2018,3,1)),'Growth Index'!D$3:D$2188)-1,LOOKUP(2,1/('Daily Prices'!$A$3:$A$2188<DATE(2018,4,1)+0),'Growth Index'!D$3:D$2188)/100-1) -> -0.056836404 | E34: =IFERROR(LOOKUP(2,1/('Daily Prices'!$A$3:$A$2188<DATE(2018,5,1)+0),'Growth Index'!D$3:D$2188)/LOOKUP(2,1/('Daily Prices'!$A$3:$A$2188<DATE(2018,4,1)),'Growth Index'!D$3:D$2188)-1,LOOKUP(2,1/('Daily Prices'!$A$3:$A$2188<DATE(2018,5,1)+0),'Growth Index'!D$3:D$2188)/100-1) -> 0.054976039 | F34: =IFERROR(LOOKUP(2,1/('Daily Prices'!$A$3:$A$2188<DATE(2018,6,1)+0),'Growth Index'!D$3:D$2188)/LOOKUP(2,1/('Daily Prices'!$A$3:$A$2188<DATE(2018,5,1)),'Growth Index'!D$3:D$2188)-1,LOOKUP(2,1/('Daily Prices'!$A$3:$A$2188<DATE(2018,6,1)+0),'Growth Index'!D$3:D$2188)/100-1) -> -0.017099748 | G34: =IFERROR(LOOKUP(2,1/('Daily Prices'!$A$3:$A$2188<DATE(2018,7,1)+0),'Growth Index'!D$3:D$2188)/LOOKUP(2,1/('Daily Prices'!$A$3:$A$2188<DATE(2018,6,1)),'Growth Index'!D$3:D$2188)-1,LOOKUP(2,1/('Daily Prices'!$A$3:$A$2188<DATE(2018,7,1)+0),'Growth Index'!D$3:D$2188)/100-1) -> -0.03329881 | H34: =IFERROR(LOOKUP(2,1/('Daily Prices'!$A$3:$A$2188<DATE(2018,8,1)+0),'Growth Index'!D$3:D$2188)/LOOKUP(2,1/('Daily Prices'!$A$3:$A$2188<DATE(2018,7,1)),'Growth Index'!D$3:D$2188)-1,LOOKUP(2,1/('Daily Prices'!$A$3:$A$2188<DATE(2018,8,1)+0),'Growth Index'!D$3:D$2188)/100-1) -> 0.071303031 | I34: =IFERROR(LOOKUP(2,1/('Daily Prices'!$A$3:$A$2188<DATE(2018,9,1)+0),'Growth Index'!D$3:D$2188)/LOOKUP(2,1/('Daily Prices'!$A$3:$A$2188<DATE(2018,8,1)),'Growth Index'!D$3:D$2188)-1,LOOKUP(2,1/('Daily Prices'!$A$3:$A$2188<DATE(2018,9,1)+0),'Growth Index'!D$3:D$2188)/100-1) -> 0.052850945 | J34: =IFERROR(LOOKUP(2,1/('Daily Prices'!$A$3:$A$2188<DATE(2018,10,1)+0),'Growth Index'!D$3:D$2188)/LOOKUP(2,1/('Daily Prices'!$A$3:$A$2188<DATE(2018,9,1)),'Growth Index'!D$3:D$2188)-1,LOOKUP(2,1/('Daily Prices'!$A$3:$A$2188<DATE(2018,10,1)+0),'Growth Index'!D$3:D$2188)/100-1) -> -0.078457143 | K34: =IFERROR(LOOKUP(2,1/('Daily Prices'!$A$3:$A$2188<DATE(2018,11,1)+0),'Growth Index'!D$3:D$2188)/LOOKUP(2,1/('Daily Prices'!$A$3:$A$2188<DATE(2018,10,1)),'Growth Index'!D$3:D$2188)-1,LOOKUP(2,1/('Daily Prices'!$A$3:$A$2188<DATE(2018,11,1)+0),'Growth Index'!D$3:D$2188)/100-1) -> -0.002555036 | L34: =IFERROR(LOOKUP(2,1/('Daily Prices'!$A$3:$A$2188<DATE(2018,12,1)+0),'Growth Index'!D$3:D$2188)/LOOKUP(2,1/('Daily Prices'!$A$3:$A$2188<DATE(2018,11,1)),'Growth Index'!D$3:D$2188)-1,LOOKUP(2,1/('Daily Prices'!$A$3:$A$2188<DATE(2018,12,1)+0),'Growth Index'!D$3:D$2188)/100-1) -> 0.0094970497 | M34: =IFERROR(LOOKUP(2,1/('Daily Prices'!$A$3:$A$2188<DATE(2019,1,1)),'Growth Index'!D$3:D$2188)/LOOKUP(2,1/('Daily Prices'!$A$3:$A$2188<DATE(2018,12,1)),'Growth Index'!D$3:D$2188)-1,LOOKUP(2,1/('Daily Prices'!$A$3:$A$2188<DATE(2019,1,1)),'Growth Index'!D$3:D$2188)/100-1) -> 0.021764207 | N34: =IFERROR(LOOKUP(2,1/('Daily Prices'!$A$3:$A$2188<DATE(2019,1,1)),'Growth Index'!D$3:D$2188)/LOOKUP(2,1/('Daily Prices'!$A$3:$A$2188<DATE(2018,1,1)),'Growth Index'!D$3:D$2188)-1,LOOKUP(2,1/('Daily Prices'!$A$3:$A$2188<DATE(2019,1,1)),'Growth Index'!D$3:D$2188)/100-1) -> -0.026244201
A35: 2019 | B35: =IFERROR(LOOKUP(2,1/('Daily Prices'!$A$3:$A$2188<DATE(2019,2,1)+0),'Growth Index'!D$3:D$2188)/LOOKUP(2,1/('Daily Prices'!$A$3:$A$2188<DATE(2019,1,1)),'Growth Index'!D$3:D$2188)-1,LOOKUP(2,1/('Daily Prices'!$A$3:$A$2188<DATE(2019,2,1)+0),'Growth Index'!D$3:D$2188)/100-1) -> 0.00042374228 | C35: =IFERROR(LOOKUP(2,1/('Daily Prices'!$A$3:$A$2188<DATE(2019,3,1)+0),'Growth Index'!D$3:D$2188)/LOOKUP(2,1/('Daily Prices'!$A$3:$A$2188<DATE(2019,2,1)),'Growth Index'!D$3:D$2188)-1,LOOKUP(2,1/('Daily Prices'!$A$3:$A$2188<DATE(2019,3,1)+0),'Growth Index'!D$3:D$2188)/100-1) -> -0.021114606 | D35: =IFERROR(LOOKUP(2,1/('Daily Prices'!$A$3:$A$2188<DATE(2019,4,1)+0),'Growth Index'!D$3:D$2188)/LOOKUP(2,1/('Daily Prices'!$A$3:$A$2188<DATE(2019,3,1)),'Growth Index'!D$3:D$2188)-1,LOOKUP(2,1/('Daily Prices'!$A$3:$A$2188<DATE(2019,4,1)+0),'Growth Index'!D$3:D$2188)/100-1) -> 0.10658614 | E35: =IFERROR(LOOKUP(2,1/('Daily Prices'!$A$3:$A$2188<DATE(2019,5,1)+0),'Growth Index'!D$3:D$2188)/LOOKUP(2,1/('Daily Prices'!$A$3:$A$2188<DATE(2019,4,1)),'Growth Index'!D$3:D$2188)-1,LOOKUP(2,1/('Daily Prices'!$A$3:$A$2188<DATE(2019,5,1)+0),'Growth Index'!D$3:D$2188)/100-1) -> -0.0098495544 | F35: =IFERROR(LOOKUP(2,1/('Daily Prices'!$A$3:$A$2188<DATE(2019,6,1)+0),'Growth Index'!D$3:D$2188)/LOOKUP(2,1/('Daily Prices'!$A$3:$A$2188<DATE(2019,5,1)),'Growth Index'!D$3:D$2188)-1,LOOKUP(2,1/('Daily Prices'!$A$3:$A$2188<DATE(2019,6,1)+0),'Growth Index'!D$3:D$2188)/100-1) -> 0.033554766 | G35: =IFERROR(LOOKUP(2,1/('Daily Prices'!$A$3:$A$2188<DATE(2019,7,1)+0),'Growth Index'!D$3:D$2188)/LOOKUP(2,1/('Daily Prices'!$A$3:$A$2188<DATE(2019,6,1)),'Growth Index'!D$3:D$2188)-1,LOOKUP(2,1/('Daily Prices'!$A$3:$A$2188<DATE(2019,7,1)+0),'Growth Index'!D$3:D$2188)/100-1) -> 0.0053915675 | H35: =IFERROR(LOOKUP(2,1/('Daily Prices'!$A$3:$A$2188<DATE(2019,8,1)+0),'Growth Index'!D$3:D$2188)/LOOKUP(2,1/('Daily Prices'!$A$3:$A$2188<DATE(2019,7,1)),'Growth Index'!D$3:D$2188)-1,LOOKUP(2,1/('Daily Prices'!$A$3:$A$2188<DATE(2019,8,1)+0),'Growth Index'!D$3:D$2188)/100-1) -> -0.076000119 | I35: =IFERROR(LOOKUP(2,1/('Daily Prices'!$A$3:$A$2188<DATE(2019,9,1)+0),'Growth Index'!D$3:D$2188)/LOOKUP(2,1/('Daily Prices'!$A$3:$A$2188<DATE(2019,8,1)),'Growth Index'!D$3:D$2188)-1,LOOKUP(2,1/('Daily Prices'!$A$3:$A$2188<DATE(2019,9,1)+0),'Growth Index'!D$3:D$2188)/100-1) -> -0.037181536 | J35: =IFERROR(LOOKUP(2,1/('Daily Prices'!$A$3:$A$2188<DATE(2019,10,1)+0),'Growth Index'!D$3:D$2188)/LOOKUP(2,1/('Daily Prices'!$A$3:$A$2188<DATE(2019,9,1)),'Growth Index'!D$3:D$2188)-1,LOOKUP(2,1/('Daily Prices'!$A$3:$A$2188<DATE(2019,10,1)+0),'Growth Index'!D$3:D$2188)/100-1) -> 0.0334622 | K35: =IFERROR(LOOKUP(2,1/('Daily Prices'!$A$3:$A$2188<DATE(2019,11,1)+0),'Growth Index'!D$3:D$2188)/LOOKUP(2,1/('Daily Prices'!$A$3:$A$2188<DATE(2019,10,1)),'Growth Index'!D$3:D$2188)-1,LOOKUP(2,1/('Daily Prices'!$A$3:$A$2188<DATE(2019,11,1)+0),'Growth Index'!D$3:D$2188)/100-1) -> 0.037629781 | L35: =IFERROR(LOOKUP(2,1/('Daily Prices'!$A$3:$A$2188<DATE(2019,12,1)+0),'Growth Index'!D$3:D$2188)/LOOKUP(2,1/('Daily Prices'!$A$3:$A$2188<DATE(2019,11,1)),'Growth Index'!D$3:D$2188)-1,LOOKUP(2,1/('Daily Prices'!$A$3:$A$2188<DATE(2019,12,1)+0),'Growth Index'!D$3:D$2188)/100-1) -> 0.0096844549 | M35: =IFERROR(LOOKUP(2,1/('Daily Prices'!$A$3:$A$2188<DATE(2020,1,1)),'Growth Index'!D$3:D$2188)/LOOKUP(2,1/('Daily Prices'!$A$3:$A$2188<DATE(2019,12,1)),'Growth Index'!D$3:D$2188)-1,LOOKUP(2,1/('Daily Prices'!$A$3:$A$2188<DATE(2020,1,1)),'Growth Index'!D$3:D$2188)/100-1) -> 0.00029590551 | N35: =IFERROR(LOOKUP(2,1/('Daily Prices'!$A$3:$A$2188<DATE(2020,1,1)),'Growth Index'!D$3:D$2188)/LOOKUP(2,1/('Daily Prices'!$A$3:$A$2188<DATE(2019,1,1)),'Growth Index'!D$3:D$2188)-1,LOOKUP(2,1/('Daily Prices'!$A$3:$A$2188<DATE(2020,1,1)),'Growth Index'!D$3:D$2188)/100-1) -> 0.074331963
A36: 2020 | B36: =IFERROR(LOOKUP(2,1/('Daily Prices'!$A$3:$A$2188<DATE(2020,2,1)+0),'Growth Index'!D$3:D$2188)/LOOKUP(2,1/('Daily Prices'!$A$3:$A$2188<DATE(2020,1,1)),'Growth Index'!D$3:D$2188)-1,LOOKUP(2,1/('Daily Prices'!$A$3:$A$2188<DATE(2020,2,1)+0),'Growth Index'!D$3:D$2188)/100-1) -> -0.018884456 | C36: =IFERROR(LOOKUP(2,1/('Daily Prices'!$A$3:$A$2188<DATE(2020,3,1)+0),'Growth Index'!D$3:D$2188)/LOOKUP(2,1/('Daily Prices'!$A$3:$A$2188<DATE(2020,2,1)),'Growth Index'!D$3:D$2188)-1,LOOKUP(2,1/('Daily Prices'!$A$3:$A$2188<DATE(2020,3,1)+0),'Growth Index'!D$3:D$2188)/100-1) -> -0.037707961 | D36: =IFERROR(LOOKUP(2,1/('Daily Prices'!$A$3:$A$2188<DATE(2020,4,1)+0),'Growth Index'!D$3:D$2188)/LOOKUP(2,1/('Daily Prices'!$A$3:$A$2188<DATE(2020,3,1)),'Growth Index'!D$3:D$2188)-1,LOOKUP(2,1/('Daily Prices'!$A$3:$A$2188<DATE(2020,4,1)+0),'Growth Index'!D$3:D$2188)/100-1) -> -0.27818611 | E36: =IFERROR(LOOKUP(2,1/('Daily Prices'!$A$3:$A$2188<DATE(2020,5,1)+0),'Growth Index'!D$3:D$2188)/LOOKUP(2,1/('Daily Prices'!$A$3:$A$2188<DATE(2020,4,1)),'Growth Index'!D$3:D$2188)-1,LOOKUP(2,1/('Daily Prices'!$A$3:$A$2188<DATE(2020,5,1)+0),'Growth Index'!D$3:D$2188)/100-1) -> 0.087583207 | F36: =IFERROR(LOOKUP(2,1/('Daily Prices'!$A$3:$A$2188<DATE(2020,6,1)+0),'Growth Index'!D$3:D$2188)/LOOKUP(2,1/('Daily Prices'!$A$3:$A$2188<DATE(2020,5,1)),'Growth Index'!D$3:D$2188)-1,LOOKUP(2,1/('Daily Prices'!$A$3:$A$2188<DATE(2020,6,1)+0),'Growth Index'!D$3:D$2188)/100-1) -> 0.004409549 | G36: =IFERROR(LOOKUP(2,1/('Daily Prices'!$A$3:$A$2188<DATE(2020,7,1)+0),'Growth Index'!D$3:D$2188)/LOOKUP(2,1/('Daily Prices'!$A$3:$A$2188<DATE(2020,6,1)),'Growth Index'!D$3:D$2188)-1,LOOKUP(2,1/('Daily Prices'!$A$3:$A$2188<DATE(2020,7,1)+0),'Growth Index'!D$3:D$2188)/100-1) -> 0.069835563 | H36: =IFERROR(LOOKUP(2,1/('Daily Prices'!$A$3:$A$2188<DATE(2020,8,1)+0),'Growth Index'!D$3:D$2188)/LOOKUP(2,1/('Daily Prices'!$A$3:$A$2188<DATE(2020,7,1)),'Growth Index'!D$3:D$2188)-1,LOOKUP(2,1/('Daily Prices'!$A$3:$A$2188<DATE(2020,8,1)+0),'Growth Index'!D$3:D$2188)/100-1) -> 0.046278936 | I36: =IFERROR(LOOKUP(2,1/('Daily Prices'!$A$3:$A$2188<DATE(2020,9,1)+0),'Growth Index'!D$3:D$2188)/LOOKUP(2,1/('Daily Prices'!$A$3:$A$2188<DATE(2020,8,1)),'Growth Index'!D$3:D$2188)-1,LOOKUP(2,1/('Daily Prices'!$A$3:$A$2188<DATE(2020,9,1)+0),'Growth Index'!D$3:D$2188)/100-1) -> 0.055169464 | J36: =IFERROR(LOOKUP(2,1/('Daily Prices'!$A$3:$A$2188<DATE(2020,10,1)+0),'Growth Index'!D$3:D$2188)/LOOKUP(2,1/('Daily Prices'!$A$3:$A$2188<DATE(2020,9,1)),'Growth Index'!D$3:D$2188)-1,LOOKUP(2,1/('Daily Prices'!$A$3:$A$2188<DATE(2020,10,1)+0),'Growth Index'!D$3:D$2188)/100-1) -> -0.052209633 | K36: =IFERROR(LOOKUP(2,1/('Daily Prices'!$A$3:$A$2188<DATE(2020,11,1)+0),'Growth Index'!D$3:D$2188)/LOOKUP(2,1/('Daily Prices'!$A$3:$A$2188<DATE(2020,10,1)),'Growth Index'!D$3:D$2188)-1,LOOKUP(2,1/('Daily Prices'!$A$3:$A$2188<DATE(2020,11,1)+0),'Growth Index'!D$3:D$2188)/100-1) -> 0.022544406 | L36: =IFERROR(LOOKUP(2,1/('Daily Prices'!$A$3:$A$2188<DATE(2020,12,1)+0),'Growth Index'!D$3:D$2188)/LOOKUP(2,1/('Daily Prices'!$A$3:$A$2188<DATE(2020,11,1)),'Growth Index'!D$3:D$2188)-1,LOOKUP(2,1/('Daily Prices'!$A$3:$A$2188<DATE(2020,12,1)+0),'Growth Index'!D$3:D$2188)/100-1) -> 0.14495516 | M36: =IFERROR(LOOKUP(2,1/('Daily Prices'!$A$3:$A$2188<DATE(2021,1,1)),'Growth Index'!D$3:D$2188)/LOOKUP(2,1/('Daily Prices'!$A$3:$A$2188<DATE(2020,12,1)),'Growth Index'!D$3:D$2188)-1,LOOKUP(2,1/('Daily Prices'!$A$3:$A$2188<DATE(2021,1,1)),'Growth Index'!D$3:D$2188)/100-1) -> 0.097178507 | N36: =IFERROR(LOOKUP(2,1/('Daily Prices'!$A$3:$A$2188<DATE(2021,1,1)),'Growth Index'!D$3:D$2188)/LOOKUP(2,1/('Daily Prices'!$A$3:$A$2188<DATE(2020,1,1)),'Growth Index'!D$3:D$2188)-1,LOOKUP(2,1/('Daily Prices'!$A$3:$A$2188<DATE(2021,1,1)),'Growth Index'!D$3:D$2188)/100-1) -> 0.070465251
A37: 2021 | B37: =IFERROR(LOOKUP(2,1/('Daily Prices'!$A$3:$A$2188<DATE(2021,2,1)+0),'Growth Index'!D$3:D$2188)/LOOKUP(2,1/('Daily Prices'!$A$3:$A$2188<DATE(2021,1,1)),'Growth Index'!D$3:D$2188)-1,LOOKUP(2,1/('Daily Prices'!$A$3:$A$2188<DATE(2021,2,1)+0),'Growth Index'!D$3:D$2188)/100-1) -> 0.073113821 | C37: =IFERROR(LOOKUP(2,1/('Daily Prices'!$A$3:$A$2188<DATE(2021,3,1)+0),'Growth Index'!D$3:D$2188)/LOOKUP(2,1/('Daily Prices'!$A$3:$A$2188<DATE(2021,2,1)),'Growth Index'!D$3:D$2188)-1,LOOKUP(2,1/('Daily Prices'!$A$3:$A$2188<DATE(2021,3,1)+0),'Growth Index'!D$3:D$2188)/100-1) -> 0.055981069 | D37: =IFERROR(LOOKUP(2,1/('Daily Prices'!$A$3:$A$2188<DATE(2021,4,1)+0),'Growth Index'!D$3:D$2188)/LOOKUP(2,1/('Daily Prices'!$A$3:$A$2188<DATE(2021,3,1)),'Growth Index'!D$3:D$2188)-1,LOOKUP(2,1/('Daily Prices'!$A$3:$A$2188<DATE(2021,4,1)+0),'Growth Index'!D$3:D$2188)/100-1) -> -0.01559693 | E37: =IFERROR(LOOKUP(2,1/('Daily Prices'!$A$3:$A$2188<DATE(2021,5,1)+0),'Growth Index'!D$3:D$2188)/LOOKUP(2,1/('Daily Prices'!$A$3:$A$2188<DATE(2021,4,1)),'Growth Index'!D$3:D$2188)-1,LOOKUP(2,1/('Daily Prices'!$A$3:$A$2188<DATE(2021,5,1)+0),'Growth Index'!D$3:D$2188)/100-1) -> -0.00085289607 | F37: =IFERROR(LOOKUP(2,1/('Daily Prices'!$A$3:$A$2188<DATE(2021,6,1)+0),'Growth Index'!D$3:D$2188)/LOOKUP(2,1/('Daily Prices'!$A$3:$A$2188<DATE(2021,5,1)),'Growth Index'!D$3:D$2188)-1,LOOKUP(2,1/('Daily Prices'!$A$3:$A$2188<DATE(2021,6,1)+0),'Growth Index'!D$3:D$2188)/100-1) -> 0.10041831 | G37: =IFERROR(LOOKUP(2,1/('Daily Prices'!$A$3:$A$2188<DATE(2021,7,1)+0),'Growth Index'!D$3:D$2188)/LOOKUP(2,1/('Daily Prices'!$A$3:$A$2188<DATE(2021,6,1)),'Growth Index'!D$3:D$2188)-1,LOOKUP(2,1/('Daily Prices'!$A$3:$A$2188<DATE(2021,7,1)+0),'Growth Index'!D$3:D$2188)/100-1) -> 0.012947022 | H37: =IFERROR(LOOKUP(2,1/('Daily Prices'!$A$3:$A$2188<DATE(2021,8,1)+0),'Growth Index'!D$3:D$2188)/LOOKUP(2,1/('Daily Prices'!$A$3:$A$2188<DATE(2021,7,1)),'Growth Index'!D$3:D$2188)-1,LOOKUP(2,1/('Daily Prices'!$A$3:$A$2188<DATE(2021,8,1)+0),'Growth Index'!D$3:D$2188)/100-1) -> 0.015452878 | I37: =IFERROR(LOOKUP(2,1/('Daily Prices'!$A$3:$A$2188<DATE(2021,9,1)+0),'Growth Index'!D$3:D$2188)/LOOKUP(2,1/('Daily Prices'!$A$3:$A$2188<DATE(2021,8,1)),'Growth Index'!D$3:D$2188)-1,LOOKUP(2,1/('Daily Prices'!$A$3:$A$2188<DATE(2021,9,1)+0),'Growth Index'!D$3:D$2188)/100-1) -> 0.029656248 | J37: =IFERROR(LOOKUP(2,1/('Daily Prices'!$A$3:$A$2188<DATE(2021,10,1)+0),'Growth Index'!D$3:D$2188)/LOOKUP(2,1/('Daily Prices'!$A$3:$A$2188<DATE(2021,9,1)),'Growth Index'!D$3:D$2188)-1,LOOKUP(2,1/('Daily Prices'!$A$3:$A$2188<DATE(2021,10,1)+0),'Growth Index'!D$3:D$2188)/100-1) -> 0.060689929 | K37: =IFERROR(LOOKUP(2,1/('Daily Prices'!$A$3:$A$2188<DATE(2021,11,1)+0),'Growth Index'!D$3:D$2188)/LOOKUP(2,1/('Daily Prices'!$A$3:$A$2188<DATE(2021,10,1)),'Growth Index'!D$3:D$2188)-1,LOOKUP(2,1/('Daily Prices'!$A$3:$A$2188<DATE(2021,11,1)+0),'Growth Index'!D$3:D$2188)/100-1) -> 0.015087524 | L37: =IFERROR(LOOKUP(2,1/('Daily Prices'!$A$3:$A$2188<DATE(2021,12,1)+0),'Growth Index'!D$3:D$2188)/LOOKUP(2,1/('Daily Prices'!$A$3:$A$2188<DATE(2021,11,1)),'Growth Index'!D$3:D$2188)-1,LOOKUP(2,1/('Daily Prices'!$A$3:$A$2188<DATE(2021,12,1)+0),'Growth Index'!D$3:D$2188)/100-1) -> -0.040383094 | M37: =IFERROR(LOOKUP(2,1/('Daily Prices'!$A$3:$A$2188<DATE(2022,1,1)),'Growth Index'!D$3:D$2188)/LOOKUP(2,1/('Daily Prices'!$A$3:$A$2188<DATE(2021,12,1)),'Growth Index'!D$3:D$2188)-1,LOOKUP(2,1/('Daily Prices'!$A$3:$A$2188<DATE(2022,1,1)),'Growth Index'!D$3:D$2188)/100-1) -> 0.020751034 | N37: =IFERROR(LOOKUP(2,1/('Daily Prices'!$A$3:$A$2188<DATE(2022,1,1)),'Growth Index'!D$3:D$2188)/LOOKUP(2,1/('Daily Prices'!$A$3:$A$2188<DATE(2021,1,1)),'Growth Index'!D$3:D$2188)-1,LOOKUP(2,1/('Daily Prices'!$A$3:$A$2188<DATE(2022,1,1)),'Growth Index'!D$3:D$2188)/100-1) -> 0.36996838
A38: 2022 | B38: =IFERROR(LOOKUP(2,1/('Daily Prices'!$A$3:$A$2188<DATE(2022,2,1)+0),'Growth Index'!D$3:D$2188)/LOOKUP(2,1/('Daily Prices'!$A$3:$A$2188<DATE(2022,1,1)),'Growth Index'!D$3:D$2188)-1,LOOKUP(2,1/('Daily Prices'!$A$3:$A$2188<DATE(2022,2,1)+0),'Growth Index'!D$3:D$2188)/100-1) -> 0.046945196 | C38: =IFERROR(LOOKUP(2,1/('Daily Prices'!$A$3:$A$2188<DATE(2022,3,1)+0),'Growth Index'!D$3:D$2188)/LOOKUP(2,1/('Daily Prices'!$A$3:$A$2188<DATE(2022,2,1)),'Growth Index'!D$3:D$2188)-1,LOOKUP(2,1/('Daily Prices'!$A$3:$A$2188<DATE(2022,3,1)+0),'Growth Index'!D$3:D$2188)/100-1) -> -0.049181697 | D38: =IFERROR(LOOKUP(2,1/('Daily Prices'!$A$3:$A$2188<DATE(2022,4,1)+0),'Growth Index'!D$3:D$2188)/LOOKUP(2,1/('Daily Prices'!$A$3:$A$2188<DATE(2022,3,1)),'Growth Index'!D$3:D$2188)-1,LOOKUP(2,1/('Daily Prices'!$A$3:$A$2188<DATE(2022,4,1)+0),'Growth Index'!D$3:D$2188)/100-1) -> 0.043898052 | E38: =IFERROR(LOOKUP(2,1/('Daily Prices'!$A$3:$A$2188<DATE(2022,5,1)+0),'Growth Index'!D$3:D$2188)/LOOKUP(2,1/('Daily Prices'!$A$3:$A$2188<DATE(2022,4,1)),'Growth Index'!D$3:D$2188)-1,LOOKUP(2,1/('Daily Prices'!$A$3:$A$2188<DATE(2022,5,1)+0),'Growth Index'!D$3:D$2188)/100-1) -> 0.0084329643 | F38: =IFERROR(LOOKUP(2,1/('Daily Prices'!$A$3:$A$2188<DATE(2022,6,1)+0),'Growth Index'!D$3:D$2188)/LOOKUP(2,1/('Daily Prices'!$A$3:$A$2188<DATE(2022,5,1)),'Growth Index'!D$3:D$2188)-1,LOOKUP(2,1/('Daily Prices'!$A$3:$A$2188<DATE(2022,6,1)+0),'Growth Index'!D$3:D$2188)/100-1) -> -0.020706742 | G38: =IFERROR(LOOKUP(2,1/('Daily Prices'!$A$3:$A$2188<DATE(2022,7,1)+0),'Growth Index'!D$3:D$2188)/LOOKUP(2,1/('Daily Prices'!$A$3:$A$2188<DATE(2022,6,1)),'Growth Index'!D$3:D$2188)-1,LOOKUP(2,1/('Daily Prices'!$A$3:$A$2188<DATE(2022,7,1)+0),'Growth Index'!D$3:D$2188)/100-1) -> -0.0383139 | H38: =IFERROR(LOOKUP(2,1/('Daily Prices'!$A$3:$A$2188<DATE(2022,8,1)+0),'Growth Index'!D$3:D$2188)/LOOKUP(2,1/('Daily Prices'!$A$3:$A$2188<DATE(2022,7,1)),'Growth Index'!D$3:D$2188)-1,LOOKUP(2,1/('Daily Prices'!$A$3:$A$2188<DATE(2022,8,1)+0),'Growth Index'!D$3:D$2188)/100-1) -> 0.093158047 | I38: =IFERROR(LOOKUP(2,1/('Daily Prices'!$A$3:$A$2188<DATE(2022,9,1)+0),'Growth Index'!D$3:D$2188)/LOOKUP(2,1/('Daily Prices'!$A$3:$A$2188<DATE(2022,8,1)),'Growth Index'!D$3:D$2188)-1,LOOKUP(2,1/('Daily Prices'!$A$3:$A$2188<DATE(2022,9,1)+0),'Growth Index'!D$3:D$2188)/100-1) -> 0.046526743 | J38: =IFERROR(LOOKUP(2,1/('Daily Prices'!$A$3:$A$2188<DATE(2022,10,1)+0),'Growth Index'!D$3:D$2188)/LOOKUP(2,1/('Daily Prices'!$A$3:$A$2188<DATE(2022,9,1)),'Growth Index'!D$3:D$2188)-1,LOOKUP(2,1/('Daily Prices'!$A$3:$A$2188<DATE(2022,10,1)+0),'Growth Index'!D$3:D$2188)/100-1) -> -0.02645834 | K38: =IFERROR(LOOKUP(2,1/('Daily Prices'!$A$3:$A$2188<DATE(2022,11,1)+0),'Growth Index'!D$3:D$2188)/LOOKUP(2,1/('Daily Prices'!$A$3:$A$2188<DATE(2022,10,1)),'Growth Index'!D$3:D$2188)-1,LOOKUP(2,1/('Daily Prices'!$A$3:$A$2188<DATE(2022,11,1)+0),'Growth Index'!D$3:D$2188)/100-1) -> 0.066152464 | L38: =IFERROR(LOOKUP(2,1/('Daily Prices'!$A$3:$A$2188<DATE(2022,12,1)+0),'Growth Index'!D$3:D$2188)/LOOKUP(2,1/('Daily Prices'!$A$3:$A$2188<DATE(2022,11,1)),'Growth Index'!D$3:D$2188)-1,LOOKUP(2,1/('Daily Prices'!$A$3:$A$2188<DATE(2022,12,1)+0),'Growth Index'!D$3:D$2188)/100-1) -> 0.041296105 | M38: =IFERROR(LOOKUP(2,1/('Daily Prices'!$A$3:$A$2188<DATE(2023,1,1)),'Growth Index'!D$3:D$2188)/LOOKUP(2,1/('Daily Prices'!$A$3:$A$2188<DATE(2022,12,1)),'Growth Index'!D$3:D$2188)-1,LOOKUP(2,1/('Daily Prices'!$A$3:$A$2188<DATE(2023,1,1)),'Growth Index'!D$3:D$2188)/100-1) -> -0.024095247 | N38: =IFERROR(LOOKUP(2,1/('Daily Prices'!$A$3:$A$2188<DATE(2023,1,1)),'Growth Index'!D$3:D$2188)/LOOKUP(2,1/('Daily Prices'!$A$3:$A$2188<DATE(2022,1,1)),'Growth Index'!D$3:D$2188)-1,LOOKUP(2,1/('Daily Prices'!$A$3:$A$2188<DATE(2023,1,1)),'Growth Index'!D$3:D$2188)/100-1) -> 0.19086224
A39: 2023 | B39: =IFERROR(LOOKUP(2,1/('Daily Prices'!$A$3:$A$2188<DATE(2023,2,1)+0),'Growth Index'!D$3:D$2188)/LOOKUP(2,1/('Daily Prices'!$A$3:$A$2188<DATE(2023,1,1)),'Growth Index'!D$3:D$2188)-1,LOOKUP(2,1/('Daily Prices'!$A$3:$A$2188<DATE(2023,2,1)+0),'Growth Index'!D$3:D$2188)/100-1) -> -0.014354333 | C39: =IFERROR(LOOKUP(2,1/('Daily Prices'!$A$3:$A$2188<DATE(2023,3,1)+0),'Growth Index'!D$3:D$2188)/LOOKUP(2,1/('Daily Prices'!$A$3:$A$2188<DATE(2023,2,1)),'Growth Index'!D$3:D$2188)-1,LOOKUP(2,1/('Daily Prices'!$A$3:$A$2188<DATE(2023,3,1)+0),'Growth Index'!D$3:D$2188)/100-1) -> -0.018193588 | D39: =IFERROR(LOOKUP(2,1/('Daily Prices'!$A$3:$A$2188<DATE(2023,4,1)+0),'Growth Index'!D$3:D$2188)/LOOKUP(2,1/('Daily Prices'!$A$3:$A$2188<DATE(2023,3,1)),'Growth Index'!D$3:D$2188)-1,LOOKUP(2,1/('Daily Prices'!$A$3:$A$2188<DATE(2023,4,1)+0),'Growth Index'!D$3:D$2188)/100-1) -> 0.0067173055 | E39: =IFERROR(LOOKUP(2,1/('Daily Prices'!$A$3:$A$2188<DATE(2023,5,1)+0),'Growth Index'!D$3:D$2188)/LOOKUP(2,1/('Daily Prices'!$A$3:$A$2188<DATE(2023,4,1)),'Growth Index'!D$3:D$2188)-1,LOOKUP(2,1/('Daily Prices'!$A$3:$A$2188<DATE(2023,5,1)+0),'Growth Index'!D$3:D$2188)/100-1) -> 0.034108409 | F39: =IFERROR(LOOKUP(2,1/('Daily Prices'!$A$3:$A$2188<DATE(2023,6,1)+0),'Growth Index'!D$3:D$2188)/LOOKUP(2,1/('Daily Prices'!$A$3:$A$2188<DATE(2023,5,1)),'Growth Index'!D$3:D$2188)-1,LOOKUP(2,1/('Daily Prices'!$A$3:$A$2188<DATE(2023,6,1)+0),'Growth Index'!D$3:D$2188)/100-1) -> 0.032393322 | G39: =IFERROR(LOOKUP(2,1/('Daily Prices'!$A$3:$A$2188<DATE(2023,7,1)+0),'Growth Index'!D$3:D$2188)/LOOKUP(2,1/('Daily Prices'!$A$3:$A$2188<DATE(2023,6,1)),'Growth Index'!D$3:D$2188)-1,LOOKUP(2,1/('Daily Prices'!$A$3:$A$2188<DATE(2023,7,1)+0),'Growth Index'!D$3:D$2188)/100-1) -> 0.049358215 | H39: =IFERROR(LOOKUP(2,1/('Daily Prices'!$A$3:$A$2188<DATE(2023,8,1)+0),'Growth Index'!D$3:D$2188)/LOOKUP(2,1/('Daily Prices'!$A$3:$A$2188<DATE(2023,7,1)),'Growth Index'!D$3:D$2188)-1,LOOKUP(2,1/('Daily Prices'!$A$3:$A$2188<DATE(2023,8,1)+0),'Growth Index'!D$3:D$2188)/100-1) -> 0.044686408 | I39: =IFERROR(LOOKUP(2,1/('Daily Prices'!$A$3:$A$2188<DATE(2023,9,1)+0),'Growth Index'!D$3:D$2188)/LOOKUP(2,1/('Daily Prices'!$A$3:$A$2188<DATE(2023,8,1)),'Growth Index'!D$3:D$2188)-1,LOOKUP(2,1/('Daily Prices'!$A$3:$A$2188<DATE(2023,9,1)+0),'Growth Index'!D$3:D$2188)/100-1) -> 0.00096423147 | J39: =IFERROR(LOOKUP(2,1/('Daily Prices'!$A$3:$A$2188<DATE(2023,10,1)+0),'Growth Index'!D$3:D$2188)/LOOKUP(2,1/('Daily Prices'!$A$3:$A$2188<DATE(2023,9,1)),'Growth Index'!D$3:D$2188)-1,LOOKUP(2,1/('Daily Prices'!$A$3:$A$2188<DATE(2023,10,1)+0),'Growth Index'!D$3:D$2188)/100-1) -> 0.019490093 | K39: =IFERROR(LOOKUP(2,1/('Daily Prices'!$A$3:$A$2188<DATE(2023,11,1)+0),'Growth Index'!D$3:D$2188)/LOOKUP(2,1/('Daily Prices'!$A$3:$A$2188<DATE(2023,10,1)),'Growth Index'!D$3:D$2188)-1,LOOKUP(2,1/('Daily Prices'!$A$3:$A$2188<DATE(2023,11,1)+0),'Growth Index'!D$3:D$2188)/100-1) -> -0.023104317 | L39: =IFERROR(LOOKUP(2,1/('Daily Prices'!$A$3:$A$2188<DATE(2023,12,1)+0),'Growth Index'!D$3:D$2188)/LOOKUP(2,1/('Daily Prices'!$A$3:$A$2188<DATE(2023,11,1)),'Growth Index'!D$3:D$2188)-1,LOOKUP(2,1/('Daily Prices'!$A$3:$A$2188<DATE(2023,12,1)+0),'Growth Index'!D$3:D$2188)/100-1) -> 0.074411729 | M39: =IFERROR(LOOKUP(2,1/('Daily Prices'!$A$3:$A$2188<DATE(2024,1,1)),'Growth Index'!D$3:D$2188)/LOOKUP(2,1/('Daily Prices'!$A$3:$A$2188<DATE(2023,12,1)),'Growth Index'!D$3:D$2188)-1,LOOKUP(2,1/('Daily Prices'!$A$3:$A$2188<DATE(2024,1,1)),'Growth Index'!D$3:D$2188)/100-1) -> 0.07639997 | N39: =IFERROR(LOOKUP(2,1/('Daily Prices'!$A$3:$A$2188<DATE(2024,1,1)),'Growth Index'!D$3:D$2188)/LOOKUP(2,1/('Daily Prices'!$A$3:$A$2188<DATE(2023,1,1)),'Growth Index'!D$3:D$2188)-1,LOOKUP(2,1/('Daily Prices'!$A$3:$A$2188<DATE(2024,1,1)),'Growth Index'!D$3:D$2188)/100-1) -> 0.31452654
A40: 2024 | B40: =IFERROR(LOOKUP(2,1/('Daily Prices'!$A$3:$A$2188<DATE(2024,2,1)+0),'Growth Index'!D$3:D$2188)/LOOKUP(2,1/('Daily Prices'!$A$3:$A$2188<DATE(2024,1,1)),'Growth Index'!D$3:D$2188)-1,LOOKUP(2,1/('Daily Prices'!$A$3:$A$2188<DATE(2024,2,1)+0),'Growth Index'!D$3:D$2188)/100-1) -> 0.023004791 | C40: =IFERROR(LOOKUP(2,1/('Daily Prices'!$A$3:$A$2188<DATE(2024,3,1)+0),'Growth Index'!D$3:D$2188)/LOOKUP(2,1/('Daily Prices'!$A$3:$A$2188<DATE(2024,2,1)),'Growth Index'!D$3:D$2188)-1,LOOKUP(2,1/('Daily Prices'!$A$3:$A$2188<DATE(2024,3,1)+0),'Growth Index'!D$3:D$2188)/100-1) -> 0.031029364 | D40: =IFERROR(LOOKUP(2,1/('Daily Prices'!$A$3:$A$2188<DATE(2024,4,1)+0),'Growth Index'!D$3:D$2188)/LOOKUP(2,1/('Daily Prices'!$A$3:$A$2188<DATE(2024,3,1)),'Growth Index'!D$3:D$2188)-1,LOOKUP(2,1/('Daily Prices'!$A$3:$A$2188<DATE(2024,4,1)+0),'Growth Index'!D$3:D$2188)/100-1) -> 0.01251013 | E40: =IFERROR(LOOKUP(2,1/('Daily Prices'!$A$3:$A$2188<DATE(2024,5,1)+0),'Growth Index'!D$3:D$2188)/LOOKUP(2,1/('Daily Prices'!$A$3:$A$2188<DATE(2024,4,1)),'Growth Index'!D$3:D$2188)-1,LOOKUP(2,1/('Daily Prices'!$A$3:$A$2188<DATE(2024,5,1)+0),'Growth Index'!D$3:D$2188)/100-1) -> 0.033245788 | F40: =IFERROR(LOOKUP(2,1/('Daily Prices'!$A$3:$A$2188<DATE(2024,6,1)+0),'Growth Index'!D$3:D$2188)/LOOKUP(2,1/('Daily Prices'!$A$3:$A$2188<DATE(2024,5,1)),'Growth Index'!D$3:D$2188)-1,LOOKUP(2,1/('Daily Prices'!$A$3:$A$2188<DATE(2024,6,1)+0),'Growth Index'!D$3:D$2188)/100-1) -> 0.021752295 | G40: =IFERROR(LOOKUP(2,1/('Daily Prices'!$A$3:$A$2188<DATE(2024,7,1)+0),'Growth Index'!D$3:D$2188)/LOOKUP(2,1/('Daily Prices'!$A$3:$A$2188<DATE(2024,6,1)),'Growth Index'!D$3:D$2188)-1,LOOKUP(2,1/('Daily Prices'!$A$3:$A$2188<DATE(2024,7,1)+0),'Growth Index'!D$3:D$2188)/100-1) -> 0.065675053 | H40: =IFERROR(LOOKUP(2,1/('Daily Prices'!$A$3:$A$2188<DATE(2024,8,1)+0),'Growth Index'!D$3:D$2188)/LOOKUP(2,1/('Daily Prices'!$A$3:$A$2188<DATE(2024,7,1)),'Growth Index'!D$3:D$2188)-1,LOOKUP(2,1/('Daily Prices'!$A$3:$A$2188<DATE(2024,8,1)+0),'Growth Index'!D$3:D$2188)/100-1) -> 0.03364568 | I40: =IFERROR(LOOKUP(2,1/('Daily Prices'!$A$3:$A$2188<DATE(2024,9,1)+0),'Growth Index'!D$3:D$2188)/LOOKUP(2,1/('Daily Prices'!$A$3:$A$2188<DATE(2024,8,1)),'Growth Index'!D$3:D$2188)-1,LOOKUP(2,1/('Daily Prices'!$A$3:$A$2188<DATE(2024,9,1)+0),'Growth Index'!D$3:D$2188)/100-1) -> 0.017684612 | J40: =IFERROR(LOOKUP(2,1/('Daily Prices'!$A$3:$A$2188<DATE(2024,10,1)+0),'Growth Index'!D$3:D$2188)/LOOKUP(2,1/('Daily Prices'!$A$3:$A$2188<DATE(2024,9,1)),'Growth Index'!D$3:D$2188)-1,LOOKUP(2,1/('Daily Prices'!$A$3:$A$2188<DATE(2024,10,1)+0),'Growth Index'!D$3:D$2188)/100-1) -> 0.029921505 | K40: =IFERROR(LOOKUP(2,1/('Daily Prices'!$A$3:$A$2188<DATE(2024,11,1)+0),'Growth Index'!D$3:D$2188)/LOOKUP(2,1/('Daily Prices'!$A$3:$A$2188<DATE(2024,10,1)),'Growth Index'!D$3:D$2188)-1,LOOKUP(2,1/('Daily Prices'!$A$3:$A$2188<DATE(2024,11,1)+0),'Growth Index'!D$3:D$2188)/100-1) -> -0.036881531 | L40: =IFERROR(LOOKUP(2,1/('Daily Prices'!$A$3:$A$2188<DATE(2024,12,1)+0),'Growth Index'!D$3:D$2188)/LOOKUP(2,1/('Daily Prices'!$A$3:$A$2188<DATE(2024,11,1)),'Growth Index'!D$3:D$2188)-1,LOOKUP(2,1/('Daily Prices'!$A$3:$A$2188<DATE(2024,12,1)+0),'Growth Index'!D$3:D$2188)/100-1) -> 0.0038621793 | M40: =IFERROR(LOOKUP(2,1/('Daily Prices'!$A$3:$A$2188<DATE(2025,1,1)),'Growth Index'!D$3:D$2188)/LOOKUP(2,1/('Daily Prices'!$A$3:$A$2188<DATE(2024,12,1)),'Growth Index'!D$3:D$2188)-1,LOOKUP(2,1/('Daily Prices'!$A$3:$A$2188<DATE(2025,1,1)),'Growth Index'!D$3:D$2188)/100-1) -> -0.012132393 | N40: =IFERROR(LOOKUP(2,1/('Daily Prices'!$A$3:$A$2188<DATE(2025,1,1)),'Growth Index'!D$3:D$2188)/LOOKUP(2,1/('Daily Prices'!$A$3:$A$2188<DATE(2024,1,1)),'Growth Index'!D$3:D$2188)-1,LOOKUP(2,1/('Daily Prices'!$A$3:$A$2188<DATE(2025,1,1)),'Growth Index'!D$3:D$2188)/100-1) -> 0.24326503
A42: Portfolio
A43: Year | B43: Jan | C43: Feb | D43: Mar | E43: Apr | F43: May | G43: Jun | H43: Jul | I43: Aug | J43: Sep | K43: Oct | L43: Nov | M43: Dec | N43: Year
A44: 2015 | B44: =IFERROR(LOOKUP(2,1/('Daily Prices'!$A$3:$A$2188<DATE(2015,2,1)+0),'Growth Index'!E$3:E$2188)/LOOKUP(2,1/('Daily Prices'!$A$3:$A$2188<DATE(2015,1,1)),'Growth Index'!E$3:E$2188)-1,LOOKUP(2,1/('Daily Prices'!$A$3:$A$2188<DATE(2015,2,1)+0),'Growth Index'!E$3:E$2188)/100-1) -> 0.042022446 | C44: =IFERROR(LOOKUP(2,1/('Daily Prices'!$A$3:$A$2188<DATE(2015,3,1)+0),'Growth Index'!E$3:E$2188)/LOOKUP(2,1/('Daily Prices'!$A$3:$A$2188<DATE(2015,2,1)),'Growth Index'!E$3:E$2188)-1,LOOKUP(2,1/('Daily Prices'!$A$3:$A$2188<DATE(2015,3,1)+0),'Growth Index'!E$3:E$2188)/100-1) -> -0.022741323 | D44: =IFERROR(LOOKUP(2,1/('Daily Prices'!$A$3:$A$2188<DATE(2015,4,1)+0),'Growth Index'!E$3:E$2188)/LOOKUP(2,1/('Daily Prices'!$A$3:$A$2188<DATE(2015,3,1)),'Growth Index'!E$3:E$2188)-1,LOOKUP(2,1/('Daily Prices'!$A$3:$A$2188<DATE(2015,4,1)+0),'Growth Index'!E$3:E$2188)/100-1) -> -0.02357633 | E44: =IFERROR(LOOKUP(2,1/('Daily Prices'!$A$3:$A$2188<DATE(2015,5,1)+0),'Growth Index'!E$3:E$2188)/LOOKUP(2,1/('Daily Prices'!$A$3:$A$2188<DATE(2015,4,1)),'Growth Index'!E$3:E$2188)-1,LOOKUP(2,1/('Daily Prices'!$A$3:$A$2188<DATE(2015,5,1)+0),'Growth Index'!E$3:E$2188)/100-1) -> -0.0098734017 | F44: =IFERROR(LOOKUP(2,1/('Daily Prices'!$A$3:$A$2188<DATE(2015,6,1)+0),'Growth Index'!E$3:E$2188)/LOOKUP(2,1/('Daily Prices'!$A$3:$A$2188<DATE(2015,5,1)),'Growth Index'!E$3:E$2188)-1,LOOKUP(2,1/('Daily Prices'!$A$3:$A$2188<DATE(2015,6,1)+0),'Growth Index'!E$3:E$2188)/100-1) -> 0.019224038 | G44: =IFERROR(LOOKUP(2,1/('Daily Prices'!$A$3:$A$2188<DATE(2015,7,1)+0),'Growth Index'!E$3:E$2188)/LOOKUP(2,1/('Daily Prices'!$A$3:$A$2188<DATE(2015,6,1)),'Growth Index'!E$3:E$2188)-1,LOOKUP(2,1/('Daily Prices'!$A$3:$A$2188<DATE(2015,7,1)+0),'Growth Index'!E$3:E$2188)/100-1) -> -0.0097501637 | H44: =IFERROR(LOOKUP(2,1/('Daily Prices'!$A$3:$A$2188<DATE(2015,8,1)+0),'Growth Index'!E$3:E$2188)/LOOKUP(2,1/('Daily Prices'!$A$3:$A$2188<DATE(2015,7,1)),'Growth Index'!E$3:E$2188)-1,LOOKUP(2,1/('Daily Prices'!$A$3:$A$2188<DATE(2015,8,1)+0),'Growth Index'!E$3:E$2188)/100-1) -> -0.0090760477 | I44: =IFERROR(LOOKUP(2,1/('Daily Prices'!$A$3:$A$2188<DATE(2015,9,1)+0),'Growth Index'!E$3:E$2188)/LOOKUP(2,1/('Daily Prices'!$A$3:$A$2188<DATE(2015,8,1)),'Growth Index'!E$3:E$2188)-1,LOOKUP(2,1/('Daily Prices'!$A$3:$A$2188<DATE(2015,9,1)+0),'Growth Index'!E$3:E$2188)/100-1) -> -0.011751168 | J44: =IFERROR(LOOKUP(2,1/('Daily Prices'!$A$3:$A$2188<DATE(2015,10,1)+0),'Growth Index'!E$3:E$2188)/LOOKUP(2,1/('Daily Prices'!$A$3:$A$2188<DATE(2015,9,1)),'Growth Index'!E$3:E$2188)-1,LOOKUP(2,1/('Daily Prices'!$A$3:$A$2188<DATE(2015,10,1)+0),'Growth Index'!E$3:E$2188)/100-1) -> -0.013931294 | K44: =IFERROR(LOOKUP(2,1/('Daily Prices'!$A$3:$A$2188<DATE(2015,11,1)+0),'Growth Index'!E$3:E$2188)/LOOKUP(2,1/('Daily Prices'!$A$3:$A$2188<DATE(2015,10,1)),'Growth Index'!E$3:E$2188)-1,LOOKUP(2,1/('Daily Prices'!$A$3:$A$2188<DATE(2015,11,1)+0),'Growth Index'!E$3:E$2188)/100-1) -> 0.01970379 | L44: =IFERROR(LOOKUP(2,1/('Daily Prices'!$A$3:$A$2188<DATE(2015,12,1)+0),'Growth Index'!E$3:E$2188)/LOOKUP(2,1/('Daily Prices'!$A$3:$A$2188<DATE(2015,11,1)),'Growth Index'!E$3:E$2188)-1,LOOKUP(2,1/('Daily Prices'!$A$3:$A$2188<DATE(2015,12,1)+0),'Growth Index'!E$3:E$2188)/100-1) -> -0.024717802 | M44: =IFERROR(LOOKUP(2,1/('Daily Prices'!$A$3:$A$2188<DATE(2016,1,1)),'Growth Index'!E$3:E$2188)/LOOKUP(2,1/('Daily Prices'!$A$3:$A$2188<DATE(2015,12,1)),'Growth Index'!E$3:E$2188)-1,LOOKUP(2,1/('Daily Prices'!$A$3:$A$2188<DATE(2016,1,1)),'Growth Index'!E$3:E$2188)/100-1) -> -0.0076476312 | N44: =IFERROR(LOOKUP(2,1/('Daily Prices'!$A$3:$A$2188<DATE(2016,1,1)),'Growth Index'!E$3:E$2188)/LOOKUP(2,1/('Daily Prices'!$A$3:$A$2188<DATE(2015,1,1)),'Growth Index'!E$3:E$2188)-1,LOOKUP(2,1/('Daily Prices'!$A$3:$A$2188<DATE(2016,1,1)),'Growth Index'!E$3:E$2188)/100-1) -> -0.053078177
A45: 2016 | B45: =IFERROR(LOOKUP(2,1/('Daily Prices'!$A$3:$A$2188<DATE(2016,2,1)+0),'Growth Index'!E$3:E$2188)/LOOKUP(2,1/('Daily Prices'!$A$3:$A$2188<DATE(2016,1,1)),'Growth Index'!E$3:E$2188)-1,LOOKUP(2,1/('Daily Prices'!$A$3:$A$2188<DATE(2016,2,1)+0),'Growth Index'!E$3:E$2188)/100-1) -> -0.013114346 | C45: =IFERROR(LOOKUP(2,1/('Daily Prices'!$A$3:$A$2188<DATE(2016,3,1)+0),'Growth Index'!E$3:E$2188)/LOOKUP(2,1/('Daily Prices'!$A$3:$A$2188<DATE(2016,2,1)),'Growth Index'!E$3:E$2188)-1,LOOKUP(2,1/('Daily Prices'!$A$3:$A$2188<DATE(2016,3,1)+0),'Growth Index'!E$3:E$2188)/100-1) -> -0.012444114 | D45: =IFERROR(LOOKUP(2,1/('Daily Prices'!$A$3:$A$2188<DATE(2016,4,1)+0),'Growth Index'!E$3:E$2188)/LOOKUP(2,1/('Daily Prices'!$A$3:$A$2188<DATE(2016,3,1)),'Growth Index'!E$3:E$2188)-1,LOOKUP(2,1/('Daily Prices'!$A$3:$A$2188<DATE(2016,4,1)+0),'Growth Index'!E$3:E$2188)/100-1) -> 0.063633537 | E45: =IFERROR(LOOKUP(2,1/('Daily Prices'!$A$3:$A$2188<DATE(2016,5,1)+0),'Growth Index'!E$3:E$2188)/LOOKUP(2,1/('Daily Prices'!$A$3:$A$2188<DATE(2016,4,1)),'Growth Index'!E$3:E$2188)-1,LOOKUP(2,1/('Daily Prices'!$A$3:$A$2188<DATE(2016,5,1)+0),'Growth Index'!E$3:E$2188)/100-1) -> 0.030517827 | F45: =IFERROR(LOOKUP(2,1/('Daily Prices'!$A$3:$A$2188<DATE(2016,6,1)+0),'Growth Index'!E$3:E$2188)/LOOKUP(2,1/('Daily Prices'!$A$3:$A$2188<DATE(2016,5,1)),'Growth Index'!E$3:E$2188)-1,LOOKUP(2,1/('Daily Prices'!$A$3:$A$2188<DATE(2016,6,1)+0),'Growth Index'!E$3:E$2188)/100-1) -> 0.0063854247 | G45: =IFERROR(LOOKUP(2,1/('Daily Prices'!$A$3:$A$2188<DATE(2016,7,1)+0),'Growth Index'!E$3:E$2188)/LOOKUP(2,1/('Daily Prices'!$A$3:$A$2188<DATE(2016,6,1)),'Growth Index'!E$3:E$2188)-1,LOOKUP(2,1/('Daily Prices'!$A$3:$A$2188<DATE(2016,7,1)+0),'Growth Index'!E$3:E$2188)/100-1) -> 0.051565648 | H45: =IFERROR(LOOKUP(2,1/('Daily Prices'!$A$3:$A$2188<DATE(2016,8,1)+0),'Growth Index'!E$3:E$2188)/LOOKUP(2,1/('Daily Prices'!$A$3:$A$2188<DATE(2016,7,1)),'Growth Index'!E$3:E$2188)-1,LOOKUP(2,1/('Daily Prices'!$A$3:$A$2188<DATE(2016,8,1)+0),'Growth Index'!E$3:E$2188)/100-1) -> 0.030325452 | I45: =IFERROR(LOOKUP(2,1/('Daily Prices'!$A$3:$A$2188<DATE(2016,9,1)+0),'Growth Index'!E$3:E$2188)/LOOKUP(2,1/('Daily Prices'!$A$3:$A$2188<DATE(2016,8,1)),'Growth Index'!E$3:E$2188)-1,LOOKUP(2,1/('Daily Prices'!$A$3:$A$2188<DATE(2016,9,1)+0),'Growth Index'!E$3:E$2188)/100-1) -> 0.004481615 | J45: =IFERROR(LOOKUP(2,1/('Daily Prices'!$A$3:$A$2188<DATE(2016,10,1)+0),'Growth Index'!E$3:E$2188)/LOOKUP(2,1/('Daily Prices'!$A$3:$A$2188<DATE(2016,9,1)),'Growth Index'!E$3:E$2188)-1,LOOKUP(2,1/('Daily Prices'!$A$3:$A$2188<DATE(2016,10,1)+0),'Growth Index'!E$3:E$2188)/100-1) -> -0.0035066046 | K45: =IFERROR(LOOKUP(2,1/('Daily Prices'!$A$3:$A$2188<DATE(2016,11,1)+0),'Growth Index'!E$3:E$2188)/LOOKUP(2,1/('Daily Prices'!$A$3:$A$2188<DATE(2016,10,1)),'Growth Index'!E$3:E$2188)-1,LOOKUP(2,1/('Daily Prices'!$A$3:$A$2188<DATE(2016,11,1)+0),'Growth Index'!E$3:E$2188)/100-1) -> -0.0051853746 | L45: =IFERROR(LOOKUP(2,1/('Daily Prices'!$A$3:$A$2188<DATE(2016,12,1)+0),'Growth Index'!E$3:E$2188)/LOOKUP(2,1/('Daily Prices'!$A$3:$A$2188<DATE(2016,11,1)),'Growth Index'!E$3:E$2188)-1,LOOKUP(2,1/('Daily Prices'!$A$3:$A$2188<DATE(2016,12,1)+0),'Growth Index'!E$3:E$2188)/100-1) -> -0.047205944 | M45: =IFERROR(LOOKUP(2,1/('Daily Prices'!$A$3:$A$2188<DATE(2017,1,1)),'Growth Index'!E$3:E$2188)/LOOKUP(2,1/('Daily Prices'!$A$3:$A$2188<DATE(2016,12,1)),'Growth Index'!E$3:E$2188)-1,LOOKUP(2,1/('Daily Prices'!$A$3:$A$2188<DATE(2017,1,1)),'Growth Index'!E$3:E$2188)/100-1) -> -0.020135773 | N45: =IFERROR(LOOKUP(2,1/('Daily Prices'!$A$3:$A$2188<DATE(2017,1,1)),'Growth Index'!E$3:E$2188)/LOOKUP(2,1/('Daily Prices'!$A$3:$A$2188<DATE(2016,1,1)),'Growth Index'!E$3:E$2188)-1,LOOKUP(2,1/('Daily Prices'!$A$3:$A$2188<DATE(2017,1,1)),'Growth Index'!E$3:E$2188)/100-1) -> 0.082866022
A46: 2017 | B46: =IFERROR(LOOKUP(2,1/('Daily Prices'!$A$3:$A$2188<DATE(2017,2,1)+0),'Growth Index'!E$3:E$2188)/LOOKUP(2,1/('Daily Prices'!$A$3:$A$2188<DATE(2017,1,1)),'Growth Index'!E$3:E$2188)-1,LOOKUP(2,1/('Daily Prices'!$A$3:$A$2188<DATE(2017,2,1)+0),'Growth Index'!E$3:E$2188)/100-1) -> 0.051659595 | C46: =IFERROR(LOOKUP(2,1/('Daily Prices'!$A$3:$A$2188<DATE(2017,3,1)+0),'Growth Index'!E$3:E$2188)/LOOKUP(2,1/('Daily Prices'!$A$3:$A$2188<DATE(2017,2,1)),'Growth Index'!E$3:E$2188)-1,LOOKUP(2,1/('Daily Prices'!$A$3:$A$2188<DATE(2017,3,1)+0),'Growth Index'!E$3:E$2188)/100-1) -> 0.032022806 | D46: =IFERROR(LOOKUP(2,1/('Daily Prices'!$A$3:$A$2188<DATE(2017,4,1)+0),'Growth Index'!E$3:E$2188)/LOOKUP(2,1/('Daily Prices'!$A$3:$A$2188<DATE(2017,3,1)),'Growth Index'!E$3:E$2188)-1,LOOKUP(2,1/('Daily Prices'!$A$3:$A$2188<DATE(2017,4,1)+0),'Growth Index'!E$3:E$2188)/100-1) -> 0.0064361309 | E46: =IFERROR(LOOKUP(2,1/('Daily Prices'!$A$3:$A$2188<DATE(2017,5,1)+0),'Growth Index'!E$3:E$2188)/LOOKUP(2,1/('Daily Prices'!$A$3:$A$2188<DATE(2017,4,1)),'Growth Index'!E$3:E$2188)-1,LOOKUP(2,1/('Daily Prices'!$A$3:$A$2188<DATE(2017,5,1)+0),'Growth Index'!E$3:E$2188)/100-1) -> 0.017293967 | F46: =IFERROR(LOOKUP(2,1/('Daily Prices'!$A$3:$A$2188<DATE(2017,6,1)+0),'Growth Index'!E$3:E$2188)/LOOKUP(2,1/('Daily Prices'!$A$3:$A$2188<DATE(2017,5,1)),'Growth Index'!E$3:E$2188)-1,LOOKUP(2,1/('Daily Prices'!$A$3:$A$2188<DATE(2017,6,1)+0),'Growth Index'!E$3:E$2188)/100-1) -> 0.019963804 | G46: =IFERROR(LOOKUP(2,1/('Daily Prices'!$A$3:$A$2188<DATE(2017,7,1)+0),'Growth Index'!E$3:E$2188)/LOOKUP(2,1/('Daily Prices'!$A$3:$A$2188<DATE(2017,6,1)),'Growth Index'!E$3:E$2188)-1,LOOKUP(2,1/('Daily Prices'!$A$3:$A$2188<DATE(2017,7,1)+0),'Growth Index'!E$3:E$2188)/100-1) -> -0.0099919465 | H46: =IFERROR(LOOKUP(2,1/('Daily Prices'!$A$3:$A$2188<DATE(2017,8,1)+0),'Growth Index'!E$3:E$2188)/LOOKUP(2,1/('Daily Prices'!$A$3:$A$2188<DATE(2017,7,1)),'Growth Index'!E$3:E$2188)-1,LOOKUP(2,1/('Daily Prices'!$A$3:$A$2188<DATE(2017,8,1)+0),'Growth Index'!E$3:E$2188)/100-1) -> 0.040588875 | I46: =IFERROR(LOOKUP(2,1/('Daily Prices'!$A$3:$A$2188<DATE(2017,9,1)+0),'Growth Index'!E$3:E$2188)/LOOKUP(2,1/('Daily Prices'!$A$3:$A$2188<DATE(2017,8,1)),'Growth Index'!E$3:E$2188)-1,LOOKUP(2,1/('Daily Prices'!$A$3:$A$2188<DATE(2017,9,1)+0),'Growth Index'!E$3:E$2188)/100-1) -> -0.0040054407 | J46: =IFERROR(LOOKUP(2,1/('Daily Prices'!$A$3:$A$2188<DATE(2017,10,1)+0),'Growth Index'!E$3:E$2188)/LOOKUP(2,1/('Daily Prices'!$A$3:$A$2188<DATE(2017,9,1)),'Growth Index'!E$3:E$2188)-1,LOOKUP(2,1/('Daily Prices'!$A$3:$A$2188<DATE(2017,10,1)+0),'Growth Index'!E$3:E$2188)/100-1) -> -0.0093669791 | K46: =IFERROR(LOOKUP(2,1/('Daily Prices'!$A$3:$A$2188<DATE(2017,11,1)+0),'Growth Index'!E$3:E$2188)/LOOKUP(2,1/('Daily Prices'!$A$3:$A$2188<DATE(2017,10,1)),'Growth Index'!E$3:E$2188)-1,LOOKUP(2,1/('Daily Prices'!$A$3:$A$2188<DATE(2017,11,1)+0),'Growth Index'!E$3:E$2188)/100-1) -> 0.027146524 | L46: =IFERROR(LOOKUP(2,1/('Daily Prices'!$A$3:$A$2188<DATE(2017,12,1)+0),'Growth Index'!E$3:E$2188)/LOOKUP(2,1/('Daily Prices'!$A$3:$A$2188<DATE(2017,11,1)),'Growth Index'!E$3:E$2188)-1,LOOKUP(2,1/('Daily Prices'!$A$3:$A$2188<DATE(2017,12,1)+0),'Growth Index'!E$3:E$2188)/100-1) -> 0.014173565 | M46: =IFERROR(LOOKUP(2,1/('Daily Prices'!$A$3:$A$2188<DATE(2018,1,1)),'Growth Index'!E$3:E$2188)/LOOKUP(2,1/('Daily Prices'!$A$3:$A$2188<DATE(2017,12,1)),'Growth Index'!E$3:E$2188)-1,LOOKUP(2,1/('Daily Prices'!$A$3:$A$2188<DATE(2018,1,1)),'Growth Index'!E$3:E$2188)/100-1) -> 0.016961787 | N46: =IFERROR(LOOKUP(2,1/('Daily Prices'!$A$3:$A$2188<DATE(2018,1,1)),'Growth Index'!E$3:E$2188)/LOOKUP(2,1/('Daily Prices'!$A$3:$A$2188<DATE(2017,1,1)),'Growth Index'!E$3:E$2188)-1,LOOKUP(2,1/('Daily Prices'!$A$3:$A$2188<DATE(2018,1,1)),'Growth Index'!E$3:E$2188)/100-1) -> 0.220447
A47: 2018 | B47: =IFERROR(LOOKUP(2,1/('Daily Prices'!$A$3:$A$2188<DATE(2018,2,1)+0),'Growth Index'!E$3:E$2188)/LOOKUP(2,1/('Daily Prices'!$A$3:$A$2188<DATE(2018,1,1)),'Growth Index'!E$3:E$2188)-1,LOOKUP(2,1/('Daily Prices'!$A$3:$A$2188<DATE(2018,2,1)+0),'Growth Index'!E$3:E$2188)/100-1) -> 0.041077873 | C47: =IFERROR(LOOKUP(2,1/('Daily Prices'!$A$3:$A$2188<DATE(2018,3,1)+0),'Growth Index'!E$3:E$2188)/LOOKUP(2,1/('Daily Prices'!$A$3:$A$2188<DATE(2018,2,1)),'Growth Index'!E$3:E$2188)-1,LOOKUP(2,1/('Daily Prices'!$A$3:$A$2188<DATE(2018,3,1)+0),'Growth Index'!E$3:E$2188)/100-1) -> -0.033333423 | D47: =IFERROR(LOOKUP(2,1/('Daily Prices'!$A$3:$A$2188<DATE(2018,4,1)+0),'Growth Index'!E$3:E$2188)/LOOKUP(2,1/('Daily Prices'!$A$3:$A$2188<DATE(2018,3,1)),'Growth Index'!E$3:E$2188)-1,LOOKUP(2,1/('Daily Prices'!$A$3:$A$2188<DATE(2018,4,1)+0),'Growth Index'!E$3:E$2188)/100-1) -> -0.023010833 | E47: =IFERROR(LOOKUP(2,1/('Daily Prices'!$A$3:$A$2188<DATE(2018,5,1)+0),'Growth Index'!E$3:E$2188)/LOOKUP(2,1/('Daily Prices'!$A$3:$A$2188<DATE(2018,4,1)),'Growth Index'!E$3:E$2188)-1,LOOKUP(2,1/('Daily Prices'!$A$3:$A$2188<DATE(2018,5,1)+0),'Growth Index'!E$3:E$2188)/100-1) -> 0.039798169 | F47: =IFERROR(LOOKUP(2,1/('Daily Prices'!$A$3:$A$2188<DATE(2018,6,1)+0),'Growth Index'!E$3:E$2188)/LOOKUP(2,1/('Daily Prices'!$A$3:$A$2188<DATE(2018,5,1)),'Growth Index'!E$3:E$2188)-1,LOOKUP(2,1/('Daily Prices'!$A$3:$A$2188<DATE(2018,6,1)+0),'Growth Index'!E$3:E$2188)/100-1) -> -0.0007328043 | G47: =IFERROR(LOOKUP(2,1/('Daily Prices'!$A$3:$A$2188<DATE(2018,7,1)+0),'Growth Index'!E$3:E$2188)/LOOKUP(2,1/('Daily Prices'!$A$3:$A$2188<DATE(2018,6,1)),'Growth Index'!E$3:E$2188)-1,LOOKUP(2,1/('Daily Prices'!$A$3:$A$2188<DATE(2018,7,1)+0),'Growth Index'!E$3:E$2188)/100-1) -> -0.019634701 | H47: =IFERROR(LOOKUP(2,1/('Daily Prices'!$A$3:$A$2188<DATE(2018,8,1)+0),'Growth Index'!E$3:E$2188)/LOOKUP(2,1/('Daily Prices'!$A$3:$A$2188<DATE(2018,7,1)),'Growth Index'!E$3:E$2188)-1,LOOKUP(2,1/('Daily Prices'!$A$3:$A$2188<DATE(2018,8,1)+0),'Growth Index'!E$3:E$2188)/100-1) -> 0.029885442 | I47: =IFERROR(LOOKUP(2,1/('Daily Prices'!$A$3:$A$2188<DATE(2018,9,1)+0),'Growth Index'!E$3:E$2188)/LOOKUP(2,1/('Daily Prices'!$A$3:$A$2188<DATE(2018,8,1)),'Growth Index'!E$3:E$2188)-1,LOOKUP(2,1/('Daily Prices'!$A$3:$A$2188<DATE(2018,9,1)+0),'Growth Index'!E$3:E$2188)/100-1) -> 0.032466917 | J47: =IFERROR(LOOKUP(2,1/('Daily Prices'!$A$3:$A$2188<DATE(2018,10,1)+0),'Growth Index'!E$3:E$2188)/LOOKUP(2,1/('Daily Prices'!$A$3:$A$2188<DATE(2018,9,1)),'Growth Index'!E$3:E$2188)-1,LOOKUP(2,1/('Daily Prices'!$A$3:$A$2188<DATE(2018,10,1)+0),'Growth Index'!E$3:E$2188)/100-1) -> -0.038284631 | K47: =IFERROR(LOOKUP(2,1/('Daily Prices'!$A$3:$A$2188<DATE(2018,11,1)+0),'Growth Index'!E$3:E$2188)/LOOKUP(2,1/('Daily Prices'!$A$3:$A$2188<DATE(2018,10,1)),'Growth Index'!E$3:E$2188)-1,LOOKUP(2,1/('Daily Prices'!$A$3:$A$2188<DATE(2018,11,1)+0),'Growth Index'!E$3:E$2188)/100-1) -> 0.0028853367 | L47: =IFERROR(LOOKUP(2,1/('Daily Prices'!$A$3:$A$2188<DATE(2018,12,1)+0),'Growth Index'!E$3:E$2188)/LOOKUP(2,1/('Daily Prices'!$A$3:$A$2188<DATE(2018,11,1)),'Growth Index'!E$3:E$2188)-1,LOOKUP(2,1/('Daily Prices'!$A$3:$A$2188<DATE(2018,12,1)+0),'Growth Index'!E$3:E$2188)/100-1) -> -0.0050511849 | M47: =IFERROR(LOOKUP(2,1/('Daily Prices'!$A$3:$A$2188<DATE(2019,1,1)),'Growth Index'!E$3:E$2188)/LOOKUP(2,1/('Daily Prices'!$A$3:$A$2188<DATE(2018,12,1)),'Growth Index'!E$3:E$2188)-1,LOOKUP(2,1/('Daily Prices'!$A$3:$A$2188<DATE(2019,1,1)),'Growth Index'!E$3:E$2188)/100-1) -> 0.027193747 | N47: =IFERROR(LOOKUP(2,1/('Daily Prices'!$A$3:$A$2188<DATE(2019,1,1)),'Growth Index'!E$3:E$2188)/LOOKUP(2,1/('Daily Prices'!$A$3:$A$2188<DATE(2018,1,1)),'Growth Index'!E$3:E$2188)-1,LOOKUP(2,1/('Daily Prices'!$A$3:$A$2188<DATE(2019,1,1)),'Growth Index'!E$3:E$2188)/100-1) -> 0.049746136
A48: 2019 | B48: =IFERROR(LOOKUP(2,1/('Daily Prices'!$A$3:$A$2188<DATE(2019,2,1)+0),'Growth Index'!E$3:E$2188)/LOOKUP(2,1/('Daily Prices'!$A$3:$A$2188<DATE(2019,1,1)),'Growth Index'!E$3:E$2188)-1,LOOKUP(2,1/('Daily Prices'!$A$3:$A$2188<DATE(2019,2,1)+0),'Growth Index'!E$3:E$2188)/100-1) -> 0.021839695 | C48: =IFERROR(LOOKUP(2,1/('Daily Prices'!$A$3:$A$2188<DATE(2019,3,1)+0),'Growth Index'!E$3:E$2188)/LOOKUP(2,1/('Daily Prices'!$A$3:$A$2188<DATE(2019,2,1)),'Growth Index'!E$3:E$2188)-1,LOOKUP(2,1/('Daily Prices'!$A$3:$A$2188<DATE(2019,3,1)+0),'Growth Index'!E$3:E$2188)/100-1) -> -0.011285436 | D48: =IFERROR(LOOKUP(2,1/('Daily Prices'!$A$3:$A$2188<DATE(2019,4,1)+0),'Growth Index'!E$3:E$2188)/LOOKUP(2,1/('Daily Prices'!$A$3:$A$2188<DATE(2019,3,1)),'Growth Index'!E$3:E$2188)-1,LOOKUP(2,1/('Daily Prices'!$A$3:$A$2188<DATE(2019,4,1)+0),'Growth Index'!E$3:E$2188)/100-1) -> 0.039091262 | E48: =IFERROR(LOOKUP(2,1/('Daily Prices'!$A$3:$A$2188<DATE(2019,5,1)+0),'Growth Index'!E$3:E$2188)/LOOKUP(2,1/('Daily Prices'!$A$3:$A$2188<DATE(2019,4,1)),'Growth Index'!E$3:E$2188)-1,LOOKUP(2,1/('Daily Prices'!$A$3:$A$2188<DATE(2019,5,1)+0),'Growth Index'!E$3:E$2188)/100-1) -> -0.0024901767 | F48: =IFERROR(LOOKUP(2,1/('Daily Prices'!$A$3:$A$2188<DATE(2019,6,1)+0),'Growth Index'!E$3:E$2188)/LOOKUP(2,1/('Daily Prices'!$A$3:$A$2188<DATE(2019,5,1)),'Growth Index'!E$3:E$2188)-1,LOOKUP(2,1/('Daily Prices'!$A$3:$A$2188<DATE(2019,6,1)+0),'Growth Index'!E$3:E$2188)/100-1) -> 0.020330441 | G48: =IFERROR(LOOKUP(2,1/('Daily Prices'!$A$3:$A$2188<DATE(2019,7,1)+0),'Growth Index'!E$3:E$2188)/LOOKUP(2,1/('Daily Prices'!$A$3:$A$2188<DATE(2019,6,1)),'Growth Index'!E$3:E$2188)-1,LOOKUP(2,1/('Daily Prices'!$A$3:$A$2188<DATE(2019,7,1)+0),'Growth Index'!E$3:E$2188)/100-1) -> 0.029874524 | H48: =IFERROR(LOOKUP(2,1/('Daily Prices'!$A$3:$A$2188<DATE(2019,8,1)+0),'Growth Index'!E$3:E$2188)/LOOKUP(2,1/('Daily Prices'!$A$3:$A$2188<DATE(2019,7,1)),'Growth Index'!E$3:E$2188)-1,LOOKUP(2,1/('Daily Prices'!$A$3:$A$2188<DATE(2019,8,1)+0),'Growth Index'!E$3:E$2188)/100-1) -> -0.032705576 | I48: =IFERROR(LOOKUP(2,1/('Daily Prices'!$A$3:$A$2188<DATE(2019,9,1)+0),'Growth Index'!E$3:E$2188)/LOOKUP(2,1/('Daily Prices'!$A$3:$A$2188<DATE(2019,8,1)),'Growth Index'!E$3:E$2188)-1,LOOKUP(2,1/('Daily Prices'!$A$3:$A$2188<DATE(2019,9,1)+0),'Growth Index'!E$3:E$2188)/100-1) -> 0.03160889 | J48: =IFERROR(LOOKUP(2,1/('Daily Prices'!$A$3:$A$2188<DATE(2019,10,1)+0),'Growth Index'!E$3:E$2188)/LOOKUP(2,1/('Daily Prices'!$A$3:$A$2188<DATE(2019,9,1)),'Growth Index'!E$3:E$2188)-1,LOOKUP(2,1/('Daily Prices'!$A$3:$A$2188<DATE(2019,10,1)+0),'Growth Index'!E$3:E$2188)/100-1) -> 0.0055066016 | K48: =IFERROR(LOOKUP(2,1/('Daily Prices'!$A$3:$A$2188<DATE(2019,11,1)+0),'Growth Index'!E$3:E$2188)/LOOKUP(2,1/('Daily Prices'!$A$3:$A$2188<DATE(2019,10,1)),'Growth Index'!E$3:E$2188)-1,LOOKUP(2,1/('Daily Prices'!$A$3:$A$2188<DATE(2019,11,1)+0),'Growth Index'!E$3:E$2188)/100-1) -> 0.032177948 | L48: =IFERROR(LOOKUP(2,1/('Daily Prices'!$A$3:$A$2188<DATE(2019,12,1)+0),'Growth Index'!E$3:E$2188)/LOOKUP(2,1/('Daily Prices'!$A$3:$A$2188<DATE(2019,11,1)),'Growth Index'!E$3:E$2188)-1,LOOKUP(2,1/('Daily Prices'!$A$3:$A$2188<DATE(2019,12,1)+0),'Growth Index'!E$3:E$2188)/100-1) -> -0.0010781176 | M48: =IFERROR(LOOKUP(2,1/('Daily Prices'!$A$3:$A$2188<DATE(2020,1,1)),'Growth Index'!E$3:E$2188)/LOOKUP(2,1/('Daily Prices'!$A$3:$A$2188<DATE(2019,12,1)),'Growth Index'!E$3:E$2188)-1,LOOKUP(2,1/('Daily Prices'!$A$3:$A$2188<DATE(2020,1,1)),'Growth Index'!E$3:E$2188)/100-1) -> 0.016119131 | N48: =IFERROR(LOOKUP(2,1/('Daily Prices'!$A$3:$A$2188<DATE(2020,1,1)),'Growth Index'!E$3:E$2188)/LOOKUP(2,1/('Daily Prices'!$A$3:$A$2188<DATE(2019,1,1)),'Growth Index'!E$3:E$2188)-1,LOOKUP(2,1/('Daily Prices'!$A$3:$A$2188<DATE(2020,1,1)),'Growth Index'!E$3:E$2188)/100-1) -> 0.15674905
A49: 2020 | B49: =IFERROR(LOOKUP(2,1/('Daily Prices'!$A$3:$A$2188<DATE(2020,2,1)+0),'Growth Index'!E$3:E$2188)/LOOKUP(2,1/('Daily Prices'!$A$3:$A$2188<DATE(2020,1,1)),'Growth Index'!E$3:E$2188)-1,LOOKUP(2,1/('Daily Prices'!$A$3:$A$2188<DATE(2020,2,1)+0),'Growth Index'!E$3:E$2188)/100-1) -> 0.010595351 | C49: =IFERROR(LOOKUP(2,1/('Daily Prices'!$A$3:$A$2188<DATE(2020,3,1)+0),'Growth Index'!E$3:E$2188)/LOOKUP(2,1/('Daily Prices'!$A$3:$A$2188<DATE(2020,2,1)),'Growth Index'!E$3:E$2188)-1,LOOKUP(2,1/('Daily Prices'!$A$3:$A$2188<DATE(2020,3,1)+0),'Growth Index'!E$3:E$2188)/100-1) -> -0.017456578 | D49: =IFERROR(LOOKUP(2,1/('Daily Prices'!$A$3:$A$2188<DATE(2020,4,1)+0),'Growth Index'!E$3:E$2188)/LOOKUP(2,1/('Daily Prices'!$A$3:$A$2188<DATE(2020,3,1)),'Growth Index'!E$3:E$2188)-1,LOOKUP(2,1/('Daily Prices'!$A$3:$A$2188<DATE(2020,4,1)+0),'Growth Index'!E$3:E$2188)/100-1) -> -0.14282509 | E49: =IFERROR(LOOKUP(2,1/('Daily Prices'!$A$3:$A$2188<DATE(2020,5,1)+0),'Growth Index'!E$3:E$2188)/LOOKUP(2,1/('Daily Prices'!$A$3:$A$2188<DATE(2020,4,1)),'Growth Index'!E$3:E$2188)-1,LOOKUP(2,1/('Daily Prices'!$A$3:$A$2188<DATE(2020,5,1)+0),'Growth Index'!E$3:E$2188)/100-1) -> 0.09390062 | F49: =IFERROR(LOOKUP(2,1/('Daily Prices'!$A$3:$A$2188<DATE(2020,6,1)+0),'Growth Index'!E$3:E$2188)/LOOKUP(2,1/('Daily Prices'!$A$3:$A$2188<DATE(2020,5,1)),'Growth Index'!E$3:E$2188)-1,LOOKUP(2,1/('Daily Prices'!$A$3:$A$2188<DATE(2020,6,1)+0),'Growth Index'!E$3:E$2188)/100-1) -> -0.0012695505 | G49: =IFERROR(LOOKUP(2,1/('Daily Prices'!$A$3:$A$2188<DATE(2020,7,1)+0),'Growth Index'!E$3:E$2188)/LOOKUP(2,1/('Daily Prices'!$A$3:$A$2188<DATE(2020,6,1)),'Growth Index'!E$3:E$2188)-1,LOOKUP(2,1/('Daily Prices'!$A$3:$A$2188<DATE(2020,7,1)+0),'Growth Index'!E$3:E$2188)/100-1) -> 0.053350683 | H49: =IFERROR(LOOKUP(2,1/('Daily Prices'!$A$3:$A$2188<DATE(2020,8,1)+0),'Growth Index'!E$3:E$2188)/LOOKUP(2,1/('Daily Prices'!$A$3:$A$2188<DATE(2020,7,1)),'Growth Index'!E$3:E$2188)-1,LOOKUP(2,1/('Daily Prices'!$A$3:$A$2188<DATE(2020,8,1)+0),'Growth Index'!E$3:E$2188)/100-1) -> 0.078285376 | I49: =IFERROR(LOOKUP(2,1/('Daily Prices'!$A$3:$A$2188<DATE(2020,9,1)+0),'Growth Index'!E$3:E$2188)/LOOKUP(2,1/('Daily Prices'!$A$3:$A$2188<DATE(2020,8,1)),'Growth Index'!E$3:E$2188)-1,LOOKUP(2,1/('Daily Prices'!$A$3:$A$2188<DATE(2020,9,1)+0),'Growth Index'!E$3:E$2188)/100-1) -> 0.014558815 | J49: =IFERROR(LOOKUP(2,1/('Daily Prices'!$A$3:$A$2188<DATE(2020,10,1)+0),'Growth Index'!E$3:E$2188)/LOOKUP(2,1/('Daily Prices'!$A$3:$A$2188<DATE(2020,9,1)),'Growth Index'!E$3:E$2188)-1,LOOKUP(2,1/('Daily Prices'!$A$3:$A$2188<DATE(2020,10,1)+0),'Growth Index'!E$3:E$2188)/100-1) -> -0.03219746 | K49: =IFERROR(LOOKUP(2,1/('Daily Prices'!$A$3:$A$2188<DATE(2020,11,1)+0),'Growth Index'!E$3:E$2188)/LOOKUP(2,1/('Daily Prices'!$A$3:$A$2188<DATE(2020,10,1)),'Growth Index'!E$3:E$2188)-1,LOOKUP(2,1/('Daily Prices'!$A$3:$A$2188<DATE(2020,11,1)+0),'Growth Index'!E$3:E$2188)/100-1) -> 0.023871937 | L49: =IFERROR(LOOKUP(2,1/('Daily Prices'!$A$3:$A$2188<DATE(2020,12,1)+0),'Growth Index'!E$3:E$2188)/LOOKUP(2,1/('Daily Prices'!$A$3:$A$2188<DATE(2020,11,1)),'Growth Index'!E$3:E$2188)-1,LOOKUP(2,1/('Daily Prices'!$A$3:$A$2188<DATE(2020,12,1)+0),'Growth Index'!E$3:E$2188)/100-1) -> 0.049551186 | M49: =IFERROR(LOOKUP(2,1/('Daily Prices'!$A$3:$A$2188<DATE(2021,1,1)),'Growth Index'!E$3:E$2188)/LOOKUP(2,1/('Daily Prices'!$A$3:$A$2188<DATE(2020,12,1)),'Growth Index'!E$3:E$2188)-1,LOOKUP(2,1/('Daily Prices'!$A$3:$A$2188<DATE(2021,1,1)),'Growth Index'!E$3:E$2188)/100-1) -> 0.073658893 | N49: =IFERROR(LOOKUP(2,1/('Daily Prices'!$A$3:$A$2188<DATE(2021,1,1)),'Growth Index'!E$3:E$2188)/LOOKUP(2,1/('Daily Prices'!$A$3:$A$2188<DATE(2020,1,1)),'Growth Index'!E$3:E$2188)-1,LOOKUP(2,1/('Daily Prices'!$A$3:$A$2188<DATE(2021,1,1)),'Growth Index'!E$3:E$2188)/100-1) -> 0.19649512
A50: 2021 | B50: =IFERROR(LOOKUP(2,1/('Daily Prices'!$A$3:$A$2188<DATE(2021,2,1)+0),'Growth Index'!E$3:E$2188)/LOOKUP(2,1/('Daily Prices'!$A$3:$A$2188<DATE(2021,1,1)),'Growth Index'!E$3:E$2188)-1,LOOKUP(2,1/('Daily Prices'!$A$3:$A$2188<DATE(2021,2,1)+0),'Growth Index'!E$3:E$2188)/100-1) -> 0.0060279313 | C50: =IFERROR(LOOKUP(2,1/('Daily Prices'!$A$3:$A$2188<DATE(2021,3,1)+0),'Growth Index'!E$3:E$2188)/LOOKUP(2,1/('Daily Prices'!$A$3:$A$2188<DATE(2021,2,1)),'Growth Index'!E$3:E$2188)-1,LOOKUP(2,1/('Daily Prices'!$A$3:$A$2188<DATE(2021,3,1)+0),'Growth Index'!E$3:E$2188)/100-1) -> 0.014515421 | D50: =IFERROR(LOOKUP(2,1/('Daily Prices'!$A$3:$A$2188<DATE(2021,4,1)+0),'Growth Index'!E$3:E$2188)/LOOKUP(2,1/('Daily Prices'!$A$3:$A$2188<DATE(2021,3,1)),'Growth Index'!E$3:E$2188)-1,LOOKUP(2,1/('Daily Prices'!$A$3:$A$2188<DATE(2021,4,1)+0),'Growth Index'!E$3:E$2188)/100-1) -> -0.016643363 | E50: =IFERROR(LOOKUP(2,1/('Daily Prices'!$A$3:$A$2188<DATE(2021,5,1)+0),'Growth Index'!E$3:E$2188)/LOOKUP(2,1/('Daily Prices'!$A$3:$A$2188<DATE(2021,4,1)),'Growth Index'!E$3:E$2188)-1,LOOKUP(2,1/('Daily Prices'!$A$3:$A$2188<DATE(2021,5,1)+0),'Growth Index'!E$3:E$2188)/100-1) -> 0.018221612 | F50: =IFERROR(LOOKUP(2,1/('Daily Prices'!$A$3:$A$2188<DATE(2021,6,1)+0),'Growth Index'!E$3:E$2188)/LOOKUP(2,1/('Daily Prices'!$A$3:$A$2188<DATE(2021,5,1)),'Growth Index'!E$3:E$2188)-1,LOOKUP(2,1/('Daily Prices'!$A$3:$A$2188<DATE(2021,6,1)+0),'Growth Index'!E$3:E$2188)/100-1) -> 0.070795828 | G50: =IFERROR(LOOKUP(2,1/('Daily Prices'!$A$3:$A$2188<DATE(2021,7,1)+0),'Growth Index'!E$3:E$2188)/LOOKUP(2,1/('Daily Prices'!$A$3:$A$2188<DATE(2021,6,1)),'Growth Index'!E$3:E$2188)-1,LOOKUP(2,1/('Daily Prices'!$A$3:$A$2188<DATE(2021,7,1)+0),'Growth Index'!E$3:E$2188)/100-1) -> -0.012047054 | H50: =IFERROR(LOOKUP(2,1/('Daily Prices'!$A$3:$A$2188<DATE(2021,8,1)+0),'Growth Index'!E$3:E$2188)/LOOKUP(2,1/('Daily Prices'!$A$3:$A$2188<DATE(2021,7,1)),'Growth Index'!E$3:E$2188)-1,LOOKUP(2,1/('Daily Prices'!$A$3:$A$2188<DATE(2021,8,1)+0),'Growth Index'!E$3:E$2188)/100-1) -> 0.019964488 | I50: =IFERROR(LOOKUP(2,1/('Daily Prices'!$A$3:$A$2188<DATE(2021,9,1)+0),'Growth Index'!E$3:E$2188)/LOOKUP(2,1/('Daily Prices'!$A$3:$A$2188<DATE(2021,8,1)),'Growth Index'!E$3:E$2188)-1,LOOKUP(2,1/('Daily Prices'!$A$3:$A$2188<DATE(2021,9,1)+0),'Growth Index'!E$3:E$2188)/100-1) -> 0.027038743 | J50: =IFERROR(LOOKUP(2,1/('Daily Prices'!$A$3:$A$2188<DATE(2021,10,1)+0),'Growth Index'!E$3:E$2188)/LOOKUP(2,1/('Daily Prices'!$A$3:$A$2188<DATE(2021,9,1)),'Growth Index'!E$3:E$2188)-1,LOOKUP(2,1/('Daily Prices'!$A$3:$A$2188<DATE(2021,10,1)+0),'Growth Index'!E$3:E$2188)/100-1) -> 0.01731382 | K50: =IFERROR(LOOKUP(2,1/('Daily Prices'!$A$3:$A$2188<DATE(2021,11,1)+0),'Growth Index'!E$3:E$2188)/LOOKUP(2,1/('Daily Prices'!$A$3:$A$2188<DATE(2021,10,1)),'Growth Index'!E$3:E$2188)-1,LOOKUP(2,1/('Daily Prices'!$A$3:$A$2188<DATE(2021,11,1)+0),'Growth Index'!E$3:E$2188)/100-1) -> 0.016003066 | L50: =IFERROR(LOOKUP(2,1/('Daily Prices'!$A$3:$A$2188<DATE(2021,12,1)+0),'Growth Index'!E$3:E$2188)/LOOKUP(2,1/('Daily Prices'!$A$3:$A$2188<DATE(2021,11,1)),'Growth Index'!E$3:E$2188)-1,LOOKUP(2,1/('Daily Prices'!$A$3:$A$2188<DATE(2021,12,1)+0),'Growth Index'!E$3:E$2188)/100-1) -> -0.014589622 | M50: =IFERROR(LOOKUP(2,1/('Daily Prices'!$A$3:$A$2188<DATE(2022,1,1)),'Growth Index'!E$3:E$2188)/LOOKUP(2,1/('Daily Prices'!$A$3:$A$2188<DATE(2021,12,1)),'Growth Index'!E$3:E$2188)-1,LOOKUP(2,1/('Daily Prices'!$A$3:$A$2188<DATE(2022,1,1)),'Growth Index'!E$3:E$2188)/100-1) -> 0.0095546157 | N50: =IFERROR(LOOKUP(2,1/('Daily Prices'!$A$3:$A$2188<DATE(2022,1,1)),'Growth Index'!E$3:E$2188)/LOOKUP(2,1/('Daily Prices'!$A$3:$A$2188<DATE(2021,1,1)),'Growth Index'!E$3:E$2188)-1,LOOKUP(2,1/('Daily Prices'!$A$3:$A$2188<DATE(2022,1,1)),'Growth Index'!E$3:E$2188)/100-1) -> 0.16448467
A51: 2022 | B51: =IFERROR(LOOKUP(2,1/('Daily Prices'!$A$3:$A$2188<DATE(2022,2,1)+0),'Growth Index'!E$3:E$2188)/LOOKUP(2,1/('Daily Prices'!$A$3:$A$2188<DATE(2022,1,1)),'Growth Index'!E$3:E$2188)-1,LOOKUP(2,1/('Daily Prices'!$A$3:$A$2188<DATE(2022,2,1)+0),'Growth Index'!E$3:E$2188)/100-1) -> 0.011596333 | C51: =IFERROR(LOOKUP(2,1/('Daily Prices'!$A$3:$A$2188<DATE(2022,3,1)+0),'Growth Index'!E$3:E$2188)/LOOKUP(2,1/('Daily Prices'!$A$3:$A$2188<DATE(2022,2,1)),'Growth Index'!E$3:E$2188)-1,LOOKUP(2,1/('Daily Prices'!$A$3:$A$2188<DATE(2022,3,1)+0),'Growth Index'!E$3:E$2188)/100-1) -> 0.007315226 | D51: =IFERROR(LOOKUP(2,1/('Daily Prices'!$A$3:$A$2188<DATE(2022,4,1)+0),'Growth Index'!E$3:E$2188)/LOOKUP(2,1/('Daily Prices'!$A$3:$A$2188<DATE(2022,3,1)),'Growth Index'!E$3:E$2188)-1,LOOKUP(2,1/('Daily Prices'!$A$3:$A$2188<DATE(2022,4,1)+0),'Growth Index'!E$3:E$2188)/100-1) -> 0.036069156 | E51: =IFERROR(LOOKUP(2,1/('Daily Prices'!$A$3:$A$2188<DATE(2022,5,1)+0),'Growth Index'!E$3:E$2188)/LOOKUP(2,1/('Daily Prices'!$A$3:$A$2188<DATE(2022,4,1)),'Growth Index'!E$3:E$2188)-1,LOOKUP(2,1/('Daily Prices'!$A$3:$A$2188<DATE(2022,5,1)+0),'Growth Index'!E$3:E$2188)/100-1) -> -0.0072134818 | F51: =IFERROR(LOOKUP(2,1/('Daily Prices'!$A$3:$A$2188<DATE(2022,6,1)+0),'Growth Index'!E$3:E$2188)/LOOKUP(2,1/('Daily Prices'!$A$3:$A$2188<DATE(2022,5,1)),'Growth Index'!E$3:E$2188)-1,LOOKUP(2,1/('Daily Prices'!$A$3:$A$2188<DATE(2022,6,1)+0),'Growth Index'!E$3:E$2188)/100-1) -> -0.022701045 | G51: =IFERROR(LOOKUP(2,1/('Daily Prices'!$A$3:$A$2188<DATE(2022,7,1)+0),'Growth Index'!E$3:E$2188)/LOOKUP(2,1/('Daily Prices'!$A$3:$A$2188<DATE(2022,6,1)),'Growth Index'!E$3:E$2188)-1,LOOKUP(2,1/('Daily Prices'!$A$3:$A$2188<DATE(2022,7,1)+0),'Growth Index'!E$3:E$2188)/100-1) -> -0.023186112 | H51: =IFERROR(LOOKUP(2,1/('Daily Prices'!$A$3:$A$2188<DATE(2022,8,1)+0),'Growth Index'!E$3:E$2188)/LOOKUP(2,1/('Daily Prices'!$A$3:$A$2188<DATE(2022,7,1)),'Growth Index'!E$3:E$2188)-1,LOOKUP(2,1/('Daily Prices'!$A$3:$A$2188<DATE(2022,8,1)+0),'Growth Index'!E$3:E$2188)/100-1) -> 0.040946536 | I51: =IFERROR(LOOKUP(2,1/('Daily Prices'!$A$3:$A$2188<DATE(2022,9,1)+0),'Growth Index'!E$3:E$2188)/LOOKUP(2,1/('Daily Prices'!$A$3:$A$2188<DATE(2022,8,1)),'Growth Index'!E$3:E$2188)-1,LOOKUP(2,1/('Daily Prices'!$A$3:$A$2188<DATE(2022,9,1)+0),'Growth Index'!E$3:E$2188)/100-1) -> 0.020576854 | J51: =IFERROR(LOOKUP(2,1/('Daily Prices'!$A$3:$A$2188<DATE(2022,10,1)+0),'Growth Index'!E$3:E$2188)/LOOKUP(2,1/('Daily Prices'!$A$3:$A$2188<DATE(2022,9,1)),'Growth Index'!E$3:E$2188)-1,LOOKUP(2,1/('Daily Prices'!$A$3:$A$2188<DATE(2022,10,1)+0),'Growth Index'!E$3:E$2188)/100-1) -> -0.023489125 | K51: =IFERROR(LOOKUP(2,1/('Daily Prices'!$A$3:$A$2188<DATE(2022,11,1)+0),'Growth Index'!E$3:E$2188)/LOOKUP(2,1/('Daily Prices'!$A$3:$A$2188<DATE(2022,10,1)),'Growth Index'!E$3:E$2188)-1,LOOKUP(2,1/('Daily Prices'!$A$3:$A$2188<DATE(2022,11,1)+0),'Growth Index'!E$3:E$2188)/100-1) -> 0.03605919 | L51: =IFERROR(LOOKUP(2,1/('Daily Prices'!$A$3:$A$2188<DATE(2022,12,1)+0),'Growth Index'!E$3:E$2188)/LOOKUP(2,1/('Daily Prices'!$A$3:$A$2188<DATE(2022,11,1)),'Growth Index'!E$3:E$2188)-1,LOOKUP(2,1/('Daily Prices'!$A$3:$A$2188<DATE(2022,12,1)+0),'Growth Index'!E$3:E$2188)/100-1) -> 0.045299602 | M51: =IFERROR(LOOKUP(2,1/('Daily Prices'!$A$3:$A$2188<DATE(2023,1,1)),'Growth Index'!E$3:E$2188)/LOOKUP(2,1/('Daily Prices'!$A$3:$A$2188<DATE(2022,12,1)),'Growth Index'!E$3:E$2188)-1,LOOKUP(2,1/('Daily Prices'!$A$3:$A$2188<DATE(2023,1,1)),'Growth Index'!E$3:E$2188)/100-1) -> 0.0024549314 | N51: =IFERROR(LOOKUP(2,1/('Daily Prices'!$A$3:$A$2188<DATE(2023,1,1)),'Growth Index'!E$3:E$2188)/LOOKUP(2,1/('Daily Prices'!$A$3:$A$2188<DATE(2022,1,1)),'Growth Index'!E$3:E$2188)-1,LOOKUP(2,1/('Daily Prices'!$A$3:$A$2188<DATE(2023,1,1)),'Growth Index'!E$3:E$2188)/100-1) -> 0.12693263
A52: 2023 | B52: =IFERROR(LOOKUP(2,1/('Daily Prices'!$A$3:$A$2188<DATE(2023,2,1)+0),'Growth Index'!E$3:E$2188)/LOOKUP(2,1/('Daily Prices'!$A$3:$A$2188<DATE(2023,1,1)),'Growth Index'!E$3:E$2188)-1,LOOKUP(2,1/('Daily Prices'!$A$3:$A$2188<DATE(2023,2,1)+0),'Growth Index'!E$3:E$2188)/100-1) -> 0.0085420037 | C52: =IFERROR(LOOKUP(2,1/('Daily Prices'!$A$3:$A$2188<DATE(2023,3,1)+0),'Growth Index'!E$3:E$2188)/LOOKUP(2,1/('Daily Prices'!$A$3:$A$2188<DATE(2023,2,1)),'Growth Index'!E$3:E$2188)-1,LOOKUP(2,1/('Daily Prices'!$A$3:$A$2188<DATE(2023,3,1)+0),'Growth Index'!E$3:E$2188)/100-1) -> -0.024708819 | D52: =IFERROR(LOOKUP(2,1/('Daily Prices'!$A$3:$A$2188<DATE(2023,4,1)+0),'Growth Index'!E$3:E$2188)/LOOKUP(2,1/('Daily Prices'!$A$3:$A$2188<DATE(2023,3,1)),'Growth Index'!E$3:E$2188)-1,LOOKUP(2,1/('Daily Prices'!$A$3:$A$2188<DATE(2023,4,1)+0),'Growth Index'!E$3:E$2188)/100-1) -> 0.033813112 | E52: =IFERROR(LOOKUP(2,1/('Daily Prices'!$A$3:$A$2188<DATE(2023,5,1)+0),'Growth Index'!E$3:E$2188)/LOOKUP(2,1/('Daily Prices'!$A$3:$A$2188<DATE(2023,4,1)),'Growth Index'!E$3:E$2188)-1,LOOKUP(2,1/('Daily Prices'!$A$3:$A$2188<DATE(2023,5,1)+0),'Growth Index'!E$3:E$2188)/100-1) -> 0.019827774 | F52: =IFERROR(LOOKUP(2,1/('Daily Prices'!$A$3:$A$2188<DATE(2023,6,1)+0),'Growth Index'!E$3:E$2188)/LOOKUP(2,1/('Daily Prices'!$A$3:$A$2188<DATE(2023,5,1)),'Growth Index'!E$3:E$2188)-1,LOOKUP(2,1/('Daily Prices'!$A$3:$A$2188<DATE(2023,6,1)+0),'Growth Index'!E$3:E$2188)/100-1) -> 0.018688208 | G52: =IFERROR(LOOKUP(2,1/('Daily Prices'!$A$3:$A$2188<DATE(2023,7,1)+0),'Growth Index'!E$3:E$2188)/LOOKUP(2,1/('Daily Prices'!$A$3:$A$2188<DATE(2023,6,1)),'Growth Index'!E$3:E$2188)-1,LOOKUP(2,1/('Daily Prices'!$A$3:$A$2188<DATE(2023,7,1)+0),'Growth Index'!E$3:E$2188)/100-1) -> 0.01081445 | H52: =IFERROR(LOOKUP(2,1/('Daily Prices'!$A$3:$A$2188<DATE(2023,8,1)+0),'Growth Index'!E$3:E$2188)/LOOKUP(2,1/('Daily Prices'!$A$3:$A$2188<DATE(2023,7,1)),'Growth Index'!E$3:E$2188)-1,LOOKUP(2,1/('Daily Prices'!$A$3:$A$2188<DATE(2023,8,1)+0),'Growth Index'!E$3:E$2188)/100-1) -> 0.035456917 | I52: =IFERROR(LOOKUP(2,1/('Daily Prices'!$A$3:$A$2188<DATE(2023,9,1)+0),'Growth Index'!E$3:E$2188)/LOOKUP(2,1/('Daily Prices'!$A$3:$A$2188<DATE(2023,8,1)),'Growth Index'!E$3:E$2188)-1,LOOKUP(2,1/('Daily Prices'!$A$3:$A$2188<DATE(2023,9,1)+0),'Growth Index'!E$3:E$2188)/100-1) -> -0.010793621 | J52: =IFERROR(LOOKUP(2,1/('Daily Prices'!$A$3:$A$2188<DATE(2023,10,1)+0),'Growth Index'!E$3:E$2188)/LOOKUP(2,1/('Daily Prices'!$A$3:$A$2188<DATE(2023,9,1)),'Growth Index'!E$3:E$2188)-1,LOOKUP(2,1/('Daily Prices'!$A$3:$A$2188<DATE(2023,10,1)+0),'Growth Index'!E$3:E$2188)/100-1) -> -0.0025240883 | K52: =IFERROR(LOOKUP(2,1/('Daily Prices'!$A$3:$A$2188<DATE(2023,11,1)+0),'Growth Index'!E$3:E$2188)/LOOKUP(2,1/('Daily Prices'!$A$3:$A$2188<DATE(2023,10,1)),'Growth Index'!E$3:E$2188)-1,LOOKUP(2,1/('Daily Prices'!$A$3:$A$2188<DATE(2023,11,1)+0),'Growth Index'!E$3:E$2188)/100-1) -> 0.011369228 | L52: =IFERROR(LOOKUP(2,1/('Daily Prices'!$A$3:$A$2188<DATE(2023,12,1)+0),'Growth Index'!E$3:E$2188)/LOOKUP(2,1/('Daily Prices'!$A$3:$A$2188<DATE(2023,11,1)),'Growth Index'!E$3:E$2188)-1,LOOKUP(2,1/('Daily Prices'!$A$3:$A$2188<DATE(2023,12,1)+0),'Growth Index'!E$3:E$2188)/100-1) -> 0.045414957 | M52: =IFERROR(LOOKUP(2,1/('Daily Prices'!$A$3:$A$2188<DATE(2024,1,1)),'Growth Index'!E$3:E$2188)/LOOKUP(2,1/('Daily Prices'!$A$3:$A$2188<DATE(2023,12,1)),'Growth Index'!E$3:E$2188)-1,LOOKUP(2,1/('Daily Prices'!$A$3:$A$2188<DATE(2024,1,1)),'Growth Index'!E$3:E$2188)/100-1) -> 0.053746314 | N52: =IFERROR(LOOKUP(2,1/('Daily Prices'!$A$3:$A$2188<DATE(2024,1,1)),'Growth Index'!E$3:E$2188)/LOOKUP(2,1/('Daily Prices'!$A$3:$A$2188<DATE(2023,1,1)),'Growth Index'!E$3:E$2188)-1,LOOKUP(2,1/('Daily Prices'!$A$3:$A$2188<DATE(2024,1,1)),'Growth Index'!E$3:E$2188)/100-1) -> 0.21553019
A53: 2024 | B53: =IFERROR(LOOKUP(2,1/('Daily Prices'!$A$3:$A$2188<DATE(2024,2,1)+0),'Growth Index'!E$3:E$2188)/LOOKUP(2,1/('Daily Prices'!$A$3:$A$2188<DATE(2024,1,1)),'Growth Index'!E$3:E$2188)-1,LOOKUP(2,1/('Daily Prices'!$A$3:$A$2188<DATE(2024,2,1)+0),'Growth Index'!E$3:E$2188)/100-1) -> -0.00063248178 | C53: =IFERROR(LOOKUP(2,1/('Daily Prices'!$A$3:$A$2188<DATE(2024,3,1)+0),'Growth Index'!E$3:E$2188)/LOOKUP(2,1/('Daily Prices'!$A$3:$A$2188<DATE(2024,2,1)),'Growth Index'!E$3:E$2188)-1,LOOKUP(2,1/('Daily Prices'!$A$3:$A$2188<DATE(2024,3,1)+0),'Growth Index'!E$3:E$2188)/100-1) -> 0.011103022 | D53: =IFERROR(LOOKUP(2,1/('Daily Prices'!$A$3:$A$2188<DATE(2024,4,1)+0),'Growth Index'!E$3:E$2188)/LOOKUP(2,1/('Daily Prices'!$A$3:$A$2188<DATE(2024,3,1)),'Growth Index'!E$3:E$2188)-1,LOOKUP(2,1/('Daily Prices'!$A$3:$A$2188<DATE(2024,4,1)+0),'Growth Index'!E$3:E$2188)/100-1) -> 0.043113808 | E53: =IFERROR(LOOKUP(2,1/('Daily Prices'!$A$3:$A$2188<DATE(2024,5,1)+0),'Growth Index'!E$3:E$2188)/LOOKUP(2,1/('Daily Prices'!$A$3:$A$2188<DATE(2024,4,1)),'Growth Index'!E$3:E$2188)-1,LOOKUP(2,1/('Daily Prices'!$A$3:$A$2188<DATE(2024,5,1)+0),'Growth Index'!E$3:E$2188)/100-1) -> 0.031213317 | F53: =IFERROR(LOOKUP(2,1/('Daily Prices'!$A$3:$A$2188<DATE(2024,6,1)+0),'Growth Index'!E$3:E$2188)/LOOKUP(2,1/('Daily Prices'!$A$3:$A$2188<DATE(2024,5,1)),'Growth Index'!E$3:E$2188)-1,LOOKUP(2,1/('Daily Prices'!$A$3:$A$2188<DATE(2024,6,1)+0),'Growth Index'!E$3:E$2188)/100-1) -> 0.012096234 | G53: =IFERROR(LOOKUP(2,1/('Daily Prices'!$A$3:$A$2188<DATE(2024,7,1)+0),'Growth Index'!E$3:E$2188)/LOOKUP(2,1/('Daily Prices'!$A$3:$A$2188<DATE(2024,6,1)),'Growth Index'!E$3:E$2188)-1,LOOKUP(2,1/('Daily Prices'!$A$3:$A$2188<DATE(2024,7,1)+0),'Growth Index'!E$3:E$2188)/100-1) -> 0.036881099 | H53: =IFERROR(LOOKUP(2,1/('Daily Prices'!$A$3:$A$2188<DATE(2024,8,1)+0),'Growth Index'!E$3:E$2188)/LOOKUP(2,1/('Daily Prices'!$A$3:$A$2188<DATE(2024,7,1)),'Growth Index'!E$3:E$2188)-1,LOOKUP(2,1/('Daily Prices'!$A$3:$A$2188<DATE(2024,8,1)+0),'Growth Index'!E$3:E$2188)/100-1) -> 0.038759443 | I53: =IFERROR(LOOKUP(2,1/('Daily Prices'!$A$3:$A$2188<DATE(2024,9,1)+0),'Growth Index'!E$3:E$2188)/LOOKUP(2,1/('Daily Prices'!$A$3:$A$2188<DATE(2024,8,1)),'Growth Index'!E$3:E$2188)-1,LOOKUP(2,1/('Daily Prices'!$A$3:$A$2188<DATE(2024,9,1)+0),'Growth Index'!E$3:E$2188)/100-1) -> 0.023161212 | J53: =IFERROR(LOOKUP(2,1/('Daily Prices'!$A$3:$A$2188<DATE(2024,10,1)+0),'Growth Index'!E$3:E$2188)/LOOKUP(2,1/('Daily Prices'!$A$3:$A$2188<DATE(2024,9,1)),'Growth Index'!E$3:E$2188)-1,LOOKUP(2,1/('Daily Prices'!$A$3:$A$2188<DATE(2024,10,1)+0),'Growth Index'!E$3:E$2188)/100-1) -> 0.034043661 | K53: =IFERROR(LOOKUP(2,1/('Daily Prices'!$A$3:$A$2188<DATE(2024,11,1)+0),'Growth Index'!E$3:E$2188)/LOOKUP(2,1/('Daily Prices'!$A$3:$A$2188<DATE(2024,10,1)),'Growth Index'!E$3:E$2188)-1,LOOKUP(2,1/('Daily Prices'!$A$3:$A$2188<DATE(2024,11,1)+0),'Growth Index'!E$3:E$2188)/100-1) -> -0.011632951 | L53: =IFERROR(LOOKUP(2,1/('Daily Prices'!$A$3:$A$2188<DATE(2024,12,1)+0),'Growth Index'!E$3:E$2188)/LOOKUP(2,1/('Daily Prices'!$A$3:$A$2188<DATE(2024,11,1)),'Growth Index'!E$3:E$2188)-1,LOOKUP(2,1/('Daily Prices'!$A$3:$A$2188<DATE(2024,12,1)+0),'Growth Index'!E$3:E$2188)/100-1) -> -0.0064712415 | M53: =IFERROR(LOOKUP(2,1/('Daily Prices'!$A$3:$A$2188<DATE(2025,1,1)),'Growth Index'!E$3:E$2188)/LOOKUP(2,1/('Daily Prices'!$A$3:$A$2188<DATE(2024,12,1)),'Growth Index'!E$3:E$2188)-1,LOOKUP(2,1/('Daily Prices'!$A$3:$A$2188<DATE(2025,1,1)),'Growth Index'!E$3:E$2188)/100-1) -> -0.011441878 | N53: =IFERROR(LOOKUP(2,1/('Daily Prices'!$A$3:$A$2188<DATE(2025,1,1)),'Growth Index'!E$3:E$2188)/LOOKUP(2,1/('Daily Prices'!$A$3:$A$2188<DATE(2024,1,1)),'Growth Index'!E$3:E$2188)-1,LOOKUP(2,1/('Daily Prices'!$A$3:$A$2188<DATE(2025,1,1)),'Growth Index'!E$3:E$2188)/100-1) -> 0.21688756

Sheet Investment Growth
A1: Investment Growth — Lumpsum vs SIP (with XIRR)
A2: Lumpsum uses the Assumptions amount at the start; SIP invests the monthly amount every month.
A4: Lumpsum Outcome
A5: Asset | B5: Invested (₹) | C5: Final Value (₹) | D5: Abs. Return | E5: CAGR
A6: Sensex | B6: =Assumptions!$C$6 -> 100000 | C6: ='Metrics Summary'!B29 -> 284063.97 | D6: =C6/B6-1 -> 1.8406397 | E6: ='Metrics Summary'!B8 -> 0.1100635
A7: Gold | B7: =Assumptions!$C$6 -> 100000 | C7: ='Metrics Summary'!C29 -> 292249.23 | D7: =C7/B7-1 -> 1.9224923 | E7: ='Metrics Summary'!C8 -> 0.11322183
A8: HDFC Flexi Cap | B8: =Assumptions!$C$6 -> 100000 | C8: ='Metrics Summary'!D29 -> 425314.13 | D8: =C8/B8-1 -> 3.2531413 | E8: ='Metrics Summary'!D8 -> 0.15579175
A9: Portfolio | B9: =Assumptions!$C$6 -> 100000 | C9: ='Metrics Summary'!E29 -> 352931.22 | D9: =C9/B9-1 -> 2.5293122 | E9: ='Metrics Summary'!E8 -> 0.13442687
A11: SIP Cash-Flow Schedule & XIRR (monthly investment, priced at each month-start)
A12: Contribution Date | B12: Sensex CF (₹) | C12: Gold CF (₹) | D12: HDFC CF (₹) | E12: Portfolio CF (₹)
A13: =DATE(2015,1,1) -> 42005 | B13: =-Assumptions!$C$7 -> -5000 | C13: =-Assumptions!$C$7 -> -5000 | D13: =-Assumptions!$C$7 -> -5000 | E13: =-Assumptions!$C$7 -> -5000 | G13: =Assumptions!$C$7/LOOKUP(2,1/('Daily Prices'!$A$3:$A$2188<=DATE(2015,1,1)),'Daily Prices'!B$3:B$2188) -> 0.18176834 | H13: =Assumptions!$C$7/LOOKUP(2,1/('Daily Prices'!$A$3:$A$2188<=DATE(2015,1,1)),'Daily Prices'!C$3:C$2188) -> 2.0376574 | I13: =Assumptions!$C$7/LOOKUP(2,1/('Daily Prices'!$A$3:$A$2188<=DATE(2015,1,1)),'Daily Prices'!D$3:D$2188) -> 10.495602
A14: =DATE(2015,2,1) -> 42036 | B14: =-Assumptions!$C$7 -> -5000 | C14: =-Assumptions!$C$7 -> -5000 | D14: =-Assumptions!$C$7 -> -5000 | E14: =-Assumptions!$C$7 -> -5000 | G14: =Assumptions!$C$7/LOOKUP(2,1/('Daily Prices'!$A$3:$A$2188<=DATE(2015,2,1)),'Daily Prices'!B$3:B$2188) -> 0.17133292 | H14: =Assumptions!$C$7/LOOKUP(2,1/('Daily Prices'!$A$3:$A$2188<=DATE(2015,2,1)),'Daily Prices'!C$3:C$2188) -> 1.9878013 | I14: =Assumptions!$C$7/LOOKUP(2,1/('Daily Prices'!$A$3:$A$2188<=DATE(2015,2,1)),'Daily Prices'!D$3:D$2188) -> 10.05581
A15: =DATE(2015,3,1) -> 42064 | B15: =-Assumptions!$C$7 -> -5000 | C15: =-Assumptions!$C$7 -> -5000 | D15: =-Assumptions!$C$7 -> -5000 | E15: =-Assumptions!$C$7 -> -5000 | G15: =Assumptions!$C$7/LOOKUP(2,1/('Daily Prices'!$A$3:$A$2188<=DATE(2015,3,1)),'Daily Prices'!B$3:B$2188) -> 0.17111497 | H15: =Assumptions!$C$7/LOOKUP(2,1/('Daily Prices'!$A$3:$A$2188<=DATE(2015,3,1)),'Daily Prices'!C$3:C$2188) -> 2.0769097 | I15: =Assumptions!$C$7/LOOKUP(2,1/('Daily Prices'!$A$3:$A$2188<=DATE(2015,3,1)),'Daily Prices'!D$3:D$2188) -> 10.263295
A16: =DATE(2015,4,1) -> 42095 | B16: =-Assumptions!$C$7 -> -5000 | C16: =-Assumptions!$C$7 -> -5000 | D16: =-Assumptions!$C$7 -> -5000 | E16: =-Assumptions!$C$7 -> -5000 | G16: =Assumptions!$C$7/LOOKUP(2,1/('Daily Prices'!$A$3:$A$2188<=DATE(2015,4,1)),'Daily Prices'!B$3:B$2188) -> 0.17692764 | H16: =Assumptions!$C$7/LOOKUP(2,1/('Daily Prices'!$A$3:$A$2188<=DATE(2015,4,1)),'Daily Prices'!C$3:C$2188) -> 2.0851023 | I16: =Assumptions!$C$7/LOOKUP(2,1/('Daily Prices'!$A$3:$A$2188<=DATE(2015,4,1)),'Daily Prices'!D$3:D$2188) -> 10.3748
A17: =DATE(2015,5,1) -> 42125 | B17: =-Assumptions!$C$7 -> -5000 | C17: =-Assumptions!$C$7 -> -5000 | D17: =-Assumptions!$C$7 -> -5000 | E17: =-Assumptions!$C$7 -> -5000 | G17: =Assumptions!$C$7/LOOKUP(2,1/('Daily Prices'!$A$3:$A$2188<=DATE(2015,5,1)),'Daily Prices'!B$3:B$2188) -> 0.18510765 | H17: =Assumptions!$C$7/LOOKUP(2,1/('Daily Prices'!$A$3:$A$2188<=DATE(2015,5,1)),'Daily Prices'!C$3:C$2188) -> 2.0712317 | I17: =Assumptions!$C$7/LOOKUP(2,1/('Daily Prices'!$A$3:$A$2188<=DATE(2015,5,1)),'Daily Prices'!D$3:D$2188) -> 10.690179
A18: =DATE(2015,6,1) -> 42156 | B18: =-Assumptions!$C$7 -> -5000 | C18: =-Assumptions!$C$7 -> -5000 | D18: =-Assumptions!$C$7 -> -5000 | E18: =-Assumptions!$C$7 -> -5000 | G18: =Assumptions!$C$7/LOOKUP(2,1/('Daily Prices'!$A$3:$A$2188<=DATE(2015,6,1)),'Daily Prices'!B$3:B$2188) -> 0.17953972 | H18: =Assumptions!$C$7/LOOKUP(2,1/('Daily Prices'!$A$3:$A$2188<=DATE(2015,6,1)),'Daily Prices'!C$3:C$2188) -> 2.0378793 | I18: =Assumptions!$C$7/LOOKUP(2,1/('Daily Prices'!$A$3:$A$2188<=DATE(2015,6,1)),'Daily Prices'!D$3:D$2188) -> 10.472981
A19: =DATE(2015,7,1) -> 42186 | B19: =-Assumptions!$C$7 -> -5000 | C19: =-Assumptions!$C$7 -> -5000 | D19: =-Assumptions!$C$7 -> -5000 | E19: =-Assumptions!$C$7 -> -5000 | G19: =Assumptions!$C$7/LOOKUP(2,1/('Daily Prices'!$A$3:$A$2188<=DATE(2015,7,1)),'Daily Prices'!B$3:B$2188) -> 0.17843843 | H19: =Assumptions!$C$7/LOOKUP(2,1/('Daily Prices'!$A$3:$A$2188<=DATE(2015,7,1)),'Daily Prices'!C$3:C$2188) -> 2.0940081 | I19: =Assumptions!$C$7/LOOKUP(2,1/('Daily Prices'!$A$3:$A$2188<=DATE(2015,7,1)),'Daily Prices'!D$3:D$2188) -> 10.432881
A20: =DATE(2015,8,1) -> 42217 | B20: =-Assumptions!$C$7 -> -5000 | C20: =-Assumptions!$C$7 -> -5000 | D20: =-Assumptions!$C$7 -> -5000 | E20: =-Assumptions!$C$7 -> -5000 | G20: =Assumptions!$C$7/LOOKUP(2,1/('Daily Prices'!$A$3:$A$2188<=DATE(2015,8,1)),'Daily Prices'!B$3:B$2188) -> 0.17784379 | H20: =Assumptions!$C$7/LOOKUP(2,1/('Daily Prices'!$A$3:$A$2188<=DATE(2015,8,1)),'Daily Prices'!C$3:C$2188) -> 2.2130338 | I20: =Assumptions!$C$7/LOOKUP(2,1/('Daily Prices'!$A$3:$A$2188<=DATE(2015,8,1)),'Daily Prices'!D$3:D$2188) -> 10.231644
A21: =DATE(2015,9,1) -> 42248 | B21: =-Assumptions!$C$7 -> -5000 | C21: =-Assumptions!$C$7 -> -5000 | D21: =-Assumptions!$C$7 -> -5000 | E21: =-Assumptions!$C$7 -> -5000 | G21: =Assumptions!$C$7/LOOKUP(2,1/('Daily Prices'!$A$3:$A$2188<=DATE(2015,9,1)),'Daily Prices'!B$3:B$2188) -> 0.19457948 | H21: =Assumptions!$C$7/LOOKUP(2,1/('Daily Prices'!$A$3:$A$2188<=DATE(2015,9,1)),'Daily Prices'!C$3:C$2188) -> 2.0507936 | I21: =Assumptions!$C$7/LOOKUP(2,1/('Daily Prices'!$A$3:$A$2188<=DATE(2015,9,1)),'Daily Prices'!D$3:D$2188) -> 11.239339
A22: =DATE(2015,10,1) -> 42278 | B22: =-Assumptions!$C$7 -> -5000 | C22: =-Assumptions!$C$7 -> -5000 | D22: =-Assumptions!$C$7 -> -5000 | E22: =-Assumptions!$C$7 -> -5000 | G22: =Assumptions!$C$7/LOOKUP(2,1/('Daily Prices'!$A$3:$A$2188<=DATE(2015,10,1)),'Daily Prices'!B$3:B$2188) -> 0.19068722 | H22: =Assumptions!$C$7/LOOKUP(2,1/('Daily Prices'!$A$3:$A$2188<=DATE(2015,10,1)),'Daily Prices'!C$3:C$2188) -> 2.1174204 | I22: =Assumptions!$C$7/LOOKUP(2,1/('Daily Prices'!$A$3:$A$2188<=DATE(2015,10,1)),'Daily Prices'!D$3:D$2188) -> 11.021348
A23: =DATE(2015,11,1) -> 42309 | B23: =-Assumptions!$C$7 -> -5000 | C23: =-Assumptions!$C$7 -> -5000 | D23: =-Assumptions!$C$7 -> -5000 | E23: =-Assumptions!$C$7 -> -5000 | G23: =Assumptions!$C$7/LOOKUP(2,1/('Daily Prices'!$A$3:$A$2188<=DATE(2015,11,1)),'Daily Prices'!B$3:B$2188) -> 0.18756919 | H23: =Assumptions!$C$7/LOOKUP(2,1/('Daily Prices'!$A$3:$A$2188<=DATE(2015,11,1)),'Daily Prices'!C$3:C$2188) -> 2.081274 | I23: =Assumptions!$C$7/LOOKUP(2,1/('Daily Prices'!$A$3:$A$2188<=DATE(2015,11,1)),'Daily Prices'!D$3:D$2188) -> 10.866187
A24: =DATE(2015,12,1) -> 42339 | B24: =-Assumptions!$C$7 -> -5000 | C24: =-Assumptions!$C$7 -> -5000 | D24: =-Assumptions!$C$7 -> -5000 | E24: =-Assumptions!$C$7 -> -5000 | G24: =Assumptions!$C$7/LOOKUP(2,1/('Daily Prices'!$A$3:$A$2188<=DATE(2015,12,1)),'Daily Prices'!B$3:B$2188) -> 0.19106277 | H24: =Assumptions!$C$7/LOOKUP(2,1/('Daily Prices'!$A$3:$A$2188<=DATE(2015,12,1)),'Daily Prices'!C$3:C$2188) -> 2.1958218 | I24: =Assumptions!$C$7/LOOKUP(2,1/('Daily Prices'!$A$3:$A$2188<=DATE(2015,12,1)),'Daily Prices'!D$3:D$2188) -> 10.783043
A25: =DATE(2016,1,1) -> 42370 | B25: =-Assumptions!$C$7 -> -5000 | C25: =-Assumptions!$C$7 -> -5000 | D25: =-Assumptions!$C$7 -> -5000 | E25: =-Assumptions!$C$7 -> -5000 | G25: =Assumptions!$C$7/LOOKUP(2,1/('Daily Prices'!$A$3:$A$2188<=DATE(2016,1,1)),'Daily Prices'!B$3:B$2188) -> 0.19112492 | H25: =Assumptions!$C$7/LOOKUP(2,1/('Daily Prices'!$A$3:$A$2188<=DATE(2016,1,1)),'Daily Prices'!C$3:C$2188) -> 2.2078784 | I25: =Assumptions!$C$7/LOOKUP(2,1/('Daily Prices'!$A$3:$A$2188<=DATE(2016,1,1)),'Daily Prices'!D$3:D$2188) -> 10.918056
A26: =DATE(2016,2,1) -> 42401 | B26: =-Assumptions!$C$7 -> -5000 | C26: =-Assumptions!$C$7 -> -5000 | D26: =-Assumptions!$C$7 -> -5000 | E26: =-Assumptions!$C$7 -> -5000 | G26: =Assumptions!$C$7/LOOKUP(2,1/('Daily Prices'!$A$3:$A$2188<=DATE(2016,2,1)),'Daily Prices'!B$3:B$2188) -> 0.20103986 | H26: =Assumptions!$C$7/LOOKUP(2,1/('Daily Prices'!$A$3:$A$2188<=DATE(2016,2,1)),'Daily Prices'!C$3:C$2188) -> 2.0608206 | I26: =Assumptions!$C$7/LOOKUP(2,1/('Daily Prices'!$A$3:$A$2188<=DATE(2016,2,1)),'Daily Prices'!D$3:D$2188) -> 12.039084
A27: =DATE(2016,3,1) -> 42430 | B27: =-Assumptions!$C$7 -> -5000 | C27: =-Assumptions!$C$7 -> -5000 | D27: =-Assumptions!$C$7 -> -5000 | E27: =-Assumptions!$C$7 -> -5000 | G27: =Assumptions!$C$7/LOOKUP(2,1/('Daily Prices'!$A$3:$A$2188<=DATE(2016,3,1)),'Daily Prices'!B$3:B$2188) -> 0.2173724 | H27: =Assumptions!$C$7/LOOKUP(2,1/('Daily Prices'!$A$3:$A$2188<=DATE(2016,3,1)),'Daily Prices'!C$3:C$2188) -> 1.8460389 | I27: =Assumptions!$C$7/LOOKUP(2,1/('Daily Prices'!$A$3:$A$2188<=DATE(2016,3,1)),'Daily Prices'!D$3:D$2188) -> 13.534364
A28: =DATE(2016,4,1) -> 42461 | B28: =-Assumptions!$C$7 -> -5000 | C28: =-Assumptions!$C$7 -> -5000 | D28: =-Assumptions!$C$7 -> -5000 | E28: =-Assumptions!$C$7 -> -5000 | G28: =Assumptions!$C$7/LOOKUP(2,1/('Daily Prices'!$A$3:$A$2188<=DATE(2016,4,1)),'Daily Prices'!B$3:B$2188) -> 0.1978659 | H28: =Assumptions!$C$7/LOOKUP(2,1/('Daily Prices'!$A$3:$A$2188<=DATE(2016,4,1)),'Daily Prices'!C$3:C$2188) -> 1.9352986 | I28: =Assumptions!$C$7/LOOKUP(2,1/('Daily Prices'!$A$3:$A$2188<=DATE(2016,4,1)),'Daily Prices'!D$3:D$2188) -> 11.19337
A29: =DATE(2016,5,1) -> 42491 | B29: =-Assumptions!$C$7 -> -5000 | C29: =-Assumptions!$C$7 -> -5000 | D29: =-Assumptions!$C$7 -> -5000 | E29: =-Assumptions!$C$7 -> -5000 | G29: =Assumptions!$C$7/LOOKUP(2,1/('Daily Prices'!$A$3:$A$2188<=DATE(2016,5,1)),'Daily Prices'!B$3:B$2188) -> 0.19526201 | H29: =Assumptions!$C$7/LOOKUP(2,1/('Daily Prices'!$A$3:$A$2188<=DATE(2016,5,1)),'Daily Prices'!C$3:C$2188) -> 1.8209889 | I29: =Assumptions!$C$7/LOOKUP(2,1/('Daily Prices'!$A$3:$A$2188<=DATE(2016,5,1)),'Daily Prices'!D$3:D$2188) -> 11.376927
A30: =DATE(2016,6,1) -> 42522 | B30: =-Assumptions!$C$7 -> -5000 | C30: =-Assumptions!$C$7 -> -5000 | D30: =-Assumptions!$C$7 -> -5000 | E30: =-Assumptions!$C$7 -> -5000 | G30: =Assumptions!$C$7/LOOKUP(2,1/('Daily Prices'!$A$3:$A$2188<=DATE(2016,6,1)),'Daily Prices'!B$3:B$2188) -> 0.18716827 | H30: =Assumptions!$C$7/LOOKUP(2,1/('Daily Prices'!$A$3:$A$2188<=DATE(2016,6,1)),'Daily Prices'!C$3:C$2188) -> 1.8979547 | I30: =Assumptions!$C$7/LOOKUP(2,1/('Daily Prices'!$A$3:$A$2188<=DATE(2016,6,1)),'Daily Prices'!D$3:D$2188) -> 11.243737
A31: =DATE(2016,7,1) -> 42552 | B31: =-Assumptions!$C$7 -> -5000 | C31: =-Assumptions!$C$7 -> -5000 | D31: =-Assumptions!$C$7 -> -5000 | E31: =-Assumptions!$C$7 -> -5000 | G31: =Assumptions!$C$7/LOOKUP(2,1/('Daily Prices'!$A$3:$A$2188<=DATE(2016,7,1)),'Daily Prices'!B$3:B$2188) -> 0.1841966 | H31: =Assumptions!$C$7/LOOKUP(2,1/('Daily Prices'!$A$3:$A$2188<=DATE(2016,7,1)),'Daily Prices'!C$3:C$2188) -> 1.7265681 | I31: =Assumptions!$C$7/LOOKUP(2,1/('Daily Prices'!$A$3:$A$2188<=DATE(2016,7,1)),'Daily Prices'!D$3:D$2188) -> 10.544445
A32: =DATE(2016,8,1) -> 42583 | B32: =-Assumptions!$C$7 -> -5000 | C32: =-Assumptions!$C$7 -> -5000 | D32: =-Assumptions!$C$7 -> -5000 | E32: =-Assumptions!$C$7 -> -5000 | G32: =Assumptions!$C$7/LOOKUP(2,1/('Daily Prices'!$A$3:$A$2188<=DATE(2016,8,1)),'Daily Prices'!B$3:B$2188) -> 0.17855153 | H32: =Assumptions!$C$7/LOOKUP(2,1/('Daily Prices'!$A$3:$A$2188<=DATE(2016,8,1)),'Daily Prices'!C$3:C$2188) -> 1.7270956 | I32: =Assumptions!$C$7/LOOKUP(2,1/('Daily Prices'!$A$3:$A$2188<=DATE(2016,8,1)),'Daily Prices'!D$3:D$2188) -> 10.021364
A33: =DATE(2016,9,1) -> 42614 | B33: =-Assumptions!$C$7 -> -5000 | C33: =-Assumptions!$C$7 -> -5000 | D33: =-Assumptions!$C$7 -> -5000 | E33: =-Assumptions!$C$7 -> -5000 | G33: =Assumptions!$C$7/LOOKUP(2,1/('Daily Prices'!$A$3:$A$2188<=DATE(2016,9,1)),'Daily Prices'!B$3:B$2188) -> 0.17573352 | H33: =Assumptions!$C$7/LOOKUP(2,1/('Daily Prices'!$A$3:$A$2188<=DATE(2016,9,1)),'Daily Prices'!C$3:C$2188) -> 1.7741747 | I33: =Assumptions!$C$7/LOOKUP(2,1/('Daily Prices'!$A$3:$A$2188<=DATE(2016,9,1)),'Daily Prices'!D$3:D$2188) -> 9.748489
A34: =DATE(2016,10,1) -> 42644 | B34: =-Assumptions!$C$7 -> -5000 | C34: =-Assumptions!$C$7 -> -5000 | D34: =-Assumptions!$C$7 -> -5000 | E34: =-Assumptions!$C$7 -> -5000 | G34: =Assumptions!$C$7/LOOKUP(2,1/('Daily Prices'!$A$3:$A$2188<=DATE(2016,10,1)),'Daily Prices'!B$3:B$2188) -> 0.17943039 | H34: =Assumptions!$C$7/LOOKUP(2,1/('Daily Prices'!$A$3:$A$2188<=DATE(2016,10,1)),'Daily Prices'!C$3:C$2188) -> 1.7648664 | I34: =Assumptions!$C$7/LOOKUP(2,1/('Daily Prices'!$A$3:$A$2188<=DATE(2016,10,1)),'Daily Prices'!D$3:D$2188) -> 9.7519875
A35: =DATE(2016,11,1) -> 42675 | B35: =-Assumptions!$C$7 -> -5000 | C35: =-Assumptions!$C$7 -> -5000 | D35: =-Assumptions!$C$7 -> -5000 | E35: =-Assumptions!$C$7 -> -5000 | G35: =Assumptions!$C$7/LOOKUP(2,1/('Daily Prices'!$A$3:$A$2188<=DATE(2016,11,1)),'Daily Prices'!B$3:B$2188) -> 0.17936184 | H35: =Assumptions!$C$7/LOOKUP(2,1/('Daily Prices'!$A$3:$A$2188<=DATE(2016,11,1)),'Daily Prices'!C$3:C$2188) -> 1.8087866 | I35: =Assumptions!$C$7/LOOKUP(2,1/('Daily Prices'!$A$3:$A$2188<=DATE(2016,11,1)),'Daily Prices'!D$3:D$2188) -> 9.6544815
A36: =DATE(2016,12,1) -> 42705 | B36: =-Assumptions!$C$7 -> -5000 | C36: =-Assumptions!$C$7 -> -5000 | D36: =-Assumptions!$C$7 -> -5000 | E36: =-Assumptions!$C$7 -> -5000 | G36: =Assumptions!$C$7/LOOKUP(2,1/('Daily Prices'!$A$3:$A$2188<=DATE(2016,12,1)),'Daily Prices'!B$3:B$2188) -> 0.18825358 | H36: =Assumptions!$C$7/LOOKUP(2,1/('Daily Prices'!$A$3:$A$2188<=DATE(2016,12,1)),'Daily Prices'!C$3:C$2188) -> 1.9613849 | I36: =Assumptions!$C$7/LOOKUP(2,1/('Daily Prices'!$A$3:$A$2188<=DATE(2016,12,1)),'Daily Prices'!D$3:D$2188) -> 10.032042
A37: =DATE(2017,1,1) -> 42736 | B37: =-Assumptions!$C$7 -> -5000 | C37: =-Assumptions!$C$7 -> -5000 | D37: =-Assumptions!$C$7 -> -5000 | E37: =-Assumptions!$C$7 -> -5000 | G37: =Assumptions!$C$7/LOOKUP(2,1/('Daily Prices'!$A$3:$A$2188<=DATE(2017,1,1)),'Daily Prices'!B$3:B$2188) -> 0.18778313 | H37: =Assumptions!$C$7/LOOKUP(2,1/('Daily Prices'!$A$3:$A$2188<=DATE(2017,1,1)),'Daily Prices'!C$3:C$2188) -> 1.9972255 | I37: =Assumptions!$C$7/LOOKUP(2,1/('Daily Prices'!$A$3:$A$2188<=DATE(2017,1,1)),'Daily Prices'!D$3:D$2188) -> 10.171615
A38: =DATE(2017,2,1) -> 42767 | B38: =-Assumptions!$C$7 -> -5000 | C38: =-Assumptions!$C$7 -> -5000 | D38: =-Assumptions!$C$7 -> -5000 | E38: =-Assumptions!$C$7 -> -5000 | G38: =Assumptions!$C$7/LOOKUP(2,1/('Daily Prices'!$A$3:$A$2188<=DATE(2017,2,1)),'Daily Prices'!B$3:B$2188) -> 0.17767266 | H38: =Assumptions!$C$7/LOOKUP(2,1/('Daily Prices'!$A$3:$A$2188<=DATE(2017,2,1)),'Daily Prices'!C$3:C$2188) -> 1.91724 | I38: =Assumptions!$C$7/LOOKUP(2,1/('Daily Prices'!$A$3:$A$2188<=DATE(2017,2,1)),'Daily Prices'!D$3:D$2188) -> 9.4536612
A39: =DATE(2017,3,1) -> 42795 | B39: =-Assumptions!$C$7 -> -5000 | C39: =-Assumptions!$C$7 -> -5000 | D39: =-Assumptions!$C$7 -> -5000 | E39: =-Assumptions!$C$7 -> -5000 | G39: =Assumptions!$C$7/LOOKUP(2,1/('Daily Prices'!$A$3:$A$2188<=DATE(2017,3,1)),'Daily Prices'!B$3:B$2188) -> 0.17250605 | H39: =Assumptions!$C$7/LOOKUP(2,1/('Daily Prices'!$A$3:$A$2188<=DATE(2017,3,1)),'Daily Prices'!C$3:C$2188) -> 1.8791501 | I39: =Assumptions!$C$7/LOOKUP(2,1/('Daily Prices'!$A$3:$A$2188<=DATE(2017,3,1)),'Daily Prices'!D$3:D$2188) -> 9.2655019
